Workbook

Sheet 1_search_string
A1: population | B1: intervention | C1: outcome | D1: study_methods
A2: *forest* | B2: logging | C2: rut* | D2: remote sensing
A3: AND | B3: cut* | C3: wheel rut* | D3: Earth observation
A4: soil* | B4: clearcut* | C4: wheel-rut* | D4: satellite
A5: AND NOT | B5: clear-cut* | C5: skid trail* | D5: image*
A6: crop* | B6: cutblock* | C6: skidder* | D6: drone
A7: agri* | B7: timber | C7: feller* | D7: uav
B8: salvage | C8: degradation | D8: unmanned aerial vehicle
B9: forestry | C9: disturbance | D9: aerial
B10: wood extraction | C10: compaction | D10: photogrammetr*
B11: harvest | C11: erosion | D11: stereoscop*
B12: select* cut* | C12: vegetation recovery | D12: lidar
B13: select* log* | C13: vegetation disturbance | D13: optical
B14: silvicultur* | C14: slash | D14: radar
B15: high*grading | C15: wood*slash | D15: sensor
B16: block cut* | C16: drainage | D16: *spectral
B17: blowdown | C17: runoff | D17: ndvi
B18: windthrow | C18: windrow* | D18: vegetation index
B19: windsnap | C19: scalping | D19: nbr
... B22: pest* | C22: moisture | D22: digital elevation model
B23: fire*
B24: burn*
A32: ( *forest* AND NOT crop* OR urban OR maize OR wheat OR rice OR corn OR cotton OR grape OR cereal OR agri*) AND (logging OR cut* OR clearcut* OR clear*cut* OR cutblock* OR timber OR salvage OR forestry OR "wood extraction" OR harvest OR "select* cut*" OR "select* log*" OR silvicultur* OR high*grading OR "block cut*" OR blowdown OR windthrow OR windsnap OR insect* OR disease* OR pest* OR fire* OR burn*) AND ( rut* OR "wheel rut*" OR wheel-rut* OR "skid trail*" OR skidder* OR feller* OR soil* OR "soil disturbance" OR compaction OR "soil compaction" OR erosion OR "soil erosion" OR "vegetation recovery" OR "vegetation disturbance" OR slash OR "wood*slash" OR drainage OR runoff OR windrow* OR scalping OR slumping OR "soil nutrient*" OR "soil moisture" ) AND ( "remote sensing" OR "Earth observation" OR "satellite" OR "image*" OR "drone" OR uav OR "unmanned aerial vehicle" OR aerial OR photogrammetr* OR stereoscop* OR lidar OR optical OR radar OR sensor OR *spectral OR ndvi OR "vegetation index" OR nbr OR "normali*ed burn ratio" OR dem OR "digital elevation model" )

Sheet 2_dbase_list
A1: database | B1: roses_diagram_source | C1: date | D1: url | E1: n_results | F1: n_within_dbase_dupes_removed | G1: n_merged_dbase_dupes_removed | H1: search_string
A2: Scopus | B2: database search | C2: 45713 | D2: https://www.scopus.com/search/form.uri#basic | E2: 2588 | F2: 2584 | G2: 2232 | H2: TITLE-ABS-KEY ( ( *forest* AND soil* AND NOT crop* OR agri*) AND ( logging OR cut* OR clearcut* OR clear*cut* OR cutblock* OR timber OR salvage OR forestry OR "wood extraction" OR harvest OR "select* cut*" OR "select* log*" OR silvicultur* OR high*grading OR "block cut*" OR blowdown OR windthrow OR windsnap OR insect* OR disease* OR pest* OR fire* OR burn* ) AND ( rut* OR "wheel rut*" OR wheel-rut* OR "skid trail*" OR skidder* OR feller* OR degradation OR disturbance OR compaction OR erosion OR "vegetation recovery" OR "vegetation disturbance" OR slash OR "wood*slash" OR drainage OR runoff OR windrow* OR scalping OR slumping OR nutrient* OR moisture ) AND ( "remote sensing" OR "Earth observation" OR "satellite" OR "image*" OR "drone" OR uav OR "unmanned aerial vehicle" OR aerial OR photogrammetr* OR stereoscop* OR lidar OR optical OR radar OR sensor OR *spectral OR ndvi OR "vegetation index" OR nbr OR "normali*ed burn ratio" OR dem OR "digital elevation model" ) ) AND ( LIMIT-TO ( LANGUAGE , "English" ) OR LIMIT-TO ( LANGUAGE , "French" ) ) AND ( LIMIT-TO ( DOCTYPE , "ar" ) OR LIMIT-TO ( DOCTYPE , "cp" ) OR LIMIT-TO ( DOCTYPE , "re" ) OR LIMIT-TO ( DOCTYPE , "ch" ) OR LIMIT-TO ( DOCTYPE , "le" ) OR LIMIT-TO ( DOCTYPE , "bk" ) OR LIMIT-TO ( DOCTYPE , "rp" ) )
A3: EBSCOhost | B3: database search | C3: 45714 | D3: https://research.ebsco.com/ | E3: 486 | F3: 485 | G3: 159 | H3: (TI ((*forest* AND soil*) AND (logging OR cut* OR clearcut* OR clear*cut* OR cutblock* OR timber OR salvage OR forestry OR "wood extraction" OR harvest OR "select* cut*" OR "select* log*" OR silvicultur* OR high*grading OR "block cut*" OR blowdown OR windthrow OR windsnap OR insect* OR disease* OR pest* OR fire* OR burn*) AND (rut* OR "wheel rut*" OR wheel-rut* OR "skid trail*" OR skidder* OR feller* OR degradation OR disturbance OR compaction OR erosion OR "vegetation recovery" OR "vegetation disturbance" OR slash OR "wood*slash" OR drainage OR runoff OR windrow* OR scalping OR slumping OR nutrient* OR moisture) AND ("remote sensing" OR "Earth observation" OR "satellite" OR "image*" OR "drone" OR uav OR "unmanned aerial vehicle" OR aerial OR photogrammetr* OR stereoscop* OR lidar OR optical OR radar OR sensor OR *spectral OR ndvi OR "vegetation index" OR nbr OR "normali*ed burn ratio" OR dem OR "digital elevation model"))) OR (AB ((*forest* AND soil*) AND (logging OR cut* OR clearcut* OR clear*cut* OR cutblock* OR timber OR salvage OR forestry OR "wood extraction" OR harvest OR "select* cut*" OR "select* log*" OR silvicultur* OR high*grading OR "block cut*" OR blowdown OR windthrow OR windsnap OR insect* OR disease* OR pest* OR fire* OR burn*) AND (rut* OR "wheel rut*" OR wheel-rut* OR "skid trail*" OR skidder* OR feller* OR degradation OR disturbance OR compaction OR erosion OR "vegetation recovery" OR "vegetation disturbance" OR slash OR "wood*slash" OR drainage OR runoff OR windrow* OR scalping OR slumping OR nutrient* OR moisture) AND ("remote sensing" OR "Earth observation" OR "satellite" OR "image*" OR "drone" OR uav OR "unmanned aerial vehicle" OR aerial OR photogrammetr* OR stereoscop* OR lidar OR optical OR radar OR sensor OR *spectral OR ndvi OR "vegetation index" OR nbr OR "normali*ed burn ratio" OR dem OR "digital elevation model"))) OR (SU ((*forest* AND soil*) AND (logging OR cut* OR clearcut* OR clear*cut* OR cutblock* OR timber OR salvage OR forestry OR "wood extraction" OR harvest OR "select* cut*" OR "select* log*" OR silvicultur* OR high*grading OR "block cut*" OR blowdown OR windthrow OR windsnap OR insect* OR disease* OR pest* OR fire* OR burn*) AND (rut* OR "wheel rut*" OR wheel-rut* OR "skid trail*" OR skidder* OR feller* OR degradation OR disturbance OR compaction OR erosion OR "vegetation recovery" OR "vegetation disturbance" OR slash OR "wood*slash" OR drainage OR runoff OR windrow* OR scalping OR slumping OR nutrient* OR moisture) AND ("remote sensing" OR "Earth observation" OR "satellite" OR "image*" OR "drone" OR uav OR "unmanned aerial vehicle" OR aerial OR photogrammetr* OR stereoscop* OR lidar OR optical OR radar OR sensor OR *spectral OR ndvi OR "vegetation index" OR nbr OR "normali*ed burn ratio" OR dem OR "digital elevation model")))
A4: OpenAlex | B4: database search | C4: 45714 | D4: https://openalex.org/ | E4: 1431 | F4: 1381 | G4: 781 | H4: title & abstract INCLUDE ( *forest* AND soil* AND NOT crop* OR agri* ) AND ( logging OR cut* OR clearcut* OR clear*cut* OR cutblock* OR timber OR salvage OR forestry OR "wood extraction" OR harvest OR "select* cut*" OR "select* log*" OR silvicultur* OR high*grading OR "block cut*" OR blowdown OR windthrow OR windsnap OR insect* OR disease* OR pest* OR fire* OR burn* ) AND ( rut* OR "wheel rut*" OR wheel-rut* OR "skid trail*" OR skidder* OR feller* OR degradation OR disturbance OR compaction OR erosion OR "vegetation recovery" OR "vegetation disturbance" OR slash OR "wood*slash" OR drainage OR runoff OR windrow* OR scalping OR slumping OR nutrient* OR moisture ) AND ( "remote sensing" OR "Earth observation" OR "satellite" OR "image*" OR "drone" OR uav OR "unmanned aerial vehicle" OR aerial OR photogrammetr* OR stereoscop* OR lidar OR optical OR radar OR sensor OR *spectral OR ndvi OR "vegetation index" OR nbr OR "normali*ed burn ratio" OR dem OR "digital elevation model" ), type IS NOT "dataset", type IS NOT "peer-review", type IS NOT "reference-entry", type IS NOT "paratext"
A5: Google Scholar | B5: database search | C5: 45713 | D5: https://scholar.google.ca/ | E5: 300 | F5: 299 | G5: 42 | H5: KEYWORDS (*forest* AND soil*) AND (log* OR *cut* OR harvest* OR timber OR fire OR insect* OR windthrow) AND (degradation OR disturbance OR erosion OR compaction OR *rut*) AND "remote sensing"
A6: OSTR | B6: database search | C6: 45713 | D6: https://ostrnrcan-dostrncan.canada.ca/home | E6: 71 | F6: 67 | G6: 29 | H6: dc.description.abstract: ( *forest* AND soil* ) AND ( logging OR cut* OR clearcut* OR clear*cut* OR cutblock* OR timber OR salvage OR forestry OR "wood extraction" OR harvest OR "select* cut*" OR "select* log*" OR silvicultur* OR high*grading OR "block cut*" OR blowdown OR windthrow OR windsnap OR insect* OR disease* OR pest* OR fire* OR burn* ) AND ( rut* OR "wheel rut*" OR wheel-rut* OR "skid trail*" OR skidder* OR feller* OR degradation OR disturbance OR compaction OR erosion OR "vegetation recovery" OR "vegetation disturbance" OR slash OR "wood*slash" OR drainage OR runoff OR windrow* OR scalping OR slumping OR nutrient* OR moisture ) AND ( "remote sensing" OR "Earth observation" OR "satellite" OR "image*" OR "drone" OR uav OR "unmanned aerial vehicle" OR aerial OR photogrammetr* OR stereoscop* OR lidar OR optical OR radar OR sensor OR *spectral OR ndvi OR "vegetation index" OR nbr OR "normali*ed burn ratio" OR dem OR "digital elevation model" )
A7: MFFP | B7: other search | C7: 45713 | D7: https://mffp.gouv.qc.ca/le-ministere/publications | E7: 0 | H7: remote sensing forest soil degradation
A8: MNRF | B8: other search | E8: 0
A9: USDA Forest Service | B9: other search | C9: 45735 | D9: https://research.fs.usda.gov/treesearch | E9: 15 | F9: 15 | G9: 13 | H9: remote sensing forest soil
D10: RECORDS IDENTIFIED THROUGH DBASE SEARCH | E10: =SUM(E2:E5) -> 4805 | F10: =SUM(F2:F5) -> 4749 | G10: =SUM(G2:G5) -> 3214
D11: RECORDS IDENTIFIED THROUGH OTHER SOURCES | E11: =SUM(E6:E9) -> 86 | F11: =SUM(F6:F9) -> 82 | G11: =SUM(G6:G9) -> 42
D12: TOTAL | E12: =SUM(E2:E9) -> 4891 | F12: =SUM(F2:F9) -> 4831 | G12: =SUM(G2:G9) -> 3256
D13: NUMBER OF DUPLICATES REMOVED | G13: =E10-G12 -> 1549
G20: =(E10-F10)+(E11-F11) -> 60
G21: =E12-G12 -> 1635

Sheet 3_screening
A1: study_id | B1: first_author | C1: authors | D1: year | E1: title | F1: source | G1: type | H1: doi | I1: link_url | J1: dbase | K1: select_on_title_abs | L1: text_retrievable | M1: select_on_full_text | N1: excluded_reason | O1: notes
A2: Sclifó Zucon_Pedreira_Vargas_etal_2022 | B2: Sclifó Zucon | C2: SclifÃ³ Zucon A.R.; Pedreira G.Q.; Vargas Motta A.C.; Gotz L.F.; Maeda S.; Martins Bassaco M.V.; Magri E.; Prior S.A.; de Paula Souza L.C.; de Oliveira Junior J.C. | D2: 2022 | E2: Piling Secondary Subtropical Forest Residue: Long-Term Impacts on Soil, Trees, and Weeds | F2: Forests | G2: article | H2: https://doi.org/10.3390/f13081183 | I2: https://www.scopus.com/inward/record.uri?eid=2-s2.0-85137560174&doi=10.3390%2ff13081183&partnerID=40&md5=cbbea97332b60567fab1888abf0e36ef | J2: Scopus | K2: keep | L2: yes | M2: drop | N2: population | O2: Use of UAV derived NDVI to evaluate vegetation regrowth as an indocator of soil recovery after piling residues, subtropical, was initially screened in but closer review of paper reveals this is an intensive tree plantation with added fertilizer treatments etc... so removed
A3: Conrad-Rooney_Barker_Pasquarella_etal_2021 | B3: Conrad-Rooney | C3: Conrad-Rooney E.; Barker Plotkin A.; Pasquarella V.J.; Elkinton J.; Chandler J.L.; Matthes J.H. | D3: 2021 | E3: Defoliation severity is positively related to soil solution nitrogen availability and negatively related to soil nitrogen concentrations following a multi-year invasive insect irruption | F3: AoB PLANTS | G3: article | H3: https://doi.org/10.1093/aobpla/plaa059 | I3: https://www.scopus.com/inward/record.uri?eid=2-s2.0-85099435960&doi=10.1093%2faobpla%2fplaa059&partnerID=40&md5=93c8bf37f28030b7dcfef8e743258eb6 | J3: Scopus | K3: keep | L3: yes | M3: keep | O3: Link between RS defoliation and in-situ soil nutrients, mainly N
A4: Sewell_Quideau_Dyck_etal_2020 | B4: Sewell | C4: Sewell P.D.; Quideau S.A.; Dyck M.; Macdonald E. | D4: 2020 | E4: Long-term effects of harvest on boreal forest soils in relation to a remote sensing-based soil moisture index | F4: Forest Ecology and Management | G4: article | H4: https://doi.org/10.1016/j.foreco.2020.117986 | I4: https://www.scopus.com/inward/record.uri?eid=2-s2.0-85079405075&doi=10.1016%2fj.foreco.2020.117986&partnerID=40&md5=a9c22c5e4316cb706282e584fb8f1094 | J4: Scopus | K4: keep | L4: yes | M4: keep | O4: Uses LiDAR to compute depth to water table and comapre with in-situ soil C and minerals in harvested and non-harvested forest stands
A5: Mohieddinne_Brasseur_Spicher_etal_2019 | B5: Mohieddinne | C5: Mohieddinne H.; Brasseur B.; Spicher F.; Gallet-Moron E.; Buridant J.; Kobaissi A.; Horen H. | D5: 2019 | E5: Physical recovery of forest soil after compaction by heavy machines, revealed by penetration resistance over multiple decades | F5: Forest Ecology and Management | G5: article | H5: https://doi.org/10.1016/j.foreco.2019.117472 | I5: https://www.scopus.com/inward/record.uri?eid=2-s2.0-85069650177&doi=10.1016%2fj.foreco.2019.117472&partnerID=40&md5=fc9e63bc82d557235b81804f4dbf61b8 | J5: Scopus | K5: keep | L5: yes | M5: keep | O5: LiDAR used solely to identify machine trails then perfrom in-situ measurement of soil compaction with penetrometer
A6: Lewis_Robichaud_Hudak_etal_2012 | B6: Lewis | C6: Sarah A. Lewis, Peter R. Robichaud, Andrew T. Hudak, Brian Austin, Robert J. Liebermann | D6: 2012 | E6: Utility of remotely sensed imagery for assessing the impact of salvage logging after forest fires | F6: Remote Sensing | G6: article | H6: https://doi.org/10.3390/rs4072112 | I6: https://research.fs.usda.gov/treesearch/41111 | J6: USFSTreesearch | K6: keep | L6: yes | M6: keep
A7: Morgan_Keane_Dillon_etal_2014 | B7: Morgan | C7: Penelope Morgan, Robert E. Keane, Gregory K. Dillon, Theresa B. Jain, Andrew T. Hudak, Eva C. Karau, Pamela G. Sikkink, Zachery A. Holden, Eva K. Strand | D7: 2014 | E7: Challenges of assessing fire and burn severity using field measures, remote sensing and modelling | F7: International Journal of Wildland Fire | G7: article | H7: https://doi.org/10.1071/WF13058 | I7: https://research.fs.usda.gov/treesearch/47843 | J7: USFSTreesearch | K7: keep | L7: yes | M7: keep
A8: Sikkink | B8: Sikkink | C8: Pamela G. Sikkink | D8: 2015 | E8: Comparison of six fire severity classification methods using Montana and Washington wildland fires | F8: USDA Forest Service Proceedings | G8: conference-paper | I8: https://research.fs.usda.gov/treesearch/49447 | J8: USFSTreesearch | K8: keep | L8: yes | M8: keep | O8: Directly relates RS burn severity indicators to CBI and soil burn index
A9: Lewis_Hudak_Robichaud_etal_2017 | B9: Lewis | C9: Sarah A. Lewis, Andrew T. Hudak, Peter R. Robichaud, Penelope Morgan, Kevin L. Satterberg, Eva K. Strand, Alistair M. S. Smith, Joseph A. Zamudio, Leigh B. Lentile | D9: 2017 | E9: Indicators of burn severity at extended temporal scales: a decade of ecosystem response in mixed-conifer forests of western Montana | F9: International Journal of Wildland Fire | G9: article | H9: https://doi.org/10.1071/WF17019 | I9: https://research.fs.usda.gov/treesearch/55517 | J9: USFSTreesearch | K9: keep | L9: yes | M9: keep | O9: RS burn indices correllated to field plots for spectral unmixing analysis, including soil endmembers
A10: Lewis_Robichaud_Elliot_etal_2004 | B10: Lewis | C10: Sarah A. Lewis, Peter R. Robichaud, William J. Elliot, Bruce E. Frazier, Joan Q. Wu | D10: 2004 | E10: Hyperspectral remote sensing of postfire soil properties | F10: American Society of Photogrammetry and Remote Sensing Conference Proceedings | G10: conference-paper | I10: https://research.fs.usda.gov/treesearch/23527 | J10: USFSTreesearch | K10: keep | L10: yes | M10: keep
A11: Hudak_Robichaud_Jain_etal_2004 | B11: Hudak | C11: Andrew Hudak, Pete Robichaud, Terrie Jain, Penelope Morgan, Carter Stone, Jess Clark | D11: 2004 | E11: The relationship of field burn severity measures to satellite-derived Burned Area Reflectance Classification (BARC) maps | F11: American Society of Photogrammetry and Remote Sensing Conference Proceedings | G11: conference-paper | I11: https://research.fs.usda.gov/treesearch/26195 | J11: USFSTreesearch | K11: keep | L11: yes | M11: keep | O11: Post-fire RS indices correlated to field measurement including soil indicators
A12: Hudak_Robichaud_Evans_etal_2004 | B12: Hudak | C12: Andrew T. Hudak, Peter R. Robichaud, Jeffery B. Evans, Jess Clark, Keith Lannom, Penelope Morgan, Carter Stone | D12: 2004 | E12: Field validation of Burned Area Reflectance Classification (BARC) products for post fire assessment | F12: American Society of Photogrammetry and Remote Sensing Conference Proceedings | G12: conference-paper | I12: https://research.fs.usda.gov/treesearch/23530 | J12: USFSTreesearch | K12: keep | L12: yes | M12: keep | O12: Post-fire RS indices correlated to field measurement including soil indicators
A13: Hudak_Morgan_Bobbitt_etal_2007 | B13: Hudak | C13: Andrew T. Hudak, Penelope Morgan, Michael J. Bobbitt, Allstair M. S. Smith, Sarah A. Lewis, Leigh B. Lentile, Peter R. Robichaud, Jess T. Clark, Randy A. McKinley | D13: 2007 | E13: The relationship of multispectral satellite imagery to immediate fire effects | F13: Fire Ecology | G13: article | H13: https://doi.org/10.4996/fireecology.0301064 | I13: https://research.fs.usda.gov/treesearch/29489 | J13: USFSTreesearch | K13: keep | L13: yes | M13: keep
A14: Verbyla_Lord_2008 | B14: Verbyla | C14: D. Verbyla, R. Lord | D14: 2008 | E14: Estimating post-fire organic soil depth in the Alaskan boreal forest using the Normalized Burn Ratio | F14: International Journal of Remote Sensing | G14: article | H14: https://doi.org/10.1080101431160701802497 | I14: https://research.fs.usda.gov/treesearch/35232 | J14: USFSTreesearch | K14: keep | L14: yes | M14: keep | O14: Post-fire NBR compared to in-situ organic soil depth
A15: Melander_Ritala_2018 | B15: Melander | C15: Lari Melander;Risto Ritala | D15: 2018 | E15: Time-of-flight imaging for assessing soil deformations and improving forestry vehicle tracking accuracy | F15: International Journal of Forest Engineering | G15: article | H15: https://doi.org/10.1080/14942119.2018.1421341 | I15: https://doi.org/10.1080/14942119.2018.1421341 | J15: OpenAlex | K15: keep | L15: yes | M15: keep | O15: Measure vehicle position and estimates rut depth in near real time using vehicle mounted sensors and software, in-situ rut depth measurements
A16: Lee_Elliott_Tiansawat_2023 | B16: Lee | C16: Lee K.; Elliott S.; Tiansawat P. | D16: 2023 | E16: Use of Drone RGB Imagery to Quantify Indicator Variables of Tropical-Forest-Ecosystem Degradation and Restoration | F16: Forests | G16: article | H16: https://doi.org/10.3390/f14030586 | I16: https://www.scopus.com/inward/record.uri?eid=2-s2.0-85151317509&doi=10.3390%2ff14030586&partnerID=40&md5=2c35118cf95a3946c8bb43f1c60d8a8f | J16: Scopus | K16: keep | L16: yes | M16: keep | O16: RS estimates of forest degradation, ground-truthing with ground plots including indicators of vegetation structure and bare soil/rock
A17: Robichaud_Lewis_Brown_etal_2020 | B17: Robichaud | C17: Robichaud, Peter R. ; Lewis, Sarah A. ; Brown, Robert E. ; Bone, Edwin D. ; Brooks, Erin S. | D17: 2020 | E17: Evaluating post-wildfire logging-slash cover treatment to reduce hillslope erosion after salvage logging using ground measurements and remote sensing | F17: Hydrological Processes | G17: analytic | H17: https://doi.org/10.1002/hyp.13882 | I17: https://research.ebsco.com/linkprocessor/plink?id=d3c53c39-0c96-3d2a-8bd7-33d879808112 | J17: EBSCOhost | K17: keep | L17: yes | M17: keep
A18: Giannetti_Chirici_Travaglini_etal_2017 | B18: Giannetti | C18: Giannetti, Francesca ; Chirici, Gherardo ; Travaglini, Davide ; Bottalico, Francesca ; Marchi, Enrico ; Cambi, Martina | D18: 2017 | E18: Assessment of soil disturbance caused by forest operations by means of portable laser scanner and soil physical parameters | F18: Soil Science Society of America Journal | G18: analytic | H18: https://doi.org/10.2136/sssaj2017.02.0051 | I18: https://research.ebsco.com/linkprocessor/plink?id=4378dfed-f1dc-38de-9046-ad9e964e6f49 | J18: EBSCOhost | K18: keep | L18: yes | M18: keep
A19: Bourgeau-Chavez_Kasischke_Riordan_etal_2007 | B19: Bourgeau-Chavez | C19: Laura Bourgeau-Chavez;Eric S. Kasischke;K. Riordan;S. Brunzell;M. C. Nolan;E. J. Hyer;J. Slawski;MÃ¡rta Medvecz;T.B. Walters;S. Ames | D19: 2007 | E19: Remote monitoring of spatial and temporal surface soil moisture in fire disturbed boreal forest ecosystems with ERS SAR imagery | F19: International Journal of Remote Sensing | G19: article | H19: https://doi.org/10.1080/01431160600976061 | I19: https://doi.org/10.1080/01431160600976061 | J19: OpenAlex | K19: keep | L19: yes | M19: keep | O19: RS radar soil moisture post-fire
A20: Salmivaara_Miettinen_Finér_etal_2018 | B20: Salmivaara | C20: Aura Salmivaara;Mikko Miettinen;Leena Finér;Samuli Launiainen;Heikki Korpunen;Sakari Tuominen;Jukka Heikkonen;Paavo Nevalainen;Matti SirÃ¨n;Jari Ala-IlomÃ¤ki;Jori Uusitalo | D20: 2018 | E20: Wheel rut measurements by forest machine-mounted LiDAR sensors – accuracy and potential for operational applications? | F20: International Journal of Forest Engineering | G20: article | H20: https://doi.org/10.1080/14942119.2018.1419677 | I20: https://doi.org/10.1080/14942119.2018.1419677 | J20: OpenAlex | K20: keep | L20: yes | M20: keep
A21: Beltrán-Marcos_Suárez-Seoane_Fernández-Guisuraga_etal_2021 | B21: Beltràn-Marcos | C21: David BeltrÃ¡n-Marcos;Susana SuÃ¡rez-Seoane;JosÃ© Manuel FernÃ¡ndez-Guisuraga;Victor FernÃ¡ndez-GarcÃ­a;Rayo Pinto;Paula GarcÃ­a-Llamas;Leonor Calvo | D21: 2021 | E21: Mapping Soil Burn Severity at Very High Spatial Resolution from Unmanned Aerial Vehicles | F21: Forests | G21: article | H21: https://doi.org/10.3390/f12020179 | I21: https://doi.org/10.3390/f12020179 | J21: OpenAlex | K21: keep | L21: yes | M21: keep
A22: French_Kasischke_Bourgeau-Chavez_etal_1996 | B22: French | C22: Nancy H. F. French;Eric S. Kasischke;Laura Bourgeau-Chavez;Peter Harrell | D22: 1996 | E22: Sensitivity of ERS-1 SAR to variations in soil water in fire-disturbed boreal forest ecosystems | F22: International Journal of Remote Sensing | G22: article | H22: https://doi.org/10.1080/01431169608949126 | I22: https://doi.org/10.1080/01431169608949126 | J22: OpenAlex | K22: keep | L22: yes | M22: keep | O22: RS radar to estimate soil moisture post-fire
A23: Bhatnagar_Puliti_Talbot_etal_2022 | B23: Bhatnagar | C23: Saheba Bhatnagar;Stefano Puliti;Bruce Talbot;Joachim B. Heppelmann;Johannes Breidenbach;Rasmus Astrup | D23: 2022 | E23: Mapping wheel-ruts from timber harvesting operations using deep learning techniques in drone imagery | F23: Forestry An International Journal of Forest Research | G23: article | H23: https://doi.org/10.1093/forestry/cpac023 | I23: https://doi.org/10.1093/forestry/cpac023 | J23: OpenAlex | K23: keep | L23: yes | M23: keep
A24: Heppelmann_Talbot_Antòn-Fernández_etal_2022 | B24: Heppelmann | C24: Joachim B. Heppelmann;Bruce Talbot;Clara AntÃ³n-FernÃ¡ndez;Rasmus Astrup | D24: 2022 | E24: Depth-to-water maps as predictors of rut severity in fully mechanized harvesting operations | F24: International Journal of Forest Engineering | G24: article | H24: https://doi.org/10.1080/14942119.2022.2044724 | I24: https://doi.org/10.1080/14942119.2022.2044724 | J24: OpenAlex | K24: keep | L24: yes | M24: keep
A25: Rengers_Tucker_Moody_etal_2016 | B25: Rengers | C25: Francis K. Rengers;Gregory E. Tucker;John A. Moody;Brian A. Ebel | D25: 2016 | E25: Illuminating wildfire erosion and deposition patterns with repeat terrestrial lidar | F25: Journal of Geophysical Research Earth Surface | G25: article | H25: https://doi.org/10.1002/2015jf003600 | I25: https://doi.org/10.1002/2015jf003600 | J25: OpenAlex | K25: keep | L25: yes | M25: keep
A26: McNeil_Beurs_Eshleman_etal_2007 | B26: McNeil | C26: Brenden E. McNeil;Kirsten M. de Beurs;Keith N. Eshleman;Jane R. Foster;Philip A. Townsend | D26: 2007 | E26: Maintenance of ecosystem nitrogen limitation by ephemeral forest disturbance: An assessment using MODIS, Hyperion, and Landsat ETM+ | F26: Geophysical Research Letters | G26: article | H26: https://doi.org/10.1029/2007gl031387 | I26: https://doi.org/10.1029/2007gl031387 | J26: OpenAlex | K26: keep | L26: yes | M26: keep | O26: RS indicators of N limitation/availability in soil
A27: Guilinger_Foufoula-Georgiou_Gray_etal_2023 | B27: Guilinger | C27: James Guilinger;Efi Foufoula-Georgiou;Andrew B. Gray;James T. Randerson;Padhraic Smyth;Nicolas C. Barth;Michael L. Goulden | D27: 2023 | E27: Predicting Postfire Sediment Yields of Small Steep Catchments Using Airborne Lidar Differencing | F27: Geophysical Research Letters | G27: article | H27: https://doi.org/10.1029/2023gl104626 | I27: https://doi.org/10.1029/2023gl104626 | J27: OpenAlex | K27: keep | L27: yes | M27: keep | O27: Uses LiDAR to map out pre- and post-fire differences and estimate soil erosion
A28: Mohieddinne_Brasseur_Gallet-Moron_etal_2022 | B28: Mohieddinne | C28: Hamza Mohieddinne;Boris Brasseur;Emilie Gallet-Moron;Jonathan Lenoir;Fabien Spicher;Ahmad Kobaissi;HÃ©lÃ¨ne Horen | D28: 2022 | E28: Assessment of soil compaction and rutting in managed forests through an airborne <scp>LiDAR</scp> technique | F28: Land Degradation and Development | G28: article | H28: https://doi.org/10.1002/ldr.4553 | I28: https://doi.org/10.1002/ldr.4553 | J28: OpenAlex | K28: keep | L28: yes | M28: keep
A29: Marquì­nez_Wozniak_Fernández_etal_2008 | B29: Marquì­nez | C29: J. Marquì­nez;Edyta Wozniak;Susana Fernández;Ricardo Martì­nez | D29: 2008 | E29: Analysis of the evolution of soil erosion classes using multitemporal Landsat imagery | F29: International Journal of Wildland Fire | G29: article | H29: https://doi.org/10.1071/wf06138 | I29: https://doi.org/10.1071/wf06138 | J29: OpenAlex | K29: keep | L29: yes | M29: keep
A30: Kubiak_Spiralski_Pompeu_etal_2024 | B30: Kubiak | C30: Katarzyna Kubiak;Marcin Spiralski;JoÃ£o Pompeu;Vincent Levavasseur;RafaÅ‚ Wawer | D30: 2024 | E30: Advances in Remote Sensing for Monitoring Soil Conditions in Forest Ecosystems: Techniques, Challenges, and Applications | F30: Transactions of the Institute of Aviation | G30: article | H30: https://doi.org/10.2478/tar-2024-0019 | I30: https://doi.org/10.2478/tar-2024-0019 | J30: OpenAlex | K30: keep | L30: yes | M30: keep
A31: Latterini_Venanzi_Tocci_etal_2020 | B31: Latterini | C31: Francesco Latterini;Rachele Venanzi;Damiano Tocci;Federico Moschetti;Rodolfo Picchio | D31: 2020 | E31: Comparing Accuracy of Three Remote Sensing Methods to Evaluate Soil Impact Related to Forest Operations | F31: NA | G31: article | H31: https://doi.org/10.3390/iecf2020-07954 | I31: https://doi.org/10.3390/iecf2020-07954 | J31: OpenAlex | K31: keep | L31: yes | M31: keep
A32: Dubé_Berch_2013 | B32: Dubé | C32: Stephane DubÃ©;Shannon M. Berch | D32: 2013 | E32: Monitoring soil disturbance on salvaged areas within the mountain pine beetle infestation using digital imagery | F32: Journal of Applied Remote Sensing | G32: article | H32: https://doi.org/10.1117/1.jrs.7.073541 | I32: https://doi.org/10.1117/1.jrs.7.073541 | J32: OpenAlex | K32: keep | L32: yes | M32: keep | O32: Review
A33: Baur_Friend_Pellegrini_2024 | B33: Baur | C33: Baur M.J.; Friend A.D.; Pellegrini A.F.A. | D33: 2024 | E33: Widespread and systematic effects of fire on plantâ€“soil water relations | F33: Nature Geoscience | G33: article | H33: https://doi.org/10.1038/s41561-024-01563-6 | I33: https://www.scopus.com/inward/record.uri?eid=2-s2.0-85208926269&doi=10.1038%2fs41561-024-01563-6&partnerID=40&md5=7da423dfb2749435e3deab079f6aafdd | J33: Scopus | K33: keep | L33: yes | M33: keep | O33: Using RS to investigate post-fire changes in soil and plant moisture.
A34: Llorens_Sobrino_Fernández_etal_2024 | B34: Llorens | C34: Llorens R.; Sobrino J.A.; FernÃ¡ndez C.; FernÃ¡ndez-Alonso J.M.; Vega J.A. | D34: 2024 | E34: Soil Burn Severity Assessment Using Sentinel-2 and Radiometric Measurements | F34: Fire | G34: article | H34: https://doi.org/10.3390/fire7120487 | I34: https://www.scopus.com/inward/record.uri?eid=2-s2.0-85213458686&doi=10.3390%2ffire7120487&partnerID=40&md5=9e96b2376d83f126c38f6d1144225aff | J34: Scopus | K34: keep | L34: yes | M34: keep | O34: correlation soil burns with S2
A35: Godziek_2024 | B35: Godziek | C35: Godziek J. | D35: 2024 | E35: Root plates of uprooted trees âˆ’ Automatic detection and biotransport estimation using LiDAR data and field mapping | F35: International Journal of Applied Earth Observation and Geoinformation | G35: article | H35: https://doi.org/10.1016/j.jag.2024.103992 | I35: https://www.scopus.com/inward/record.uri?eid=2-s2.0-85196815799&doi=10.1016%2fj.jag.2024.103992&partnerID=40&md5=88629a03095eeabeae591081345757d2 | J35: Scopus | K35: keep | L35: yes | M35: keep | O35: RS detection of root plates (likely from windthrow)
A36: Kadakci Koca_Küçükuysal_Gül_etal_2024 | B36: Kadakci | C36: Kadakci Koca T.; KÃ¼Ã§Ã¼kuysal C.; GÃ¼l M.; Esetlili T. | D36: 2024 | E36: A comprehensive approach to soil burn severity mapping for erosion susceptibility assessment | F36: Catena | G36: article | H36: https://doi.org/10.1016/j.catena.2024.108302 | I36: https://www.scopus.com/inward/record.uri?eid=2-s2.0-85201004093&doi=10.1016%2fj.catena.2024.108302&partnerID=40&md5=276b36f6a250d5e83dc24389fcbc81c9 | J36: Scopus | K36: keep | L36: yes | M36: keep
A37: Kim_Seo_Woo_etal_2025 | B37: Kim | C37: Kim I.; Seo J.; Woo H.; Choi B. | D37: 2025 | E37: Assessing Rutting and Soil Compaction Caused by Wood Extraction Using Traditional and Remote Sensing Methods | F37: Forests | G37: article | H37: https://doi.org/10.3390/f16010086 | I37: https://www.scopus.com/inward/record.uri?eid=2-s2.0-85216026180&doi=10.3390%2ff16010086&partnerID=40&md5=362110f118dc038a9b299cc7affe6419 | J37: Scopus | K37: keep | L37: yes | M37: keep
A38: Lewis_Robichaud_Archer_etal_2023 | B38: Lewis | C38: Lewis S.A.; Robichaud P.R.; Archer V.A.; Hudak A.T.; Eitel J.U.H.; Strand E.K. | D38: 2023 | E38: Informing Sustainable Forest Management: Remote Sensing Strategies for Assessing Soil Disturbance after Wildfire and Salvage Logging | F38: Forests | G38: article | H38: https://doi.org/10.3390/f14112218 | I38: https://www.scopus.com/inward/record.uri?eid=2-s2.0-85178337764&doi=10.3390%2ff14112218&partnerID=40&md5=bca91638a589bee8468b5679b483373a | J38: Scopus | K38: keep | L38: yes | M38: keep
A39: Venanzi_Latterini_Civitarese_etal_2023 | B39: Venanzi | C39: Venanzi R.; Latterini F.; Civitarese V.; Picchio R. | D39: 2023 | E39: Recent Applications of Smart Technologies for Monitoring the Sustainability of Forest Operations | F39: Forests | G39: review | H39: https://doi.org/10.3390/f14071503 | I39: https://www.scopus.com/inward/record.uri?eid=2-s2.0-85166181566&doi=10.3390%2ff14071503&partnerID=40&md5=8dc574b1c5c817ef837ae882709648a5 | J39: Scopus | K39: keep | L39: yes | M39: keep | O39: Review of RS in sustainable forestry, including methods for assessing rutthing and soil degradation
A40: Kim_Kim_Ha_etal_2023 | B40: Kim | C40: Kim J.; Kim I.; Ha E.; Choi B. | D40: 2023 | E40: UAV Photogrammetry for Soil Surface Deformation Detection in a Timber Harvesting Area, South Korea | F40: Forests | G40: article | H40: https://doi.org/10.3390/f14050980 | I40: https://www.scopus.com/inward/record.uri?eid=2-s2.0-85160741835&doi=10.3390%2ff14050980&partnerID=40&md5=e773b08423b8124135f0d3c63e38f6bf | J40: Scopus | K40: keep | L40: yes | M40: keep
A41: Beltrán-Marcos_Suárez-Seoane_Fernández-Guisuraga_etal_2023 | B41: Beltrán-Marcos | C41: BeltrÃ¡n-Marcos D.; SuÃ¡rez-Seoane S.; FernÃ¡ndez-Guisuraga J.M.; FernÃ¡ndez-GarcÃ­a V.; Marcos E.; Calvo L. | D41: 2023 | E41: Relevance of UAV and sentinel-2 data fusion for estimating topsoil organic carbon after forest fire | F41: Geoderma | G41: article | H41: https://doi.org/10.1016/j.geoderma.2022.116290 | I41: https://www.scopus.com/inward/record.uri?eid=2-s2.0-85143547946&doi=10.1016%2fj.geoderma.2022.116290&partnerID=40&md5=f1b894a19e66acf6192a77b0d72f1b43 | J41: Scopus | K41: keep | L41: yes | M41: keep
A42: Fernández-Guisuraga_Marcos_Suárez-Seoane_etal_2022 | B42: Fernández-Guisuraga | C42: FernÃ¡ndez-Guisuraga J.M.; Marcos E.; SuÃ¡rez-Seoane S.; Calvo L. | D42: 2022 | E42: ALOS-2 L-band SAR backscatter data improves the estimation and temporal transferability of wildfire effects on soil properties under different post-fire vegetation responses | F42: Science of the Total Environment | G42: article | H42: https://doi.org/10.1016/j.scitotenv.2022.156852 | I42: https://www.scopus.com/inward/record.uri?eid=2-s2.0-85132935489&doi=10.1016%2fj.scitotenv.2022.156852&partnerID=40&md5=8277b1e9c58f8fccde560a535798fd36 | J42: Scopus | K42: keep | L42: yes | M42: keep | O42: Direct comparison of radar with soil mineral properties (C, N, P) post-burn and during recovery
A43: Tomljanović_Kolar_Đuka_etal_2022 | B43: Tomljanović | C43: Tomljanović K.; Kolar A.; Đuka A.; FranjeviÄ‡ M.; JurjeviÄ‡ L.; Matak I.; UgarkoviÄ‡ D.; BalenoviÄ‡ I. | D43: 2022 | E43: Application of UAS for Monitoring of Forest Ecosystems: A Review of Experience and Knowledge | F43: Croatian Journal of Forest Engineering | G43: article | H43: https://doi.org/10.5552/crojfe.2022.1727 | I43: https://www.scopus.com/inward/record.uri?eid=2-s2.0-85135446876&doi=10.5552%2fcrojfe.2022.1727&partnerID=40&md5=a9d0a471cc40358cc5e3aa32d89cd720 | J43: Scopus | K43: keep | L43: yes | M43: keep | O43: Review of UAS applications in forestry, including soil disturbances
A44: Marra_Laschi_Fabiano_etal_2022 | B44: Marra | C44: Marra E.; Laschi A.; Fabiano F.; Foderi C.; Neri F.; Mastrolonardo G.; Nordfjell T.; Marchi E. | D44: 2022 | E44: Impacts of wood extraction on soil: assessing rutting and soil compaction caused by skidding and forwarding by means of traditional and innovative methods | F44: European Journal of Forest Research | G44: article | H44: https://doi.org/10.1007/s10342-021-01420-w | I44: https://www.scopus.com/inward/record.uri?eid=2-s2.0-85119186195&doi=10.1007%2fs10342-021-01420-w&partnerID=40&md5=232f9047e4b1b12e76469724df96b79d | J44: Scopus | K44: keep | L44: yes | M44: keep
A45: Ferenčík_Dudáková_Kardoš_etal_2022 | B45: Ferenčík | C45: Ferenčík M.; Dudáková Z.; Kardoš M.; Sivák M.; Merganičová K.; Merganič J. | D45: 2022 | E45: Measuring Soil Surface Changes after Traffic of Various Wheeled Skidders with Close-Range Photogrammetry | F45: Forests | G45: article | H45: https://doi.org/10.3390/f13070976 | I45: https://www.scopus.com/inward/record.uri?eid=2-s2.0-85133207229&doi=10.3390%2ff13070976&partnerID=40&md5=c2ff3a85d6fa42a7df3976555097eb58 | J45: Scopus | K45: keep | L45: yes | M45: keep
A46: Fernández_Fernández-Alonso_Vega_etal_2021 | B46: Fernández | C46: FernÃ¡ndez C.; FernÃ¡ndez-Alonso J.M.; Vega J.A.; FontÃºrbel T.; Llorens R.; Sobrino J.A. | D46: 2021 | E46: Exploring the use of spectral indices to assess alterations in soil properties in pine stands affected by crown fire in Spain | F46: Fire Ecology | G46: article | H46: https://doi.org/10.1186/s42408-020-00089-7 | I46: https://www.scopus.com/inward/record.uri?eid=2-s2.0-85100187139&doi=10.1186%2fs42408-020-00089-7&partnerID=40&md5=8f895d1dec6d0cfa5bbb4326bccb76de | J46: Scopus | K46: keep | L46: yes | M46: keep | O46: Direct realtion between RS soil indices with soil burn severity in-situ
A47: Deligiannakis_Pallikarakis_Papanikolaou_etal_2021 | B47: Deligiannakis | C47: Deligiannakis G.; Pallikarakis A.; Papanikolaou I.; Alexiou S.; Reicherter K. | D47: 2021 | E47: Detecting and monitoring early post-fire sliding phenomena using uavâ€“sfm photogrammetry and t-lidar-derived point clouds | F47: Fire | G47: article | H47: https://doi.org/10.3390/fire4040087 | I47: https://www.scopus.com/inward/record.uri?eid=2-s2.0-85120166359&doi=10.3390%2ffire4040087&partnerID=40&md5=ebd04af5e35df3b196faa5b8c867d5b9 | J47: Scopus | K47: keep | L47: yes | M47: keep
A48: Talbot_Astrup_2021 | B48: Talbot | C48: Talbot B.; Astrup R. | D48: 2021 | E48: A review of sensors, sensor-platforms and methods used in 3D modelling of soil displacement after timber harvesting | F48: Croatian Journal of Forest Engineering | G48: review | H48: https://doi.org/10.5552/crojfe.2021.837 | I48: https://www.scopus.com/inward/record.uri?eid=2-s2.0-85097566395&doi=10.5552%2fcrojfe.2021.837&partnerID=40&md5=a19ec449d86c67601e6e6383f452f237 | J48: Scopus | K48: keep | L48: yes | M48: keep
A49: Marra_Wictorsson_Bohlin_etal_2021 | B49: Marra | C49: Marra E.; Wictorsson R.; Bohlin J.; Marchi E.; Nordfjell T. | D49: 2021 | E49: Remote measuring of the depth of wheel ruts in forest terrain using a drone | F49: International Journal of Forest Engineering | G49: article | H49: https://doi.org/10.1080/14942119.2021.1916228 | I49: https://www.scopus.com/inward/record.uri?eid=2-s2.0-85137999337&doi=10.1080%2f14942119.2021.1916228&partnerID=40&md5=5f5a066a331202018f9ab4d449a2d370 | J49: Scopus | K49: keep | L49: yes | M49: keep
A50: Efthimiou_Psomiadis_Panagos_2020 | B50: Efthimiou | C50: Efthimiou N.; Psomiadis E.; Panagos P. | D50: 2020 | E50: Fire severity and soil erosion susceptibility mapping using multi-temporal Earth Observation data: The case of Mati fatal wildfire in Eastern Attica, Greece | F50: Catena | G50: article | H50: https://doi.org/10.1016/j.catena.2019.104320 | I50: https://www.scopus.com/inward/record.uri?eid=2-s2.0-85075449602&doi=10.1016%2fj.catena.2019.104320&partnerID=40&md5=10cb7fefefb257272b02f822979c1af1 | J50: Scopus | K50: keep | L50: yes | M50: drop | N50: study design | O50: RUSLE simulation without any in-situ soil erosion indicators
A51: Xu_Hu_Guan_etal_2019 | B51: Xu | C51: Xu H.; Hu X.; Guan H.; Zhang B.; Wang M.; Chen S.; Chen M. | D51: 2019 | E51: A remote sensing based method to detect soil erosion in forests | F51: Remote Sensing | G51: article | H51: https://doi.org/10.3390/rs11050513 | I51: https://www.scopus.com/inward/record.uri?eid=2-s2.0-85062936206&doi=10.3390%2frs11050513&partnerID=40&md5=0621ba437988c8ec2b79d7523cabdfc1 | J51: Scopus | K51: keep | L51: yes | M51: drop | N51: intervention | O51: No intervention
A52: Marra_Cambi_Fernandez-Lacruz_etal_2018 | B52: Marra | C52: Marra E.; Cambi M.; Fernandez-Lacruz R.; Giannetti F.; Marchi E.; Nordfjell T. | D52: 2018 | E52: Photogrammetric estimation of wheel rut dimensions and soil compaction after increasing numbers of forwarder passes | F52: Scandinavian Journal of Forest Research | G52: review | H52: https://doi.org/10.1080/02827581.2018.1427789 | I52: https://www.scopus.com/inward/record.uri?eid=2-s2.0-85041541415&doi=10.1080%2f02827581.2018.1427789&partnerID=40&md5=0868e39f070377d79627a7d5d80d82cb | J52: Scopus | K52: keep | L52: yes | M52: keep
A53: Dąbek_Żmuda_Szczepański_etal_2018 | B53: Dąbek | C53: Dąbek P.B.; Żmuda R.;Szczepański J.; Ćmielewski B. | D53: 2018 | E53: Evaluation of water soil erosion processes in forest areas in the Western Sudetes using terrestrial laser scanning and GIS tools | F53: E3S Web of Conferences | G53: conference-paper | H53: https://doi.org/10.1051/e3sconf/20184400026 | I53: https://www.scopus.com/inward/record.uri?eid=2-s2.0-85051076068&doi=10.1051%2fe3sconf%2f20184400026&partnerID=40&md5=29beab9867d45df5817ff86be78d2a83 | J53: Scopus | K53: keep | L53: yes | M53: keep
A54: Talbot_Rahlf_Astrup_2018 | B54: Talbot | C54: Talbot B.; Rahlf J.; Astrup R. | D54: 2018 | E54: An operational UAV-based approach for stand-level assessment of soil disturbance after forest harvesting | F54: Scandinavian Journal of Forest Research | G54: article | H54: https://doi.org/10.1080/02827581.2017.1418421 | I54: https://www.scopus.com/inward/record.uri?eid=2-s2.0-85040973273&doi=10.1080%2f02827581.2017.1418421&partnerID=40&md5=566edada02915d5fe6d6363eb53859c0 | J54: Scopus | K54: keep | L54: yes | M54: keep
A55: Chasmer_Hopkinson_Petrone_etal_2017 | B55: Chasmer | C55: Chasmer L.E.; Hopkinson C.D.; Petrone R.M.; Sitar M. | D55: 2017 | E55: Using Multitemporal and Multispectral Airborne Lidar to Assess Depth of Peat Loss and Correspondence With a New Active Normalized Burn Ratio for Wildfires | F55: Geophysical Research Letters | G55: article | H55: https://doi.org/10.1002/2017GL075488 | I55: https://www.scopus.com/inward/record.uri?eid=2-s2.0-85040089813&doi=10.1002%2f2017GL075488&partnerID=40&md5=fd7de5a5a4e602489ddd29f51ab8213e | J55: Scopus | K55: keep | L55: yes | M55: keep | O55: RS metrics directly compared to soil loss (burn depth) in peatland forests
A56: Niemi_Vastaranta_Vauhkonen_etal_2017 | B56: Niemi | C56: Niemi M.T.; Vastaranta M.; Vauhkonen J.; Melkas T.; Holopainen M. | D56: 2017 | E56: Airborne LiDAR-derived elevation data in terrain trafficability mapping | F56: Scandinavian Journal of Forest Research | G56: article | H56: https://doi.org/10.1080/02827581.2017.1296181 | I56: https://www.scopus.com/inward/record.uri?eid=2-s2.0-85014538878&doi=10.1080%2f02827581.2017.1296181&partnerID=40&md5=bef030870b3e1e70062514ecc08ecaad | J56: Scopus | K56: keep | L56: yes | M56: keep
A57: Cambi_Giannetti_Bottalico_etal_2018 | B57: Cambi | C57: Cambi M.; Giannetti F.; Bottalico F.; Travaglini D.; Nordfjell T.; Chirici G.; Marchi E. | D57: 2018 | E57: Estimating machine impact on strip roads via close-range photogrammetry and soil parameters: A case study in central Italy | F57: IForest | G57: article | H57: https://doi.org/10.3832/ifor2590-010 | I57: https://www.scopus.com/inward/record.uri?eid=2-s2.0-85042373493&doi=10.3832%2fifor2590-010&partnerID=40&md5=036b72451714e07d37c137769d2b2a64 | J57: Scopus | K57: keep | L57: yes | M57: keep
A58: Affek_Zachwatowicz_Sosnowska_etal_2017 | B58: Affek | C58: Affek A.N.; Zachwatowicz M.; Sosnowska A.; GerlÃ©e A.; Kiszka K. | D58: 2017 | E58: Impacts of modern mechanised skidding on the natural and cultural heritage of the Polish Carpathian Mountains | F58: Forest Ecology and Management | G58: article | H58: https://doi.org/10.1016/j.foreco.2017.09.047 | I58: https://www.scopus.com/inward/record.uri?eid=2-s2.0-85030472101&doi=10.1016%2fj.foreco.2017.09.047&partnerID=40&md5=19ad50c4bc2f2318a4b70c90f20ec59b | J58: Scopus | K58: keep | L58: yes | M58: keep
A59: Melendy_Hagen_Sullivan_etal_2018 | B59: Melendy | C59: Melendy L.; Hagen S.C.; Sullivan F.B.; Pearson T.R.H.; Walker S.M.; Ellis P.; Kustiyo; Sambodo A.K.; Roswintiarti O.; Hanson M.A.; Klassen A.W.; Palace M.W.; Braswell B.H.; Delgado G.M. | D59: 2018 | E59: Automated method for measuring the extent of selective logging damage with airborne LiDAR data | F59: ISPRS Journal of Photogrammetry and Remote Sensing | G59: article | H59: https://doi.org/10.1016/j.isprsjprs.2018.02.022 | I59: https://www.scopus.com/inward/record.uri?eid=2-s2.0-85044441285&doi=10.1016%2fj.isprsjprs.2018.02.022&partnerID=40&md5=068999a846f5b8cf16be79b20c029f84 | J59: Scopus | K59: keep | L59: yes | M59: keep
A60: Martinis_Caspard_Plank_etal_2017 | B60: Martinis | C60: Martinis S.; Caspard M.; Plank S.; Clandillon S.; Haouet S. | D60: 2017 | E60: Mapping burn scars, fire severity and soil erosion susceptibility in Southern France using multisensoral satellite data | F60: International Geoscience and Remote Sensing Symposium (IGARSS) | G60: conference-paper | H60: https://doi.org/10.1109/IGARSS.2017.8127148 | I60: https://www.scopus.com/inward/record.uri?eid=2-s2.0-85041858852&doi=10.1109%2fIGARSS.2017.8127148&partnerID=40&md5=adee875af7dfa0933d9de6559ea42c56 | J60: Scopus | K60: keep | L60: request | M60: drop | N60: study design | O60: Requested via NRCan Library 25-06-30; dropped due to no in-situ comparison (Maisy)
A61: Pierzchała_Talbot_Astrup_2016 | B61: Pierzchała | C61: Pierzchała M.; Talbot B.; Astrup R. | D61: 2016 | E61: Measuring wheel ruts with close-range photogrammetry | F61: Forestry | G61: article | H61: https://doi.org/10.1093/forestry/cpw009 | I61: https://www.scopus.com/inward/record.uri?eid=2-s2.0-84984831766&doi=10.1093%2fforestry%2fcpw009&partnerID=40&md5=edf3ecc33280fda69547e065233ab9e8 | J61: Scopus | K61: keep | L61: yes | M61: keep | O61: RS for assessing rutting
A62: Haas_Hagge_Schack-Kirchner_etal_2016 | B62: Haas | C62: Haas J.; Hagge EllhÃ¶ft K.; Schack-Kirchner H.; Lang F. | D62: 2016 | E62: Using photogrammetry to assess rutting caused by a forwarder-A comparison of different tires and bogie tracks | F62: Soil and Tillage Research | G62: article | H62: https://doi.org/10.1016/j.still.2016.04.008 | I62: https://www.scopus.com/inward/record.uri?eid=2-s2.0-84968750687&doi=10.1016%2fj.still.2016.04.008&partnerID=40&md5=f953793acffae37ad9cc2ac67e5765ee | J62: Scopus | K62: keep | L62: yes | M62: keep | O62: RS for assessing rutting
A63: Mallinis_Maris_Kalinderis_etal_2009 | B63: Mallinis | C63: Mallinis G.; Maris F.; Kalinderis I.; Koutsias N. | D63: 2009 | E63: Assessment of post-fire soil erosion risk in fire-affected watersheds using remote sensing and GIS | F63: GIScience and Remote Sensing | G63: article | H63: https://doi.org/10.2747/1548-1603.46.4.388 | I63: https://www.scopus.com/inward/record.uri?eid=2-s2.0-76149124511&doi=10.2747%2f1548-1603.46.4.388&partnerID=40&md5=d4f4c28e0aa746ee30262b840eb0a841 | J63: Scopus | K63: keep | L63: yes | M63: keep | O63: Post-fire erosion model with RS inputs, uses "risk assessment", but contains post-intervention measurements of outcomes
A64: Kokaly_Rockwell_Haire_etal_2007 | B64: Kokaly | C64: Kokaly R.F.; Rockwell B.W.; Haire S.L.; King T.V.V. | D64: 2007 | E64: Characterization of post-fire surface cover, soils, and burn severity at the Cerro Grande Fire, New Mexico, using hyperspectral and multispectral remote sensing | F64: Remote Sensing of Environment | G64: article | H64: https://doi.org/10.1016/j.rse.2006.08.006 | I64: https://www.scopus.com/inward/record.uri?eid=2-s2.0-33846331168&doi=10.1016%2fj.rse.2006.08.006&partnerID=40&md5=71b5bc6f311c16f22b0a2780c5b88b71 | J64: Scopus | K64: keep | L64: yes | M64: keep | O64: RS burn severity with comparison of reflectance with soil properties
A65: Shakesby_Chafer_Doerr_etal_2003 | B65: Shakesby | C65: Shakesby R.A.; Chafer C.J.; Doerr S.H.; Blake W.H.; Wallbrink P.; Humphreys G.S.; Harrington B.A. | D65: 2003 | E65: Fire severity, water repellency characteristics and hydrogeomorphological changes following the Christmas 2001 Sydney forest fires | F65: Australian Geographer | G65: article | H65: https://doi.org/10.1080/00049180301736 | I65: https://www.scopus.com/inward/record.uri?eid=2-s2.0-0042889141&doi=10.1080%2f00049180301736&partnerID=40&md5=491c90dc8a5567c7615a761a2bad86c6 | J65: Scopus | K65: keep | L65: yes | M65: keep | O65: RS compared to severity and soil repellency... RS does not adequately show ground litter consumption or repellency
A66: Rogan_Franklin_2001 | B66: Rogan | C66: Rogan J.; Franklin J. | D66: 2001 | E66: Mapping wildfire burn severity in Southern California forests and shrublands using enhanced thematic mapper imagery | F66: Geocarto International | G66: article | H66: https://doi.org/10.1080/10106040108542218 | I66: https://www.scopus.com/inward/record.uri?eid=2-s2.0-33746607869&doi=10.1080%2f10106040108542218&partnerID=40&md5=5fcc968dab4f043c6e878e4d6df34010 | J66: Scopus | K66: keep | L66: yes | M66: keep | O66: RS spectral unmixing with bare soil endmember for burn severity estimates
A67: Allen_Sorbel_2008 | B67: Allen | C67: Jennifer L. Allen;Brian Sorbel | D67: 2008 | E67: Assessing the differenced Normalized Burn Ratio's ability to map burn severity in the boreal forest and tundra ecosystems of Alaska's national parks | F67: International Journal of Wildland Fire | G67: article | H67: https://doi.org/10.1071/wf08034 | I67: https://doi.org/10.1071/wf08034 | J67: OpenAlex | K67: keep | L67: yes | M67: keep
A68: Hoy_French_Turetsky_etal_2008 | B68: Hoy | C68: Elizabeth Hoy;Nancy H. F. French;M. R. Turetsky;Simon N. Trigg;Eric S. Kasischke | D68: 2008 | E68: Evaluating the potential of Landsat TM/ETM+ imagery for assessing fire severity in Alaskan black spruce forests | F68: International Journal of Wildland Fire | G68: article | H68: https://doi.org/10.1071/wf08107 | I68: https://doi.org/10.1071/wf08107 | J68: OpenAlex | K68: keep | L68: yes | M68: keep | O68: Post-fire evaluation of RS indices relative to Composite Burn Index and remaining organic layer depth
A69: Whitman_Parisien_Holsinger_etal_2020 | B69: Whitman | C69: Ellen Whitman;Marc-AndrÃ© Parisien;Lisa M. Holsinger;Jane Park;Sean A. Parks | D69: 2020 | E69: A method for creating a burn severity atlas: an example from Alberta, Canada | F69: International Journal of Wildland Fire | G69: article | H69: https://doi.org/10.1071/wf19177 | I69: https://doi.org/10.1071/wf19177 | J69: OpenAlex | K69: keep | L69: yes | M69: keep | O69: RS burn severity maps compared to field-based Composite Burn Index
A70: Udali_Talbot_Ackerman_etal_2024 | B70: Udali | C70: Alberto Udali;Bruce Talbot;Simon Ackerman;Jacob Crous;Stefano Grigolato | D70: 2024 | E70: Enhancing precision in quantification and spatial distribution of logging residues in plantation stands | F70: European Journal of Forest Research | G70: article | H70: https://doi.org/10.1007/s10342-024-01699-5 | I70: https://doi.org/10.1007/s10342-024-01699-5 | J70: OpenAlex | K70: keep | L70: yes | M70: keep
A71: Kadakci̇ Koca_2023 | B71: KadakciÌ‡ | C71: KadakciÌ‡ Koca T. | D71: 2023 | E71: A statistical approach to site-specific thresholding for burn severity maps using bi-temporal Landsat-8 images | F71: Earth Science Informatics | G71: article | H71: https://doi.org/10.1007/s12145-023-00980-2 | I71: https://www.scopus.com/inward/record.uri?eid=2-s2.0-85148611463&doi=10.1007%2fs12145-023-00980-2&partnerID=40&md5=2dc0653d7a5be0f2db22530a1ccc0f87 | J71: Scopus | K71: keep | L71: yes | M71: keep | O71: RS product validated using Composite Burn Index
A72: Pierzchała_Talbot_Astrup_2014 | B72: Pierzchała | C72: Pierzchała M.; Talbot B.; Astrup R. | D72: 2014 | E72: Estimating soil displacement from timber extraction trails in steep terrain: Application of an unmanned aircraft for 3D modelling | F72: Forests | G72: article | H72: https://doi.org/10.3390/f5061212 | I72: https://www.scopus.com/inward/record.uri?eid=2-s2.0-84902463861&doi=10.3390%2ff5061212&partnerID=40&md5=8b4ea0493f590714bce883d80a23b7ea | J72: Scopus | K72: keep | L72: yes | M72: keep
A73: Lewis_Hudak_Ottmar_etal_2011 | B73: Lewis | C73: Sarah A. Lewis;Andrew T. Hudak;Roger D. Ottmar;Peter R. Robichaud;Leigh B. Lentile;Sharon M. Hood;James B. Cronan;Penny Morgan | D73: 2011 | E73: Using hyperspectral imagery to estimate forest floor consumption from wildfire in boreal forests of Alaska, USA | F73: International Journal of Wildland Fire | G73: article | H73: https://doi.org/10.1071/wf09081 | I73: https://doi.org/10.1071/wf09081 | J73: OpenAlex | K73: keep | L73: yes | M73: keep
A74: Salesa_Minervino Amodio_Rosskopf_etal_2020 | B74: Salesa | C74: Salesa, D. ; Minervino Amodio, A. ; Rosskopf, C.M. ; GarfÃ¬, V. ; Terol, E. ; CerdÃ , A. | D74: 2020 | E74: Three topographical approaches to survey soil erosion on a mountain trail affected by a forest fire. Barranc de la Manesa, Llutxent, Eastern Iberian Peninsula. | F74: Journal of Environmental Management | G74: article | H74: https://doi.org/10.1016/j.jenvman.2020.110491 | I74: https://research.ebsco.com/linkprocessor/plink?id=2e38ffa6-69c4-3dd3-ae75-7ac64871e699 | J74: EBSCOhost | K74: keep | L74: yes | M74: drop | N74: population | O74: Focuses on erosion of mountain trails post-fire
A75: Siafali_Tsioras_2024 | B75: Siafali | C75: Siafali E.; Tsioras P.A. | D75: 2024 | E75: An Innovative Approach to Surface Deformation Estimation in Forest Road and Trail Networks Using Unmanned Aerial Vehicle Real-Time Kinematic-Derived Data for Monitoring and Maintenance | F75: Forests | G75: article | H75: https://doi.org/10.3390/f15010212 | I75: https://www.scopus.com/inward/record.uri?eid=2-s2.0-85183322860&doi=10.3390%2ff15010212&partnerID=40&md5=5b8b2376d16eeb7846549f5c4f8ed6a1 | J75: Scopus | K75: keep | L75: yes | M75: drop | N75: population | O75: Focused on erosion around forest roads and hiking trails
A76: Reiner_Baker_Wahlberg_etal_2022 | B76: Reiner | C76: Alicia L. Reiner, Craig Baker, Maximillian Wahlberg, Benjamin M. Rau, Joseph D. Birch | D76: 2022 | E76: Region-Specific Remote-Sensing Models for Predicting Burn Severity, Basal Area Change, and Canopy Cover Change following Fire in the Southwestern United States | F76: Fire | G76: article | H76: https://doi.org/10.3390/fire5050137 | I76: https://research.fs.usda.gov/treesearch/65221 | J76: USFSTreesearch | K76: keep | L76: yes | M76: drop | N76: population | O76: Relates pre- and post-fire RS data to composite burn index, but no mention of soil
A77: Lentile_Morgan_Hudak_etal_2007 | B77: Lentile | C77: Leigh B. Lentile, Penelope Morgan, Andrew T. Hudak, Michael J. Bobbitt, Sarah A. Lewis, Alistair M. S. Smith, Peter R. Robichaud | D77: 2007 | E77: Post-fire burn severity and vegetation response following eight large wildfires across the Western United States | F77: Fire Ecology | G77: article | H77: https://doi.org/10.4996/fireecology.0301091 | I77: https://research.fs.usda.gov/treesearch/29509 | J77: USFSTreesearch | K77: keep | L77: yes | M77: drop | N77: study design | O77: No clear link between the field data and the RS products
A78: Hoffmann_SchÃ¶nauer_Heppelmann_etal_2022 | B78: Hoffmann | C78: Hoffmann S.; SchÃ¶nauer M.; Heppelmann J.; Asikainen A.; Cacot E.; Eberhard B.; Hasenauer H.; Ivanovs J.; Jaeger D.; Lazdins A.; Mohtashami S.; Moskalik T.; Nordfjell T.; StereÅ„czak K.; Talbot B.; Uusitalo J.; Vuillermoz M.; Astrup R. | D78: 2022 | E78: Trafficability Prediction Using Depth-to-Water Maps: the Status of Application in Northern and Central European Forestry | F78: Current Forestry Reports | G78: review | H78: https://doi.org/10.1007/s40725-021-00153-8 | I78: https://www.scopus.com/inward/record.uri?eid=2-s2.0-85122705487&doi=10.1007%2fs40725-021-00153-8&partnerID=40&md5=567303db1baef155a15c9c28001e9c57 | J78: Scopus | K78: keep | L78: yes | M78: drop | N78: intervention | O78: Operational, review of trafficability maps using depth to water and wetness and DEM
A79: Wu_Nunes_Baartman_etal_2021 | B79: Wu | C79: Wu J.; Nunes J.P.; Baartman J.E.M.; FaÃºndez Urbina C.A. | D79: 2021 | E79: Testing the impacts of wildfire on hydrological and sediment response using the OpenLISEM model. Part 1: Calibration and evaluation for a burned Mediterranean forest catchment | F79: Catena | G79: article | H79: https://doi.org/10.1016/j.catena.2021.105658 | I79: https://www.scopus.com/inward/record.uri?eid=2-s2.0-85112805967&doi=10.1016%2fj.catena.2021.105658&partnerID=40&md5=aa8109ee731ccbff122839739da9951b | J79: Scopus | K79: keep | L79: yes | M79: drop | N79: study design | O79: Erosion modelling in forest catchments but no in-situ indicators used
A80: Kankare_Luoma_Saarinen_etal_2019 | B80: Kankare | C80: Kankare V.; Luoma V.; Saarinen N.; Peuhkurinen J.; Holopainen M.; Vastaranta M. | D80: 2019 | E80: Assessing feasibility of the forest trafficability map for avoiding rutting â€“ A case study | F80: Silva Fennica | G80: article | H80: https://doi.org/10.14214/sf.10197 | I80: https://www.scopus.com/inward/record.uri?eid=2-s2.0-85073519063&doi=10.14214%2fsf.10197&partnerID=40&md5=29638f2edfdda1cdbaf7bcff703fec12 | J80: Scopus | K80: keep | L80: yes | M80: drop | N80: intervention | O80: Operational, use of LiDAR DEM to produce traficability map, then evaluate effectiveness of maps with in-situ measurment of rut depth, no linke between RS and in-situ indicator
A81: Vijith_Dodge-Wan_2018 | B81: Vijith | C81: Vijith H.; Dodge-Wan D. | D81: 2018 | E81: Spatio-temporal changes in rate of soil loss and erosion vulnerability of selected region in the tropical forests of Borneo during last three decades | F81: Earth Science Informatics | G81: article | H81: https://doi.org/10.1007/s12145-017-0321-7 | I81: https://www.scopus.com/inward/record.uri?eid=2-s2.0-85029579155&doi=10.1007%2fs12145-017-0321-7&partnerID=40&md5=1c7bb46f14c528fbcf08005c72308ce1 | J81: Scopus | K81: keep | L81: yes | M81: drop | N81: study design | O81: RUSLE erosion analysis, time series modelling exercise without any in-situ measures
A82: Alonzo_Morton_Cook_etal_2017 | B82: Alonzo | C82: Alonzo M.; Morton D.C.; Cook B.D.; Andersen H.-E.; Babcock C.; Pattison R. | D82: 2017 | E82: Patterns of canopy and surface layer consumption in a boreal forest fire from repeat airborne lidar | F82: Environmental Research Letters | G82: article | H82: https://doi.org/10.1088/1748-9326/aa6ade | I82: https://www.scopus.com/inward/record.uri?eid=2-s2.0-85021301898&doi=10.1088%2f1748-9326%2faa6ade&partnerID=40&md5=355a38a605458040fd347ac70fa3a3cb | J82: Scopus | K82: keep | L82: yes | M82: drop | N82: study design | O82: Used LiDAR to estimate depth of soil surface layer consumption, but only compare to classic Landsat burn severity measures using dNBR, no in-situ indicators
A83: Miller_Safford_Welch_2016 | B83: Miller | C83: Miller J.D.; Safford H.D.; Welch K.R. | D83: 2016 | E83: Using one year post-fire fire severity assessments to estimate longer-term effects of fire in conifer forests of northern and eastern California, USA | F83: Forest Ecology and Management | G83: article | H83: https://doi.org/10.1016/j.foreco.2016.10.017 | I83: https://www.scopus.com/inward/record.uri?eid=2-s2.0-84992457655&doi=10.1016%2fj.foreco.2016.10.017&partnerID=40&md5=7d60f0553ef98b85e4c748ebc4c107db | J83: Scopus | K83: keep | L83: yes | M83: drop | N83: population | O83: RS burn severity, realtionship to CBI but soil is not discussed or evaluated
A84: Fox_Laaroussi_Malkinson_etal_2016 | B84: Fox | C84: Fox D.M.; Laaroussi Y.; Malkinson L.D.; Maselli F.; Andrieu J.; Bottai L.; Wittenberg L. | D84: 2016 | E84: POSTFIRE: A model to map forest fire burn scar and estimate runoff and soil erosion risks | F84: Remote Sensing Applications: Society and Environment | G84: article | H84: https://doi.org/10.1016/j.rsase.2016.07.002 | I84: https://www.scopus.com/inward/record.uri?eid=2-s2.0-84982845602&doi=10.1016%2fj.rsase.2016.07.002&partnerID=40&md5=cc1c46785b077d8166dcc2c7ccfd9a80 | J84: Scopus | K84: keep | L84: yes | M84: drop | N84: study design | O84: Interesting post-fire erosion model with RS inputs, but no in-situ comparison with erosion indicators
A85: Miller_Sirois_1986 | B85: Miller | C85: Miller James H.; Sirois Donald L. | D85: 1986 | E85: SOIL DISTURBANCE BY SKYLINE YARDING VS. SKIDDING IN A LOAMY HILL FOREST. | F85: Soil Science Society of America Journal | G85: article | H85: https://doi.org/10.2136/sssaj1986.03615995005000060039x | I85: https://www.scopus.com/inward/record.uri?eid=2-s2.0-0022923212&doi=10.2136%2fsssaj1986.03615995005000060039x&partnerID=40&md5=6c5c01df7faa7e46f289aedbb38d81f2 | J85: Scopus | K85: keep | L85: yes | M85: drop | N85: study design | O85: Aerial survey, uses imagery (technically RS) but methodological description is insufficient
... A90: Franco_Mundo_Veblen_2020 | B90: Franco | C90: Franco M.G.; Mundo I.A.; Veblen T.T. | D90: 2020 | E90: Field-validated burn-severity mapping in North Patagonian forests | F90: Remote Sensing | G90: article | H90: https://doi.org/10.3390/rs12020214 | I90: https://www.scopus.com/inward/record.uri?eid=2-s2.0-85081087283&doi=10.3390%2frs12020214&partnerID=40&md5=19b863626298ff08da8f3d42ee8d4e94 | J90: Scopus | K90: keep | L90: yes | M90: drop | N90: population | O90: Uses RS burn severity compared to an in-situ simplified version of Composite Burn Index, but no mention of soil specifically so dropped
A91: Rachmawan_Kiyoki_Sasaki_2017 | B91: Rachmawan | C91: Rachmawan I.E.W.; Kiyoki Y.; Sasaki S. | D91: 2017 | E91: An automatic feature extraction method of satellite multispectral images for interpreting deforestation effects in soil degradation | F91: International Journal on Advanced Science, Engineering and Information Technology | G91: article | H91: https://doi.org/10.18517/ijaseit.7.2.2174 | I91: https://www.scopus.com/inward/record.uri?eid=2-s2.0-85018526462&doi=10.18517%2fijaseit.7.2.2174&partnerID=40&md5=7b96038bb61d1a4521f554e90957a900 | J91: Scopus | K91: keep | L91: no | O91: super funky
A92: Miesel_Kolka_Townsend_etal_2015 | B92: Miesel | C92: Jessica R. Miesel, Randall K. Kolka, Philip A. Townsend, William C. Hockaday | D92: 2015 | E92: Fire severity effects on soil organic matter in northern Minnesota, USA | F92: FLAMMA | G92: article | I92: https://research.fs.usda.gov/treesearch/64440 | J92: USFSTreesearch | K92: drop | O92: No RS
A93: Dillon_Panunto_Davis_etal_2020 | B93: Dillon | C93: Gregory K. Dillon, Matthew H. Panunto, Brett Davis, Penelope Morgan, Donovan S. Birch, William M. Jolly | D93: 2020 | E93: Development of a Severe Fire Potential map for the contiguous United States | F93: U.S. Department of Agriculture, Forest Service | G93: report | I93: https://research.fs.usda.gov/treesearch/60733 | J93: USFSTreesearch | K93: drop
A94: Alaniz_Abarzua_Martel-Cea_etal_2021 | B94: Alaniz | C94: Alaniz, Alberto J. ; Abarzua, Ana M. ; Martel-Cea, Alejandra ; Jarpa, Leonora ; Hernandez, Marjorie ; Aquino-Lopez, Marco A. ; Smith-Ramirez, Cecilia | D94: 2021 | E94: Linking sedimentological and spatial analysis to assess the impact of the forestry industry on soil loss; the case of Lanalhue Basin, Chile | F94: Catena (Giessen) | G94: analytic | H94: https://doi.org/10.1016/j.catena.2021.105660 | I94: https://research.ebsco.com/linkprocessor/plink?id=61a79f48-81a9-3b08-aba8-bc4c3d4f7257 | J94: EBSCOhost | K94: drop | O94: Very interesting, long RUSLE time series model using lake sediment cores to assess long-term impacts of forestry in catchment
A95: Borrelli_MÃ¤rker_SchÃ¼tt_2013 | B95: Borrelli | C95: Pasquale Borrelli;Michael MÃ¤rker;Brigitta SchÃ¼tt | D95: 2013 | E95: Modelling Post-Tree-Harvesting Soil Erosion and Sediment Deposition Potential in the Turano River Basin (Italian Central Apennine) | F95: Land Degradation and Development | G95: article | H95: https://doi.org/10.1002/ldr.2214 | I95: https://doi.org/10.1002/ldr.2214 | J95: OpenAlex | K95: drop | O95: RUSLE to model erosion potential
A96: Sujatha_Sridhar_2018 | B96: Sujatha | C96: Evangelin Ramani Sujatha;Venkataramana Sridhar | D96: 2018 | E96: Spatial Prediction of Erosion Risk of a Small Mountainous Watershed Using RUSLE: A Case-Study of the Palar Sub-Watershed in Kodaikanal, South India | F96: Water | G96: article | H96: https://doi.org/10.3390/w10111608 | I96: https://doi.org/10.3390/w10111608 | J96: OpenAlex | K96: drop | O96: RUSLE to model erosion potential
A97: Park_Lee_Shin_2011 | B97: Park | C97: Sang Deog Park;Kyu Song Lee;Seung Sook Shin | D97: 2011 | E97: Statistical Soil Erosion Model for Burnt Mountain Areas in Koreaâ€”RUSLE Approach | F97: Journal of Hydrologic Engineering | G97: article | H97: https://doi.org/10.1061/(asce)he.1943-5584.0000441 | I97: https://doi.org/10.1061/(asce)he.1943-5584.0000441 | J97: OpenAlex | K97: keep | L97: request | M97: drop | N97: study design | O97: Requested via NRCan Library 25-06-30; RUSLE erosion model using DEM, mentions ground plots in abstract but need to check text; TEXT CHECKED - no RS actually used (slope and elevation recored in-situ)
A98: Coschignano_Nicolaci_Ferrari_etal_2019 | B98: Coschignano | C98: G Coschignano;Antonino Nicolaci;Ennio Ferrari;F Cruscomagno;Francesco Iovino | D98: 2019 | E98: Evaluation of hydrological and erosive effects at the basin scale in relation to the severity of forest fires | F98: iForest - Biogeosciences and Forestry | G98: article | H98: https://doi.org/10.3832/ifor2878-012 | I98: https://doi.org/10.3832/ifor2878-012 | J98: OpenAlex | K98: drop | O98: RUSLE equation for erosion estimates, no in-situ indicators
A99: French_Kasischke_Bourgeau-Chavez_etal_2002 | B99: French | C99: Nancy H. F. French;Eric S. Kasischke;Laura Bourgeau-Chavez;Peter Harrell;Norman L. Christensen | D99: 2002 | E99: Relating soil water measurements at fire disturbed sites in Alaska to ERS-1 SAR image signature | F99: NA | G99: article | H99: https://doi.org/10.1109/igarss.1994.399094 | I99: https://doi.org/10.1109/igarss.1994.399094 | J99: OpenAlex | K99: keep | L99: request | M99: drop | N99: study design | O99: Requested via NRCan Library 25-06-30; Correlating post-burn soil moisture to radar backscatter
A100: Tolorza_Poblete-Caballero_GonzÃ¡lez_etal_2021 | B100: Tolorza | C100: Violeta Tolorza;Dagoberto Poblete-Caballero;Virginia I. GonzÃ¡lez;Mauricio Zambrano-Bigiarini;JuliÃ¡n Cabezas;Mauricio Galleguillos | D100: 2021 | E100: Fire-induced catchment erosion on a depleted soil system from GeoWEPP and RUSLE models, Santa Olga, Chile | F100: NA | G100: article | H100: https://doi.org/10.5194/egusphere-egu21-13140 | I100: https://doi.org/10.5194/egusphere-egu21-13140 | J100: OpenAlex | K100: drop | O100: RUSLE erosion model, but purely a modelling exercise, no in-situ erosion indicators
A101: Putzenlechner_Koal_Karel_etal_2024 | B101: Putzenlechner | C101: Birgitta Putzenlechner;Philipp Koal;Susanne Karel;Martin Kappas;Markus LÃ¶w;Philip Mundhenk;Alexander Tischer;Jakob Wernicke;Tatjana Koukal | D101: 2024 | E101: The Role of Soil in Forest Drought Response: Remote Sensing-Based Monitoring of Disturbance Hotspots in Central Europe | F101: NA | G101: preprint | H101: https://doi.org/10.5194/egusphere-egu24-12524 | I101: https://doi.org/10.5194/egusphere-egu24-12524 | J101: OpenAlex | K101: drop
A102: Michel_Burgstall_Hirschi_etal_2022 | B102: Michel | C102: Dominik Michel;Annkatrin Burgstall;Martin Hirschi;Anke Duguay-Tetzlaff;Sonia I. Seneviratne | D102: 2022 | E102: Assessing the suitability of remote sensing estimates of soil moisture and land evaporation in Switzerland for a better preparedness for projected drying trends | F102: NA | G102: preprint | H102: https://doi.org/10.5194/egusphere-egu22-11052 | I102: https://doi.org/10.5194/egusphere-egu22-11052 | J102: OpenAlex | K102: drop | O102: Correlation of in-situ soil moisture in grassland and forest with RS data, but to intervention
A103: Senn_Seitz_Fassnacht_etal_2021 | B103: Senn | C103: Johannes Antenor Senn;Steffen Seitz;Fabian Ewald Fassnacht;Zahra Hosseini;Jannika SchÃ¤fer | D103: 2021 | E103: Time for 3D: UAV-based lidar for modelling splash erosion under vegetation | F103: NA | G103: article | H103: https://doi.org/10.5194/egusphere-egu21-7816 | I103: https://doi.org/10.5194/egusphere-egu21-7816 | J103: OpenAlex | K103: drop | O103: splash erosion under vegetation?
A104: Keizer_Silva_Augustijn_etal_2021 | B104: Keizer | C104: Jan Jacob Keizer;Joana Silva;Mathijs Augustijn;Ricardo Martins;Martinho Martins;Marta Basso;Antonio Girona-GarcÃ­a;Liliana SimÃµes;Diana Vieira | D104: 2021 | E104: Mitigation of post-fire erosion from terraced micro-catchments using timber barriers | F104: NA | G104: article | H104: https://doi.org/10.5194/egusphere-egu21-13677 | I104: https://doi.org/10.5194/egusphere-egu21-13677 | J104: OpenAlex | K104: keep | L104: no | O104: Conference slides insufficient
...

Sheet 3.5_snowball
A1: CREATE A SIMILAR SHEET AS "3_screening" but for studies identifies through snowball sampling using 1) the Research Rabbit suggestions, and 2) a review of citations of articles screened IN
A2: study_id | B2: first_author | C2: authors | D2: year | E2: title | F2: source | G2: type | H2: doi | I2: link_url | J2: dbase | K2: select_on_title_abs | L2: text_retrievable | M2: select_on_full_text | N2: excluded_reason | O2: notes
A3: Lentile_Holden_Smith_etal_2006 | B3: Lentile | C3: Leigh B. Lentile;Zachary A. Holden;Alistair M. S. Smith;Michael J. Falkowski;Andrew T. Hudak;Penelope Morgan;Paul E. Gessler;Nathan C. Benson | D3: 2006 | E3: Remote sensing techniques to assess active fire characteristics and post-fire effects | F3: International Journal of Wildland Fire | G3: NA | H3: 10.1071/wf05097 | I3: NA | J3: ResearchRabbit | K3: drop
A4: Wing_Burnett_Sessions_etal_2014 | B4: Wing | C4: Michael G. Wing;Jonathan D. Burnett;John Sessions | D4: 2014 | E4: Remote Sensing and Unmanned Aerial System Technology for Monitoring and Quantifying Forest Fire Impacts | F4: International Journal of Remote Sensing Applications | G4: NA | H4: 10.14355/ijrsa.2014.0401.02 | I4: NA | J4: ResearchRabbit | K4: drop
A5: KoreÅˆ_Koren_SlanÄ_x008d_Ã­k_etal_2014 | B5: KoreÅˆ | C5: Milan KoreÅˆ;M. Koren;M. SlanÄ_x008d_Ã­k;Josef Suchomel;J. Dubina | D5: 2014 | E5: Use of terrestrial laser scanning to evaluate the spatial distribution of soil disturbance by skidding operations | F5: Iforest - Biogeosciences and Forestry | G5: Article | H5: 10.3832/ifor1165-007 | I5: NA | J5: ResearchRabbit | K5: keep | L5: yes | M5: keep
A6: Robichaud_Lewis_Laes_etal_2007 | B6: Robichaud | C6: Peter R. Robichaud;Sarah A. Lewis;Denise Laes;Andrew T. Hudak;Raymond F. Kokaly;Joseph A. Zamudio | D6: 2007 | E6: Postfire soil burn severity mapping with hyperspectral image unmixing | F6: Remote Sensing of Environment | G6: Article | H6: 10.1016/j.rse.2006.11.027 | I6: NA | J6: ResearchRabbit | K6: keep | L6: yes | M6: keep
A7: Parks_Dillon_Miller_etal_2014 | B7: Parks | C7: Sean A. Parks;Gregory K. Dillon;Carol Miller | D7: 2014 | E7: A New Metric for Quantifying Burn Severity: The Relativized Burn Ratio | F7: Remote Sensing | G7: NA | H7: 10.3390/rs6031827 | I7: NA | J7: ResearchRabbit | K7: keep | L7: yes | M7: drop | N7: outcome
A8: FernÃ¡ndez-GarcÃ­a_Santamarta_FernÃ¡ndezâ€“Manso_etal_2018 | B8: FernÃ¡ndez-GarcÃ­a | C8: VÃ­ctor FernÃ¡ndez-GarcÃ­a;MÃ³nica Santamarta;Alfonso FernÃ¡ndezâ€“Manso;Dar A. Roberts;Carmen Quintano;Elena Marcos;Leonor Calvo | D8: 2018 | E8: Burn severity metrics in fire-prone pine ecosystems along a climatic gradient using Landsat imagery | F8: Remote Sensing of Environment | G8: NA | H8: 10.1016/j.rse.2017.12.029 | I8: NA | J8: ResearchRabbit | K8: keep | L8: yes | M8: keep
A9: Doerr_Shakesby_Blake_etal_2006 | B9: Doerr | C9: Stefan H. Doerr;Richard A. Shakesby;William H. Blake;Chris J. Chafer;Geoff S. Humphreys;Peter Wallbrink | D9: 2006 | E9: Effects of differing wildfire severities on soil wettability and implications for hydrological response | F9: Journal of Hydrology | G9: NA | H9: 10.1016/j.jhydrol.2005.06.038 | I9: NA | J9: ResearchRabbit | K9: keep | L9: yes | M9: keep
A10: Vega_FontÃºrbel_Merino_etal_2013 | B10: Vega | C10: JosÃ© A. Vega;Teresa FontÃºrbel;AgustÄ±Ì_x0081_n Merino;Cristina FernÃ¡ndez;A. Ferreiro;Enrique JimÃ©nez | D10: 2013 | E10: Testing the ability of visual indicators of soil burn severity to reflect changes in soil chemical and microbial properties in pine forests and shrubland | F10: Plant and Soil | G10: NA | H10: 10.1007/s11104-012-1532-9 | I10: NA | J10: ResearchRabbit | K10: keep | L10: yes | M10: drop | N10: study design
A11: Campbell_White_Arp_etal_2013 | B11: Campbell | C11: David M.h. M.h. Campbell;Barry White;Paul A. Arp | D11: 2013 | E11: Modeling and mapping soil resistance to penetration and rutting using LiDAR-derived digital elevation data | F11: Journal of Soil and Water Conservation | G11: NA | H11: 10.2489/jswc.68.6.460 | I11: NA | J11: ResearchRabbit | K11: keep | L11: request | M11: keep | O11: Requested via NRCan Library 25-06-30
A12: Pohjankukka_RiihimÃ¤ki_Nevalainen_etal_2016 | B12: Pohjankukka | C12: Jonne Pohjankukka;Henri RiihimÃ¤ki;Paavo Nevalainen;Tapio Pahikkala;Jari Alaâ€_x0090_IlomÃ¤ki;Eija HyvÃ¶nen;J. Varjo;Jukka Heikkonen | D12: 2016 | E12: Predictability of boreal forest soil bearing capacity by machine learning | F12: Journal of Terramechanics | G12: NA | H12: 10.1016/j.jterra.2016.09.001 | I12: NA | J12: ResearchRabbit | K12: keep | L12: yes | M12: keep
A13: Veraverbeke_Dennison_Gitas_etal_2018 | B13: Veraverbeke | C13: Sander Veraverbeke;Philip E. Dennison;Ioannis Z. Gitas;Glynn Hulley;Ðž. Ð’. ÐšÐ°Ð»Ð°ÑˆÐ½Ð¸ÐºÐ¾Ð²Ð°;Olga V. Kalashnikova;Thomas Katagis;Le Kuai;Ran Meng;Dar A. Roberts;E. Natasha Stavros | D13: 2018 | E13: Hyperspectral remote sensing of fire: State-of-the-art and future perspectives | F13: Remote Sensing of Environment | G13: NA | H13: 10.1016/j.rse.2018.06.020 | I13: NA | J13: ResearchRabbit | K13: keep | L13: yes | M13: keep
A14: Quintano_Fernandez-Manso_Calvo_etal_2019 | B14: Roberts | C14: Dar A. Roberts;Carmen Quintano;Alfonso FernÃ¡ndezâ€“Manso;Leonor Calvo | D14: 2019 | E14: Vegetation and Soil Fire Damage Analysis Based on Species Distribution Modeling Trained with Multispectral Satellite Data | F14: Remote Sensing | G14: NA | H14: 10.3390/rs11151832 | I14: NA | J14: ResearchRabbit | K14: keep | L14: yes | M14: keep | O14: Had to manually correct author order
A15: Suvinen_Tokola_Saarilahti_etal_2009 | B15: Suvinen | C15: Antti Suvinen;Timo Tokola;Martti Saarilahti | D15: 2009 | E15: Terrain Trafficability Prediction with GIS Analysis | F15: Forest Science | G15: NA | H15: NA | I15: https://doi.org/10.1093/forestscience/55.5.433 | J15: ResearchRabbit | K15: keep | L15: request | M15: drop | N15: study design | O15: Requested via NRCan Library 25-06-30
A16: Nadalâ€_x0090_Romero_Revuelto_Errea_etal_2015 | B16: Nadalâ€_x0090_Romero | C16: Estela Nadalâ€_x0090_Romero;JesÃºs Revuelto;Paz Errea;J. I. LÃ³pezâ€_x0090_Moreno | D16: 2015 | E16: The application of terrestrial laser scanner and SfM photogrammetry in measuring erosion and deposition processes in two opposite slopes in a humid badlands area (central Spanish Pyrenees) | F16: NA | G16: NA | H16: 10.5194/soil-1-561-2015 | I16: NA | J16: ResearchRabbit | K16: keep | L16: yes | M16: drop | N16: population
A17: Smith_Vericat_etal_2015 | B17: Smith | C17: Mark E. Smith;DamiÃ Vericat | D17: 2015 | E17: From experimental plots to experimental landscapes: topography, erosion and deposition in subâ€_x0090_humid badlands from Structureâ€_x0090_fromâ€_x0090_Motion photogrammetry | F17: Earth Surface Processes and Landforms | G17: NA | H17: 10.1002/esp.3747 | I17: NA | J17: ResearchRabbit | K17: keep | L17: yes | M17: drop | N17: population
A18: Tanase_Kennedy_Aponte_etal_2015 | B18: Tanase | C18: Mihai A. Tanase;Robert E. Kennedy;Cristina Aponte | D18: 2015 | E18: Fire severity estimation from space: a comparison of active and passive sensors and their synergy for different forest types | F18: International Journal of Wildland Fire | G18: NA | H18: 10.1071/wf15059 | I18: NA | J18: ResearchRabbit | K18: keep | L18: yes | M18: drop | N18: outcome
A19: SÃ¡nchez_Bisquert_Rubio_etal_2015 | B19: SÃ¡nchez | C19: Juan Manuel SÃ¡nchez;Mar Bisquert;E. Rubio;Vicente Caselles | D19: 2015 | E19: Impact of Land Cover Change Induced by a Fire Event on the Surface Energy Fluxes Derived from Remote Sensing | F19: Remote Sensing | G19: NA | H19: 10.3390/rs71114899 | I19: NA | J19: ResearchRabbit | K19: keep | L19: yes | M19: drop | N19: outcome
A20: Johnstone_Kasischke_etal_2005 | B20: Johnstone | C20: Jill F. Johnstone;Eric S. Kasischke | D20: 2005 | E20: Stand-level effects of soil burn severity on postfire regeneration in a recently burned black spruce forest | F20: Canadian Journal of Forest Research | G20: NA | H20: 10.1139/x05-087 | I20: NA | J20: ResearchRabbit | K20: keep | L20: yes | M20: drop | N20: study design
A21: Case_Meng_Arp_etal_2005 | B21: Case | C21: Bradley S. Case;Fanâ€_x0090_Rui Meng;Paul A. Arp | D21: 2005 | E21: Digital elevation modelling of soil type and drainage within small forested catchments | F21: Canadian Journal of Soil Science | G21: NA | H21: 10.4141/s04-008 | I21: NA | J21: ResearchRabbit | K21: keep | L21: yes | M21: drop | N21: intervention
A22: Vlassova_PÃ©rezâ€_x0090_Cabello_Mimbrero_etal_2014 | B22: Vlassova | C22: Lidia Vlassova;Fernando PÃ©rezâ€_x0090_Cabello;Marcos Rodrigues Mimbrero;Raquel Montorio LloverÃ­a;Alberto GarcÃ­a-MartÃ­n | D22: 2014 | E22: Analysis of the Relationship between Land Surface Temperature and Wildfire Severity in a Series of Landsat Images | F22: Remote Sensing | G22: NA | H22: 10.3390/rs6076136 | I22: NA | J22: ResearchRabbit | K22: keep | L22: yes | M22: drop | N22: outcome
A23: MilenkoviÄ‡_Pfeifer_Glira_etal_2015 | B23: MilenkoviÄ‡ | C23: Milutin MilenkoviÄ‡;Norbert Pfeifer;Philipp Glira | D23: 2015 | E23: Applying Terrestrial Laser Scanning for Soil Surface Roughness Assessment | F23: Remote Sensing | G23: NA | H23: 10.3390/rs70202007 | I23: NA | J23: ResearchRabbit | K23: keep | L23: yes | M23: drop | N23: intervention
A24: Lewis_Wu_Wu_etal_2006 | B24: Lewis | C24: Sarah A. Lewis;Ji Wu;Joan Q. Wu;Peter R. Robichaud | D24: 2006 | E24: Assessing burn severity and comparing soil water repellency, Hayman Fire, Colorado | F24: Hydrological Processes | G24: NA | H24: 10.1002/hyp.5880 | I24: NA | J24: ResearchRabbit | K24: keep | L24: yes | M24: drop | N24: study design
A25: Jaboyedoff_Demers_Locat_etal_2009 | B25: Jaboyedoff | C25: Michel Jaboyedoff;Denis Demers;Jacques Locat;Thierry Oppikofer;Denis Robitaille;Dominique Turmel | D25: 2009 | E25: Use of terrestrial laser scanning for the characterization of retrogressive landslides in sensitive clay and rotational landslides in river banks | F25: Canadian Geotechnical Journal | G25: NA | H25: 10.1139/t09-073 | I25: NA | J25: ResearchRabbit | K25: keep | L25: yes | M25: drop | N25: population
A26: Chu_Guo_etal_2013 | B26: Chu | C26: Thuan Chu;Xulin Guo | D26: 2013 | E26: Remote Sensing Techniques in Monitoring Post-Fire Effects and Patterns of Forest Recovery in Boreal Forest Regions: A Review | F26: Remote Sensing | G26: NA | H26: 10.3390/rs6010470 | I26: NA | J26: ResearchRabbit | K26: keep | L26: yes | M26: drop | N26: study design
A27: FernÃ¡ndez_Vega_etal_2016 | B27: FernÃ¡ndez | C27: Cristina FernÃ¡ndez;JosÃ© A. Vega | D27: 2016 | E27: Modelling the effect of soil burn severity on soil erosion at hillslope scale in the first year following wildfire in NW Spain | F27: Earth Surface Processes and Landforms | G27: NA | H27: 10.1002/esp.3876 | I27: NA | J27: ResearchRabbit | K27: keep | L27: yes | M27: drop | N27: study design
A28: Fang_Yang_White_etal_2018 | B28: Fang | C28: Lei Fang;Jian Yang;Megan White;Zhihua Liu | D28: 2018 | E28: Predicting Potential Fire Severity Using Vegetation, Topography and Surface Moisture Availability in a Eurasian Boreal Forest Landscape | F28: Forests | G28: NA | H28: 10.3390/f9030130 | I28: NA | J28: ResearchRabbit | K28: keep | L28: yes | M28: drop | N28: study design
A29: Marcos_FernÃ¡ndez-GarcÃ­a_FernÃ¡ndezâ€“Manso_etal_2018 | B29: Marcos | C29: Elena Marcos;VÃ­ctor FernÃ¡ndez-GarcÃ­a;Alfonso FernÃ¡ndezâ€“Manso;Dar A. Roberts;Carmen Quintano;L. Valbuena;Reyes TÃ¡rrega;E. Luisâ€_x0090_Calabuig;Leonor Calvo | D29: 2018 | E29: Evaluation of Composite Burn Index and Land Surface Temperature for Assessing Soil Burn Severity in Mediterranean Fire-Prone Pine Ecosystems | F29: Forests | G29: NA | H29: 10.3390/f9080494 | I29: NA | J29: ResearchRabbit | K29: keep | L29: yes | M29: keep
A30: Foldager_Pedersen_Skov_etal_2019 | B30: Foldager | C30: Frederik F. Foldager;Johanna Pedersen;Esben Haubro Skov;Alevtina Evgrafova;Ole Green | D30: 2019 | E30: LiDAR-Based 3D Scans of Soil Surfaces and Furrows in Two Soil Types | F30: Sensors | G30: NA | H30: 10.3390/s19030661 | I30: NA | J30: ResearchRabbit | K30: keep | L30: yes | M30: drop | N30: population
A31: Jones_Arp_etal_2019 | B31: Jones | C31: Marie-France Jones;Paul A. Arp | D31: 2019 | E31: Analyzing and Projecting Soil Moisture and Cone Penetrability Variations in Forest Soils | F31: Open Journal of Forestry | G31: NA | H31: 10.4236/ojf.2019.92005 | I31: NA | J31: ResearchRabbit | K31: keep | L31: yes | M31: drop | N31: intervention
A32: Sobrino_Llorens_FernÃ¡ndez_etal_2019 | B32: Sobrino | C32: JosÃ© A. Sobrino;Rafael Llorens;Cristina FernÃ¡ndez;JosÃ© MarÃ­a FernÃ¡ndez-Alonso | D32: 2019 | E32: Relationship between Soil Burn Severity in Forest Fires Measured In Situ and through Spectral Indices of Remote Detection | F32: Forests | G32: NA | H32: 10.3390/f10050457 | I32: NA | J32: ResearchRabbit | K32: keep | L32: yes | M32: drop | N32: outcome
A33: Salmivaara_Launiainen_Perttunen_etal_2020 | B33: Salmivaara | C33: Aura Salmivaara;Samuli Launiainen;Jari Perttunen;Paavo Nevalainen;Jonne Pohjankukka;Jari Alaâ€_x0090_IlomÃ¤ki;Matti SirÃ©n;Jori Uusitalo;Tapio Pahikkala;Jukka Heikkonen;Leena FinÃ©r | D33: 2020 | E33: Towards dynamic forest trafficability prediction using open spatial data, hydrological modelling and sensor technology | F33: Forestry: An International Journal of Forest Research | G33: NA | H33: 10.1093/forestry/cpaa010 | I33: NA | J33: ResearchRabbit | K33: keep | L33: yes | M33: drop | N33: study design
A34: Han_Pageâ€_x0090_Dumroese_Johnson_etal_2009 | B34: Han | C34: Sang-Kyun Han;Deborah S. Pageâ€_x0090_Dumroese;Leonard R. Johnson | D34: 2009 | E34: Soil compaction associated with cut-to-length and whole-tree harvesting of a coniferous forest | F34: Canadian Journal of Forest Research | G34: NA | H34: 10.1139/x09-027 | I34: NA | J34: ResearchRabbit | K34: drop
A35: Jansson_etal_1998 | B35: Jansson | C35: Karl-Johan Jansson | D35: 1998 | E35: Soil changes after traffic with a tracked and a wheeled forest machine: a case study on a silt loam in Sweden | F35: Forestry | G35: NA | H35: 10.1093/forestry/71.1.57 | I35: NA | J35: ResearchRabbit | K35: drop
A36: Huang_Huang_Roy_etal_2016 | B36: Huang | C36: Hung-Chun Huang;Haiyan Huang;David P. Roy;Luigi Boschetti;Lin Yan;Sundeep Kumar;Sanath Sathyachandran Kumar;JosÃ© GÃ³mez-Dans;Jian Li | D36: 2016 | E36: Separability Analysis of Sentinel-2A Multi-Spectral Instrument (MSI) Data for Burned Area Discrimination | F36: Remote Sensing | G36: NA | H36: 10.3390/rs8100873 | I36: NA | J36: ResearchRabbit | K36: drop
A37: Fwa_Pasindu_Ong_etal_2012 | B37: Fwa | C37: T.f. Fwa;H.r. Pasindu;G. B. Ong;Ghim Ping Ong | D37: 2012 | E37: Critical Rut Depth for Pavement Maintenance Based on Vehicle Skidding and Hydroplaning Consideration | F37: Journal of Transportation Engineering-asce | G37: NA | H37: 10.1061/(asce)te.1943-5436.0000336 | I37: NA | J37: ResearchRabbit | K37: drop
A38: Botta_Becerra_Tourn_etal_2009 | B38: Botta | C38: Guido Fernando Botta;Alfredo TolÃ³n Becerra;F. Bellora Tourn | D38: 2009 | E38: Effect of the number of tractor passes on soil rut depth and compaction in two tillage regimes | F38: Soil & Tillage Research | G38: NA | H38: 10.1016/j.still.2008.12.002 | I38: NA | J38: ResearchRabbit | K38: drop
A39: Warneke_Gouw_Stohl_etal_2006 | B39: Warneke | C39: Carsten Warneke;J. A. De Gouw;Andreas Stohl;O. R. Cooper;P. D. Goldan;W. C. Kuster;J. S. Holloway;E. J. Williams;B. M. Lerner;S. A. Mckeen;M. Trainer;F. C. Fehsenfeld;Elliot L. Atlas;V. Stroud;A. Lueb;Shingo Kato | D39: 2006 | E39: Biomass burning and anthropogenic sources of CO over New England in the summer 2004 | F39: Journal of Geophysical Research | G39: NA | H39: 10.1029/2005jd006878 | I39: NA | J39: ResearchRabbit | K39: drop
A40: Grace_Skaggs_Cassel_etal_2006 | B40: Grace | C40: Johnny M. Grace;R. W. Skaggs;D. K. Cassel | D40: 2006 | E40: Soil Physical Changes Associated with Forest Harvesting Operations on an Organic Soil | F40: Soil Science Society of America Journal | G40: NA | H40: 10.2136/sssaj2005.0154 | I40: NA | J40: ResearchRabbit | K40: drop
A41: Teillet_Guindon_Goodenough_1982 | B41: Teillet | C41: Philippe Teillet;B. Guindon;D. G. Goodenough | D41: 1982 | E41: On the Slope-Aspect Correction of Multispectral Scanner Data | F41: Canadian Journal of Remote Sensing | G41: NA | H41: 10.1080/07038992.1982.10855028 | I41: NA | J41: ResearchRabbit | K41: drop
A42: Rosso_Ustin_Hastings_2005 | B42: Rosso | C42: Pablo Rosso;Susan L. Ustin;Alan Hastings | D42: 2005 | E42: Mapping marshland vegetation of San Francisco Bay, California, using hyperspectral data | F42: International Journal of Remote Sensing | G42: NA | H42: 10.1080/01431160500218770 | I42: NA | J42: ResearchRabbit | K42: drop
A43: Earl_1997 | B43: Earl | C43: Richard A. Earl | D43: 1997 | E43: Prediction of trafficability and workability from soil moisture deficit | F43: Soil & Tillage Research | G43: NA | H43: 10.1016/s0167-1987(96)01072-0 | I43: NA | J43: ResearchRabbit | K43: drop
A44: Teillet_1986 | B44: Teillet | C44: P. M. Teillet | D44: 1986 | E44: Image correction for radiometric effects in remote sensing | F44: International Journal of Remote Sensing | G44: NA | H44: 10.1080/01431168608948958 | I44: NA | J44: ResearchRabbit | K44: drop
A45: Lee_Lee_Won_etal_2009 | B45: Lee | C45: Sangâ€_x0090_Woo Lee;Youngâ€_x0090_Geun Lee;Myoung-Soo Won;Jong-Jin Kim;Sungâ€“Kwon Hong | D45: 2009 | E45: Relationship between landscape structure and burn severity at the landscape and class levels in Samchuck, South Korea | F45: Forest Ecology and Management | G45: NA | H45: 10.1016/j.foreco.2009.07.017 | I45: NA | J45: ResearchRabbit | K45: drop
... A918: Breiman_1996 | B918: Breiman | C918: Leo Breiman | D918: 1996 | E918: Bagging predictors | F918: NA | G918: NA | H918: 10.1023/a:1018054314350 | I918: NA | J918: ResearchRabbit | K918: drop
A919: Solgi_Naghdi_Marchi_etal_2019 | B919: Solgi | C919: Ahmad Solgi;Ramin Naghdi;Enrico Marchi;Andrea Laschi;Farshad Keivan Behjou;Vahid Hemmati;Ali Masumian | D919: 2019 | E919: Impact Assessment of Skidding Extraction: Effects on Physical and Chemical Properties of Forest Soils and on Maple Seedling Growing along the Skid Trail | F919: Forests | G919: NA | H919: 10.3390/f10020134 | I919: NA | J919: ResearchRabbit | K919: drop | O919: Agriculture, no forest
A920: Harvey_Andrus_etal_2019 | B920: Harvey | C920: Brian Harvey;Robert A. Andrus | D920: 2019 | E920: Incorporating biophysical gradients and uncertainty into burn severity maps in a temperate fire-prone forested region | F920: Ecosphere | G920: NA | H920: 10.1002/ecs2.2600 | I920: NA | J920: ResearchRabbit | K920: drop
A921: Che_Jung_Olsen_etal_2019 | B921: Che | C921: Erzhuo Che;Jae Hwan Jung;Michael J. Olsen | D921: 2019 | E921: Object Recognition, Segmentation, and Classification of Mobile Laser Scanning Point Clouds: A State of the Art Review. | F921: Sensors | G921: NA | H921: 10.3390/s19040810 | I921: NA | J921: ResearchRabbit | K921: drop
A922: Jourgholami_Labelle_Poltorak_etal_2019 | B922: Jourgholami | C922: Meghdad Jourgholami;Eric R. Labelle;Benjamin J. Poltorak;Dirk Jaeger | D922: 2019 | E922: The role of brush mats in mitigating machine-induced soil disturbances: an assessment using absolute and relative soil bulk density and penetration resistance | F922: Canadian Journal of Forest Research | G922: NA | H922: 10.1139/cjfr-2018-0324 | I922: NA | J922: ResearchRabbit | K922: drop
A923: Gargoum_Basyouny_etal_2019 | B923: Gargoum | C923: Suliman Gargoum;Karim El Basyouny | D923: 2019 | E923: A literature synthesis of LiDAR applications in transportation: feature extraction and geometric assessments of highways | F923: Giscience & Remote Sensing | G923: NA | H923: 10.1080/15481603.2019.1581475 | I923: NA | J923: ResearchRabbit | K923: drop
A924: Khosrojerdi_Xiao_Qiu_etal_2019 | B924: Khosrojerdi | C924: Mahsa Khosrojerdi;Ming Xiao;Tong Qiu;Jennifer Nicks | D924: 2019 | E924: Nonlinear Equation for Predicting the Settlement of Reinforced Soil Foundations | F924: Journal of Geotechnical and Geoenvironmental Engineering | G924: NA | H924: 10.1061/(asce)gt.1943-5606.0002027 | I924: NA | J924: ResearchRabbit | K924: drop
A925: Wurm_Stark_Zhu_etal_2019 | B925: Wurm | C925: Michael Wurm;Thomas Stark;Xiao Xiang Zhu;Matthias Weigand;Hannes TaubenbÃ¶ck | D925: 2019 | E925: Semantic segmentation of slums in satellite images using transfer learning on fully convolutional neural networks | F925: Isprs Journal of Photogrammetry and Remote Sensing | G925: NA | H925: 10.1016/j.isprsjprs.2019.02.006 | I925: NA | J925: ResearchRabbit | K925: drop
A926: Ilori_Pahlevan_Knudby_etal_2019 | B926: Ilori | C926: Christopher O. Ilori;Nima Pahlevan;Anders Knudby | D926: 2019 | E926: Analyzing Performances of Different Atmospheric Correction Techniques for Landsat 8: Application for Coastal Remote Sensing | F926: Remote Sensing | G926: NA | H926: 10.3390/rs11040469 | I926: NA | J926: ResearchRabbit | K926: drop
A927: Uusitalo_Alaâ€_x0090_IlomÃ¤ki_Lindeman_etal_2019 | B927: Uusitalo | C927: Jori Uusitalo;Jari Alaâ€_x0090_IlomÃ¤ki;Harri Lindeman;Jenny Toivio;Matti SirÃ©n | D927: 2019 | E927: Modelling soil moisture â€“ soil strength relationship of fine-grained upland forest soils | F927: Silva Fennica | G927: NA | H927: 10.14214/sf.10050 | I927: NA | J927: ResearchRabbit | K927: drop
A928: Filipponi_2019 | B928: Filipponi | C928: Federico Filipponi | D928: 2019 | E928: Exploitation of Sentinel-2 Time Series to Map Burned Areas at the National Level: A Case Study on the 2017 Italy Wildfires | F928: Remote Sensing | G928: NA | H928: 10.3390/rs11060622 | I928: NA | J928: ResearchRabbit | K928: drop
A929: Safonova_Tabik_Alcarazâ€_x0090_Segura_etal_2019 | B929: Safonova | C929: Anastasiia Safonova;Siham Tabik;Domingo Alcarazâ€_x0090_Segura;Alexey V. Rubtsov;Yuriy Maglinets;Francisco Herrera | D929: 2019 | E929: Detection of Fir Trees (Abies sibirica) Damaged by the Bark Beetle in Unmanned Aerial Vehicle Images with Deep Learning | F929: Remote Sensing | G929: NA | H929: 10.3390/rs11060643 | I929: NA | J929: ResearchRabbit | K929: drop
A930: Goodbody_Coops_White_etal_2019 | B930: Goodbody | C930: Tristan R.h. Goodbody;Nicholas C. Coops;Joanne C. White | D930: 2019 | E930: Digital Aerial Photogrammetry for Updating Area-Based Forest Inventories: A Review of Opportunities, Challenges, and Future Directions | F930: NA | G930: NA | H930: 10.1007/s40725-019-00087-2 | I930: NA | J930: ResearchRabbit | K930: drop
A931: Krause_Sanders_Mund_etal_2019 | B931: Krause | C931: Stuart Krause;Tanja G. M. Sanders;Janâ€“Peter Mund;Klaus Greve | D931: 2019 | E931: UAV-Based Photogrammetric Tree Height Measurement for Intensive Forest Monitoring | F931: Remote Sensing | G931: NA | H931: 10.3390/rs11070758 | I931: NA | J931: ResearchRabbit | K931: drop
... A1065: King_Kelly_Fletcher_etal_2022 | B1065: King | C1065: Fraser King;Richard Kelly;Christopher G. Fletcher | D1065: 2022 | E1065: Evaluation of LiDAR-derived Snow Depth Estimates from the iPhone 12 Pro | F1065: IEEE Geoscience and Remote Sensing Letters | G1065: NA | H1065: 10.1109/lgrs.2022.3166665 | I1065: NA | J1065: ResearchRabbit | K1065: drop
A1066: Hornung_NA | B1066: Hornung | C1066: Roman Hornung | D1066: NA | E1066: Ordinal Forests | F1066: Journal of Classification | G1066: NA | H1066: 10.1007/s00357-018-9302-x | I1066: NA | J1066: ResearchRabbit | K1066: drop
A1067: Billingsley_Visala_Dunn_etal_NA | B1067: Billingsley | C1067: John Billingsley;Arto Visala;Mark Dunn | D1067: NA | E1067: Robotics in Agriculture and Forestry | F1067: NA | G1067: NA | H1067: 10.1007/978-3-540-30301-5_47 | I1067: NA | J1067: ResearchRabbit | K1067: drop
A1068: Hillel_NA | B1068: Hillel | C1068: Daniel Hillel | D1068: NA | E1068: Evaporation from Bare Soil and Wind Erosion | F1068: NA | G1068: NA | H1068: 10.1016/b978-012348525-0/50021-5 | I1068: NA | J1068: ResearchRabbit | K1068: drop
A1069: Hamada_Kanat_Abiche_etal_NA | B1069: Hamada | C1069: Mohamed A. Hamada;Yeleussiz Kanat;Adejor Egahi Abiche | D1069: NA | E1069: Multi-Spectral Image Segmentation Based on the K-means Clustering | F1069: International journal of innovative technology and exploring engineering | G1069: NA | H1069: 10.35940/ijitee.k1596.129219 | I1069: NA | J1069: ResearchRabbit | K1069: drop
A1070: Segal_Haehnel_Thrun_etal_NA | B1070: Segal | C1070: A. Segal;D. Haehnel;Sebastian Thrun;S. Thrun | D1070: NA | E1070: Generalized-ICP | F1070: NA | G1070: NA | H1070: 10.15607/rss.2009.v.021 | I1070: NA | J1070: ResearchRabbit | K1070: drop
A1071: Wang_LÃ³pez-Lozano_Weiss_etal_2022 | B1071: Wang | C1071: Jingwen Wang;RaÃºl LÃ³pez-Lozano;Marie Weiss;Samuel Buis;Wenjuan Li;Shouyang Liu;FrÃ©dÃ©ric Baret;Jiahua Zhang | D1071: 2022 | E1071: Crop specific inversion of PROSAIL to retrieve green area index (GAI) from several decametric satellites using a Bayesian framework | F1071: Remote Sensing of Environment | G1071: NA | H1071: 10.1016/j.rse.2022.113085 | I1071: NA | J1071: ResearchRabbit | K1071: drop
A1072: Costantino_Vozza_Pepe_etal_2022 | B1072: Costantino | C1072: Domenica Costantino;Gabriele Vozza;Massimiliano Pepe;Vincenzo Saverio Alfio | D1072: 2022 | E1072: Smartphone LiDAR Technologies for Surveying and Reality Modelling in Urban Scenarios: Evaluation Methods, Performance and Challenges | F1072: Applied system innovation | G1072: NA | H1072: 10.3390/asi5040063 | I1072: NA | J1072: ResearchRabbit | K1072: drop
A1073: MatÃ©-GonzÃ¡lez_Pietra_Piras_etal_2022 | B1073: MatÃ©-GonzÃ¡lez | C1073: Miguel Ã_x0081_ngel MatÃ©-GonzÃ¡lez;Vincenzo Di Pietra;Marco Piras | D1073: 2022 | E1073: Evaluation of Different LiDAR Technologies for the Documentation of Forgotten Cultural Heritage under Forest Environments | F1073: Sensors | G1073: NA | H1073: 10.3390/s22166314 | I1073: NA | J1073: ResearchRabbit | K1073: drop
A1074: FernÃ¡ndez-Guisuraga_Calvo_SuÃ¡rezâ€_x0090_Seoane_etal_2022 | B1074: FernÃ¡ndez-Guisuraga | C1074: JosÃ© Manuel FernÃ¡ndez-Guisuraga;Leonor Calvo;Susana SuÃ¡rezâ€_x0090_Seoane;Carmen Quintano;Dar A. Roberts;Alfonso FernÃ¡ndez-Manso | D1074: 2022 | E1074: Comparison of Physical-Based Models to Measure Forest Resilience to Fire as a Function of Burn Severity | F1074: Remote Sensing | G1074: NA | H1074: 10.3390/rs14205138 | I1074: NA | J1074: ResearchRabbit | K1074: drop
A1075: Kharroubi_Poux_Ballouch_etal_2022 | B1075: Kharroubi | C1075: Abderrazzaq Kharroubi;Florent Poux;Zouhair Ballouch;Rafika Hajji;Roland Billen | D1075: 2022 | E1075: Three Dimensional Change Detection Using Point Clouds: A Review | F1075: Geomatics | G1075: NA | H1075: 10.3390/geomatics2040025 | I1075: NA | J1075: ResearchRabbit | K1075: drop
A1076: Kedron_Frazier_etal_2022 | B1076: Kedron | C1076: Peter Kedron;Amy E. Frazier | D1076: 2022 | E1076: How to Improve the Reproducibility, Replicability, and Extensibility of Remote Sensing Research | F1076: Remote Sensing | G1076: NA | H1076: 10.3390/rs14215471 | I1076: NA | J1076: ResearchRabbit | K1076: drop
A1077: Mikita_KrauskovÃ¡_HrÅ¯za_etal_2022 | B1077: Mikita | C1077: TomÃ¡Å¡ Mikita;Dominika KrauskovÃ¡;Petr HrÅ¯za;MiloÅ¡ Cibulka;ZdenÄ›k PatoÄ_x008d_ka | D1077: 2022 | E1077: Forest Road Wearing Course Damage Assessment Possibilities with Different Types of Laser Scanning Methods including New iPhone LiDAR Scanning Apps | F1077: Forests | G1077: NA | H1077: 10.3390/f13111763 | I1077: NA | J1077: ResearchRabbit | K1077: drop
A1078: Rodrigues_CamprubÃ­_Balaguer-Romano_etal_2022 | B1078: Rodrigues | C1078: Marcos Rodrigues;Ã€ngel Cunill CamprubÃ­;Rodrigo Balaguer-Romano;Celso J. Coco MegÃ­a;Francisco CastaÃ±ares;Julien Ruffault;Paulo M. Fernandes;VÃ­ctor Resco De Dios | D1078: 2022 | E1078: Drivers and implications of the extreme 2022 wildfire season in Southwest Europe | F1078: Science of The Total Environment | G1078: NA | H1078: 10.1016/j.scitotenv.2022.160320 | I1078: NA | J1078: ResearchRabbit | K1078: drop
A1079: Huerta_Marcos_FernÃ¡ndez-GarcÃ­a_etal_2022 | B1079: Huerta | C1079: Sara Huerta;Elena Marcos;VÃ­ctor FernÃ¡ndez-GarcÃ­a;Leonor Calvo | D1079: 2022 | E1079: Resilience of Mediterranean communities to fire depends on burn severity and type of ecosystem | F1079: NA | G1079: NA | H1079: 10.1186/s42408-022-00156-1 | I1079: NA | J1079: ResearchRabbit | K1079: drop
A1080: Surname_2008 | B1080: Surname | C1080: Bob Surname | D1080: 2008 | E1080: Forest Ecosystems | F1080: NA | G1080: NA | H1080: 10.56021/9780801888403 | I1080: NA | J1080: ResearchRabbit | K1080: drop
A1081: BÃ¶hm_Kanzian_2022 | B1081: BÃ¶hm | C1081: Stephan BÃ¶hm;Christian Kanzian | D1081: 2022 | E1081: A review on cable yarding operation performance and its assessment | F1081: NA | G1081: NA | H1081: 10.1080/14942119.2022.2153505 | I1081: NA | J1081: ResearchRabbit | K1081: drop
A1082: FernÃ¡ndezâ€_x0090_Guisuraga_Calvo_Roberts_etal_2023 | B1082: FernÃ¡ndezâ€_x0090_Guisuraga | C1082: JosÃ© Manuel FernÃ¡ndezâ€_x0090_Guisuraga;Leonor Calvo;Dar A. Roberts;Alfonso FernÃ¡ndezâ€“Manso | D1082: 2023 | E1082: Fractional vegetation cover ratio estimated from radiative transfer modeling outperforms spectral indices to assess fire severity in several Mediterranean plant communities | F1082: NA | G1082: NA | H1082: 10.1016/j.rse.2023.113542 | I1082: NA | J1082: ResearchRabbit | K1082: drop
... A1084: Heyerdahl_Brubaker_Agee_2001 | B1084: Heyerdahl | C1084: Emily K. Heyerdahl;Linda B. Brubaker;James K. Agee | D1084: 2001 | E1084: SPATIAL CONTROLS OF HISTORICAL FIRE REGIMES: A MULTISCALE EXAMPLE FROM THE INTERIOR WEST, USA | F1084: NA | G1084: NA | H1084: 10.1890/0012-9658(2001)082[0660:scohfr]2.0.co;2 | I1084: NA | J1084: ResearchRabbit | K1084: drop

Sheet 4_included_studies
A1: study_id | B1: first_author | C1: authors | D1: year | E1: title | F1: source | G1: pages | H1: issue | I1: volume | J1: type | K1: doi | L1: link_url | M1: dbase | N1: date_accessed
A2: Affek_Zachwatowicz_Sosnowska_etal_2017 | B2: Affek | C2: Affek, Andrzej Norbert; Zachwatowicz, Maria; Sosnowska, Agnieszka; Gerlée, Alina; Kiszka, Krzysztof | D2: 2017 | E2: Impacts of modern mechanised skidding on the natural and cultural heritage of the Polish Carpathian Mountains | F2: Forest Ecology and Management | G2: 391-403 | I2: 405 | J2: article | K2: https://doi.org/10.1016/j.foreco.2017.09.047 | L2: https://www.scopus.com/inward/record.uri?eid=2-s2.0-85030472101&doi=10.1016%2fj.foreco.2017.09.047&partnerID=40&md5=19ad50c4bc2f2318a4b70c90f20ec59b | M2: Scopus | N2: 45730.842
A3: Allen_Sorbel_2008 | B3: Allen | C3: Allen, Jennifer L.; Sorbel, Brian | D3: 2008 | E3: Assessing the differenced Normalized Burn Ratio's ability to map burn severity in the boreal forest and tundra ecosystems of Alaska's national parks | F3: International Journal of Wildland Fire | G3: 463 | H3: 4 | I3: 17 | J3: article | K3: https://doi.org/10.1071/wf08034 | L3: https://doi.org/10.1071/wf08034 | M3: OpenAlex | N3: 45730.765
A4: Baur_Friend_Pellegrini_2024 | B4: Baur | C4: Baur, Martin J.; Friend, Andrew D.; Pellegrini, Adam F. A. | D4: 2024 | E4: Widespread and systematic effects of fire on plant–soil water relations | F4: Nature Geoscience | G4: 1115-1120 | H4: 11 | I4: 17 | J4: article | K4: https://doi.org/10.1038/s41561-024-01563-6 | L4: https://www.scopus.com/inward/record.uri?eid=2-s2.0-85208926269&doi=10.1038%2fs41561-024-01563-6&partnerID=40&md5=7da423dfb2749435e3deab079f6aafdd | M4: Scopus | N4: 45733.882
A5: Beltrán-Marcos_Suárez-Seoane_Fernández-Guisuraga_etal_2021 | B5: Beltrán-Marcos | C5: Beltrán-Marcos, David; Suárez-Seoane, Susana; Fernández-Guisuraga, José Manuel; Fernández-García, Víctor; Marcos, Elena; Calvo, Leonor | D5: 2021 | E5: Relevance of UAV and Sentinel-2 data fusion for estimating topsoil organic carbon after forest fire | F5: Geoderma | G5: 116290 | I5: 430 | J5: article | K5: https://doi.org/10.3390/f12020179 | L5: https://doi.org/10.3390/f12020179 | M5: OpenAlex | N5: 45733.81
A6: Beltrán-Marcos_Suárez-Seoane_Fernández-Guisuraga_etal_2023 | B6: Beltrán-Marcos | C6: Beltrán-Marcos, David; Suárez-Seoane, Susana; Fernández-Guisuraga, José Manuel; Fernández-García, Víctor; Pinto, Rayo; García-Llamas, Paula; Calvo, Leonor | D6: 2023 | E6: Mapping soil burn severity at very high spatial resolution from unmanned aerial vehicles | F6: Forests | G6: 179 | H6: 2 | I6: 12 | J6: article | K6: https://doi.org/10.1016/j.geoderma.2022.116290 | L6: https://www.scopus.com/inward/record.uri?eid=2-s2.0-85143547946&doi=10.1016%2fj.geoderma.2022.116290&partnerID=40&md5=f1b894a19e66acf6192a77b0d72f1b43 | M6: Scopus | N6: 45735.659
A7: Bhatnagar_Puliti_Talbot_etal_2022 | B7: Bhatnagar | C7: Bhatnagar, Saheba; Puliti, Stefano; Talbot, Bruce; Heppelmann, Joachim Bernd; Breidenbach, Johannes; Astrup, Rasmus | D7: 2022 | E7: Mapping wheel-ruts from timber harvesting operations using deep learning techniques in drone imagery | F7: Forestry: An International Journal of Forest Research | G7: cpac023 | J7: article | K7: https://doi.org/10.1093/forestry/cpac023 | L7: https://doi.org/10.1093/forestry/cpac023 | M7: OpenAlex | N7: 45631.889
A8: Bourgeau-Chavez_Kasischke_Riordan_etal_2007 | B8: Bourgeau-Chavez | C8: Bourgeau‐Chavez, L. L.; Kasischke, E. S.; Riordan, K.; Brunzell, S.; Nolan, M.; Hyer, E.; Slawski, J.; Medvecz, M.; Walters, T.; Ames, S. | D8: 2007 | E8: Remote monitoring of spatial and temporal surface soil moisture in fire disturbed boreal forest ecosystems with ERS SAR imagery | F8: International Journal of Remote Sensing | G8: 2133-2162 | H8: 10 | I8: 28 | J8: article | K8: https://doi.org/10.1080/01431160600976061 | L8: https://doi.org/10.1080/01431160600976061 | M8: OpenAlex | N8: 45735.68
A9: Cambi_Giannetti_Bottalico_etal_2018 | B9: Cambi | C9: Cambi, M; Giannetti, F; Bottalico, F; Travaglini, D; Nordfjell, T; Chirici, G; Marchi, E | D9: 2018 | E9: Estimating machine impact on strip roads via close-range photogrammetry and soil parameters: A case study in central Italy | F9: iForest - Biogeosciences and Forestry | G9: 148-154 | H9: 1 | I9: 11 | J9: article | K9: https://doi.org/10.3832/ifor2590-010 | L9: https://www.scopus.com/inward/record.uri?eid=2-s2.0-85042373493&doi=10.3832%2fifor2590-010&partnerID=40&md5=036b72451714e07d37c137769d2b2a64 | M9: Scopus | N9: 45733.71
A10: Campbell_White_Arp_etal_2013 | B10: Campbell | C10: David M.h. M.h. Campbell;Barry White;Paul A. Arp | D10: 2013 | E10: Modeling and mapping soil resistance to penetration and rutting using LiDAR-derived digital elevation data | F10: Journal of Soil and Water Conservation | G10: 460-473 | I10: 68 | J10: article | K10: http://dx.doi.org/10.2489/jswc.68.6.460 | L10: https://www.researchgate.net/publication/271300317_Modeling_and_mapping_Soil_resistance_to_penetration_and_rutting_using_LiDAR-derived_digital_elevation_data | M10: ResearchRabbit | N10: 45838
A11: Chafer_2008 | B11: Chafer | C11: Chafer C.J. | D11: 2008 | E11: A comparison of fire severity measures: An Australian example and implications for predicting major areas of soil erosion | F11: Catena | G11: 235-245 | H11: 3 | I11: 74 | J11: article | K11: https://doi.org/10.1016/j.catena.2007.12.005 | L11: https://www.scopus.com/inward/record.uri?eid=2-s2.0-48649099656&doi=10.1016%2fj.catena.2007.12.005&partnerID=40&md5=ba7b1c9bde68c98770520520f43b7f45 | M11: Scopus | N11: 45838
A12: Chasmer_Hopkinson_Petrone_etal_2017 | B12: Chasmer | C12: Chasmer, L. E.; Hopkinson, C. D.; Petrone, R. M.; Sitar, M. | D12: 2017 | E12: Using multitemporal and multispectral airborne LiDAR to assess depth of peat loss and correspondence with a new Active Normalized Burn Ratio for wildfires | F12: Geophysical Research Letters | H12: 23 | I12: 44 | J12: article | K12: https://doi.org/10.1002/2017GL075488 | L12: https://www.scopus.com/inward/record.uri?eid=2-s2.0-85040089813&doi=10.1002%2f2017GL075488&partnerID=40&md5=fd7de5a5a4e602489ddd29f51ab8213e | M12: Scopus | N12: 45733.723
A13: Conrad-Rooney_Barker_Pasquarella_etal_2021 | B13: Conrad-Rooney | C13: Conrad-Rooney, Emma; Barker Plotkin, Audrey; Pasquarella, Valerie J; Elkinton, Joseph; Chandler, Jennifer L; Matthes, Jaclyn Hatala | D13: 2021 | E13: Defoliation severity is positively related to soil solution nitrogen availability and negatively related to soil nitrogen concentrations following a multi-year invasive insect irruption | F13: AoB PLANTS | G13: plaa059 | H13: 6 | I13: 12 | J13: article | K13: https://doi.org/10.1093/aobpla/plaa059 | L13: https://www.scopus.com/inward/record.uri?eid=2-s2.0-85099435960&doi=10.1093%2faobpla%2fplaa059&partnerID=40&md5=93c8bf37f28030b7dcfef8e743258eb6 | M13: Scopus | N13: 45737.654
A14: Dąbek_Żmuda_Szczepański_etal_2018 | B14: Dąbek | C14: Dąbek, Paweł B.; Żmuda, Romuald; Szczepański, Jakub; Ćmielewski, Bartłomiej | D14: 2018 | E14: Evaluation of water soil erosion processes in forest areas in the Western Sudetes using terrestrial laser scanning and GIS tools | F14: E3S Web of Conferences | G14: 26 | I14: 44 | J14: conference-paper | K14: https://doi.org/10.1051/e3sconf/20184400026 | L14: https://www.scopus.com/inward/record.uri?eid=2-s2.0-85051076068&doi=10.1051%2fe3sconf%2f20184400026&partnerID=40&md5=29beab9867d45df5817ff86be78d2a83 | M14: Scopus | N14: 45733.725
A15: Deligiannakis_Pallikarakis_Papanikolaou_etal_2021 | B15: Deligiannakis | C15: Deligiannakis, Georgios; Pallikarakis, Aggelos; Papanikolaou, Ioannis; Alexiou, Simoni; Reicherter, Klaus | D15: 2021 | E15: Detecting and monitoring early post-fire sliding phenomena using UAV–SfM photogrammetry and t-LiDAR-derived point clouds | F15: Fire | G15: 87 | H15: 4 | I15: 4 | J15: article | K15: https://doi.org/10.3390/fire4040087 | L15: https://www.scopus.com/inward/record.uri?eid=2-s2.0-85120166359&doi=10.3390%2ffire4040087&partnerID=40&md5=ebd04af5e35df3b196faa5b8c867d5b9 | M15: Scopus | N15: 45733.781
A16: Doerr_Shakesby_Blake_etal_2006 | B16: Doerr | C16: Stefan H. Doerr;Richard A. Shakesby;William H. Blake;Chris J. Chafer;Geoff S. Humphreys;Peter Wallbrink | D16: 2006 | E16: Effects of differing wildfire severities on soil wettability and implications for hydrological response | F16: Journal of Hydrology | G16: 295-311 | H16: 45661 | J16: article | K16: https://doi.org/10.1016/j.jhydrol.2005.06.038 | M16: ResearchRabbit | N16: 45840
A17: Dubé_Berch_2013 | B17: Dubé | C17: Dubé, Stéphane; Berch, Shannon | D17: 2013 | E17: Monitoring soil disturbance on salvaged areas within the mountain pine beetle infestation using digital imagery | F17: Journal of Applied Remote Sensing | G17: 73541 | H17: 1 | I17: 7 | J17: article | K17: https://doi.org/10.1117/1.jrs.7.073541 | L17: https://doi.org/10.1117/1.jrs.7.073541 | M17: OpenAlex | N17: 45733.888
A18: Ferenčík_Dudáková_Kardoš_etal_2022 | B18: Ferenčík | C18: Ferenčík, Michal; Dudáková, Zuzana; Kardoš, Miroslav; Sivák, Miroslav; Merganičová, Katarína; Merganič, Ján | D18: 2022 | E18: Measuring soil surface changes after traffic of various wheeled skidders with close-range photogrammetry | F18: Forests | G18: 976 | H18: 7 | I18: 13 | J18: article | K18: https://doi.org/10.3390/f13070976 | L18: https://www.scopus.com/inward/record.uri?eid=2-s2.0-85133207229&doi=10.3390%2ff13070976&partnerID=40&md5=c2ff3a85d6fa42a7df3976555097eb58 | M18: Scopus | N18: 45733.789
A19: Fernández_Fernández-Alonso_Vega_etal_2021 | B19: Fernández | C19: Fernández, Cristina; Fernández-Alonso, José M.; Vega, José A.; Fontúrbel, Teresa; Llorens, Rafael; Sobrino, José A. | D19: 2021 | E19: Exploring the use of spectral indices to assess alterations in soil properties in pine stands affected by crown fire in Spain | F19: Fire Ecology | G19: 2 | H19: 1 | I19: 17 | J19: article | K19: https://doi.org/10.1186/s42408-020-00089-7 | L19: https://www.scopus.com/inward/record.uri?eid=2-s2.0-85100187139&doi=10.1186%2fs42408-020-00089-7&partnerID=40&md5=8f895d1dec6d0cfa5bbb4326bccb76de | M19: Scopus | N19: 45733.785
A20: Fernandez-Garci­a_Santamarta_Fernandez-Manso_etal_2018 | B20: Fernandez-GarcÃia | C20: VÃ­ctor FernÃ¡ndez-GarcÃ­a;MÃ³nica Santamarta;Alfonso FernÃ¡ndezâ€“Manso;Dar A. Roberts;Carmen Quintano;Elena Marcos;Leonor Calvo | D20: 2018 | E20: Burn severity metrics in fire-prone pine ecosystems along a climatic gradient using Landsat imagery | F20: Remote Sensing of Environment | G20: 205-217 | I20: 206 | J20: article | K20: https://doi.org/10.1016/j.rse.2017.12.029 | L20: https://www.sciencedirect.com/science/article/pii/S0034425717306041 | M20: ResearchRabbit | N20: 45840
A21: Fernández-Guisuraga_Marcos_Suárez-Seoane_etal_2022 | B21: Fernández-Guisuraga | C21: Fernández-Guisuraga, José Manuel; Marcos, Elena; Suárez-Seoane, Susana; Calvo, Leonor | D21: 2022 | E21: ALOS-2 L-band SAR backscatter data improves the estimation and temporal transferability of wildfire effects on soil properties under different post-fire vegetation responses | F21: Science of The Total Environment | G21: 156852 | I21: 842 | J21: article | K21: https://doi.org/10.1016/j.scitotenv.2022.156852 | L21: https://www.scopus.com/inward/record.uri?eid=2-s2.0-85132935489&doi=10.1016%2fj.scitotenv.2022.156852&partnerID=40&md5=8277b1e9c58f8fccde560a535798fd36 | M21: Scopus | N21: 45733.797
A22: French_Kasischke_Bourgeau-Chavez_etal_1996 | B22: French | C22: French, N. H. F.; Kasischke, E. S.; Bourgeau-Chavez, L. L.; Harrell, P. A. | D22: 1996 | E22: Sensitivity of ERS-1 SAR to variations in soil water in fire-disturbed boreal forest ecosystems | F22: International Journal of Remote Sensing | G22: 3037-3053 | H22: 15 | I22: 17 | J22: article | K22: https://doi.org/10.1080/01431169608949126 | L22: https://doi.org/10.1080/01431169608949126 | M22: OpenAlex
A23: Giannetti_Chirici_Travaglini_etal_2017 | B23: Giannetti | C23: Giannetti, Francesca; Chirici, Gherardo; Travaglini, Davide; Bottalico, Francesca; Marchi, Enrico; Cambi, Martina | D23: 2017 | E23: Assessment of soil disturbance caused by forest operations by means of portable laser scanner and soil physical parameters | F23: Soil Science Society of America Journal | G23: 1577-1585 | H23: 6 | I23: 81 | J23: analytic | K23: https://doi.org/10.2136/sssaj2017.02.0051 | L23: https://research.ebsco.com/linkprocessor/plink?id=4378dfed-f1dc-38de-9046-ad9e964e6f49 | M23: EBSCOhost | N23: 45728.931
A24: Godziek_2024 | B24: Godziek | C24: Godziek, Janusz | D24: 2024 | E24: Root plates of uprooted trees − Automatic detection and biotransport estimation using LiDAR data and field mapping | F24: International Journal of Applied Earth Observation and Geoinformation | G24: 103992 | I24: 131 | J24: article | K24: https://doi.org/10.1016/j.jag.2024.103992 | L24: https://www.scopus.com/inward/record.uri?eid=2-s2.0-85196815799&doi=10.1016%2fj.jag.2024.103992&partnerID=40&md5=88629a03095eeabeae591081345757d2 | M24: Scopus | N24: 45733.875
A25: Guilinger_Foufoula-Georgiou_Gray_etal_2023 | B25: Guilinger | C25: Guilinger, James J.; Foufoula‐Georgiou, Efi; Gray, Andrew B.; Randerson, James T.; Smyth, Padhraic; Barth, Nicolas C.; Goulden, Michael L. | D25: 2023 | E25: Predicting postfire sediment yields of small steep catchments using airborne LiDAR differencing | F25: Geophysical Research Letters | G25: e2023GL104626 | H25: 16 | I25: 50 | J25: article | K25: https://doi.org/10.1029/2023gl104626 | L25: https://doi.org/10.1029/2023gl104626 | M25: OpenAlex | N25: 45733.922
A26: Haas_Hagge_Schack-Kirchner_etal_2016 | B26: Haas | C26: Haas, Johannes; Hagge Ellhöft, Katrin; Schack-Kirchner, Helmer; Lang, Friederike | D26: 2016 | E26: Using photogrammetry to assess rutting caused by a forwarder—A comparison of different tires and bogie tracks | F26: Soil and Tillage Research | G26: 14-20 | I26: 163 | J26: article | K26: https://doi.org/10.1016/j.still.2016.04.008 | L26: https://www.scopus.com/inward/record.uri?eid=2-s2.0-84968750687&doi=10.1016%2fj.still.2016.04.008&partnerID=40&md5=f953793acffae37ad9cc2ac67e5765ee | M26: Scopus | N26: 45730.822
A27: Heppelmann_Talbot_Antòn-Fernández_etal_2022 | B27: Heppelmann | C27: Heppelmann, J. B.; Talbot, B.; Antón Fernández, C.; Astrup, R. | D27: 2022 | E27: Depth-to-water maps as predictors of rut severity in fully mechanized harvesting operations | F27: International Journal of Forest Engineering | G27: 108-118 | H27: 2 | I27: 33 | J27: article | K27: https://doi.org/10.1080/14942119.2022.2044724 | L27: https://doi.org/10.1080/14942119.2022.2044724 | M27: OpenAlex | N27: 45734.558
A28: Hoy_French_Turetsky_etal_2008 | B28: Hoy | C28: Hoy, Elizabeth E.; French, Nancy H. F.; Turetsky, Merritt R.; Trigg, Simon N.; Kasischke, Eric S. | D28: 2008 | E28: Evaluating the potential of Landsat TM/ETM+ imagery for assessing fire severity in Alaskan black spruce forests | F28: International Journal of Wildland Fire | G28: 500 | H28: 4 | I28: 17 | J28: article | K28: https://doi.org/10.1071/wf08107 | L28: https://doi.org/10.1071/wf08107 | M28: OpenAlex | N28: 45735.881
A29: Hudak_Morgan_Bobbitt_etal_2007 | B29: Hudak | C29: Hudak, Andrew T.; Morgan, Penelope; Bobbitt, Michael J.; Smith, Alistair M. S.; Lewis, Sarah A.; Lentile, Leigh B.; Robichaud, Peter R.; Clark, Jess T.; McKinley, Randy A. | D29: 2007 | E29: The relationship of multispectral satellite imagery to immediate fire effects | F29: Fire Ecology | G29: 64-90 | H29: 1 | I29: 3 | J29: article | K29: https://doi.org/10.4996/fireecology.0301064 | L29: https://research.fs.usda.gov/treesearch/29489 | M29: USFSTreesearch | N29: 45736.715
A30: Hudak_Robichaud_Evans_etal_2004 | B30: Hudak | C30: Hudak, Andrew T.; Robichaud, Peter R.; Evans, Jeffrey S.; Clark, Jess; Lannom, Keith; Morgan, Penelope; Stone, Carter | D30: 2004 | E30: Field validation of Burned Area Reflectance Classification (BARC) products for post fire assessment | F30: American Society of Photogrammetry and Remote Sensing Conference Proceedings | J30: conference-paper | L30: https://research.fs.usda.gov/treesearch/23530 | M30: USFSTreesearch
A31: Hudak_Robichaud_Jain_etal_2004 | B31: Hudak | C31: Hudak, Andrew; Robichaud, Peter R.; Jain, Terrie; Morgan, Penelope; Stone, Carter; Clark, Jess | D31: 2004 | E31: The relationship of field burn severity measures to satellite-derived Burned Area Reflectance Classification (BARC) maps | F31: American Society of Photogrammetry and Remote Sensing Conference Proceedings | J31: conference-paper | L31: https://research.fs.usda.gov/treesearch/26195 | M31: USFSTreesearch
A32: Kadakci Koca_Küçükuysal_Gül_etal_2024 | B32: Kadakci | C32: Kadakci Koca, Tümay; Küçükuysal, Ceren; Gül, Murat; Esetlili, Tolga | D32: 2024 | E32: A comprehensive approach to soil burn severity mapping for erosion susceptibility assessment | F32: CATENA | G32: 108302 | I32: 245 | J32: article | K32: https://doi.org/10.1016/j.catena.2024.108302 | L32: https://www.scopus.com/inward/record.uri?eid=2-s2.0-85201004093&doi=10.1016%2fj.catena.2024.108302&partnerID=40&md5=276b36f6a250d5e83dc24389fcbc81c9 | M32: Scopus | N32: 45730.646
A33: Kadakci̇ Koca_2023 | B33: KadakciÌ‡ | C33: Kadakci̇ Koca, Tümay | D33: 2023 | E33: A statistical approach to site-specific thresholding for burn severity maps using bi-temporal Landsat-8 images | F33: Earth Science Informatics | G33: 1313-1327 | H33: 2 | I33: 16 | J33: article | K33: https://doi.org/10.1007/s12145-023-00980-2 | L33: https://www.scopus.com/inward/record.uri?eid=2-s2.0-85148611463&doi=10.1007%2fs12145-023-00980-2&partnerID=40&md5=2dc0653d7a5be0f2db22530a1ccc0f87 | M33: Scopus | N33: 45730.805
A34: Kim_Kim_Ha_etal_2023 | B34: Kim | C34: Kim, Jeongjae; Kim, Ikhyun; Ha, Eugene; Choi, Byoungkoo | D34: 2023 | E34: UAV photogrammetry for soil surface deformation detection in a timber harvesting area, South Korea | F34: Forests | G34: 980 | H34: 5 | I34: 14 | J34: article | K34: https://doi.org/10.3390/f14050980 | L34: https://www.scopus.com/inward/record.uri?eid=2-s2.0-85160741835&doi=10.3390%2ff14050980&partnerID=40&md5=e773b08423b8124135f0d3c63e38f6bf | M34: Scopus | N34: 45733.812
A35: Kim_Seo_Woo_etal_2025 | B35: Kim | C35: Kim, Ikhyun; Seo, Jaewon; Woo, Heesung; Choi, Byoungkoo | D35: 2025 | E35: Assessing rutting and soil compaction caused by wood extraction using traditional and remote sensing methods | F35: Forests | G35: 86 | H35: 1 | I35: 16 | J35: article | K35: https://doi.org/10.3390/f16010086 | L35: https://www.scopus.com/inward/record.uri?eid=2-s2.0-85216026180&doi=10.3390%2ff16010086&partnerID=40&md5=362110f118dc038a9b299cc7affe6419 | M35: Scopus | N35: 45681.812
A36: Kokaly_Rockwell_Haire_etal_2007 | B36: Kokaly | C36: Kokaly, Raymond F.; Rockwell, Barnaby W.; Haire, Sandra L.; King, Trude V.V. | D36: 2007 | E36: Characterization of post-fire surface cover, soils, and burn severity at the Cerro Grande Fire, New Mexico, using hyperspectral and multispectral remote sensing | F36: Remote Sensing of Environment | G36: 305-325 | H36: 3 | I36: 106 | J36: article | K36: https://doi.org/10.1016/j.rse.2006.08.006 | L36: https://www.scopus.com/inward/record.uri?eid=2-s2.0-33846331168&doi=10.1016%2fj.rse.2006.08.006&partnerID=40&md5=71b5bc6f311c16f22b0a2780c5b88b71 | M36: Scopus | N36: 45730.749
A37: Koren_Slancik_Suchomel_etal_2014 | B37: Koren | C37: Milan KoreÅˆ;M. Koren;M. SlanÄ_x008d_Ã­k;Josef Suchomel;J. Dubina | D37: 2014 | E37: Use of terrestrial laser scanning to evaluate the spatial distribution of soil disturbance by skidding operations | F37: Iforest - Biogeosciences and Forestry | G37: 386-393 | H37: 3 | I37: 8 | J37: article | K37: https://doi.org/10.3832/ifor1165-007 | L37: https://iforest.sisef.org/contents/?id=ifor1165-007# | M37: ResearchRabbit | N37: 45828.588
A38: Kubiak_Spiralski_Pompeu_etal_2024 | B38: Kubiak | C38: Kubiak, Katarzyna; Spiralski, Marcin; Pompeu, Joao; Levavasseur, Vincent; Wawer, Rafał | D38: 2024 | E38: Advances in remote sensing for monitoring soil conditions in forest ecosystems: Techniques, challenges, and applications | F38: Transactions on Aerospace Research | G38: 45670 | H38: 4 | I38: 2024 | J38: article | K38: https://doi.org/10.2478/tar-2024-0019 | L38: https://doi.org/10.2478/tar-2024-0019 | M38: OpenAlex | N38: 45721.897
A39: Latterini_Venanzi_Tocci_etal_2020 | B39: Latterini | C39: Latterini, Francesco; Venanzi, Rachele; Tocci, Damiano; Moschetti, Federico; Picchio, Rodolfo | D39: 2020 | E39: Comparing accuracy of three remote sensing methods to evaluate soil impact related to forest operations | F39: The 1st International Electronic Conference on Forests&mdash;Forests for a Better Future: Sustainability, Innovation, Interdisciplinarity | G39: 59 | J39: article | K39: https://doi.org/10.3390/iecf2020-07954 | L39: https://doi.org/10.3390/iecf2020-07954 | M39: OpenAlex | N39: 45733.89
A40: Lee_Elliott_Tiansawat_2023 | B40: Lee | C40: Lee, Kyuho; Elliott, Stephen; Tiansawat, Pimonrat | D40: 2023 | E40: Use of drone RGB imagery to quantify indicator variables of tropical-forest-ecosystem degradation and restoration | F40: Forests | G40: 586 | H40: 3 | I40: 14 | J40: article | K40: https://doi.org/10.3390/f14030586 | L40: https://www.scopus.com/inward/record.uri?eid=2-s2.0-85151317509&doi=10.3390%2ff14030586&partnerID=40&md5=2c35118cf95a3946c8bb43f1c60d8a8f | M40: Scopus | N40: 45736.638
A41: Lewis_Hudak_Ottmar_etal_2011 | B41: Lewis | C41: Lewis, Sarah A.; Hudak, Andrew T.; Ottmar, Roger D.; Robichaud, Peter R.; Lentile, Leigh B.; Hood, Sharon M.; Cronan, James B.; Morgan, Penny | D41: 2011 | E41: Using hyperspectral imagery to estimate forest floor consumption from wildfire in boreal forests of Alaska, USA | F41: International Journal of Wildland Fire | G41: 255 | H41: 2 | I41: 20 | J41: article | K41: https://doi.org/10.1071/wf09081 | L41: https://doi.org/10.1071/wf09081 | M41: OpenAlex | N41: 45730.637
A42: Lewis_Hudak_Robichaud_etal_2017 | B42: Lewis | C42: Lewis, Sarah A.; Hudak, Andrew T.; Robichaud, Peter R.; Morgan, Penelope; Satterberg, Kevin L.; Strand, Eva K.; Smith, Alistair M. S.; Zamudio, Joseph A.; Lentile, Leigh B. | D42: 2017 | E42: Indicators of burn severity at extended temporal scales: A decade of ecosystem response in mixed-conifer forests of western Montana | F42: International Journal of Wildland Fire | G42: 755 | H42: 9 | I42: 26 | J42: article | K42: https://doi.org/10.1071/WF17019 | L42: https://research.fs.usda.gov/treesearch/55517 | M42: USFSTreesearch | N42: 45736.758
A43: Lewis_Robichaud_Archer_etal_2023 | B43: Lewis | C43: Lewis, Sarah A.; Robichaud, Peter R.; Archer, Vince A.; Hudak, Andrew T.; Eitel, Jan U. H.; Strand, Eva K. | D43: 2023 | E43: Informing sustainable forest management: Remote sensing strategies for assessing soil disturbance after wildfire and salvage logging | F43: Forests | G43: 2218 | H43: 11 | I43: 14 | J43: article | K43: https://doi.org/10.3390/f14112218 | L43: https://www.scopus.com/inward/record.uri?eid=2-s2.0-85178337764&doi=10.3390%2ff14112218&partnerID=40&md5=bca91638a589bee8468b5679b483373a | M43: Scopus | N43: 45593.777
A44: Lewis_Robichaud_Elliot_etal_2004 | B44: Lewis | C44: Lewis, Sarah A.; Robichaud, Peter R.; Elliot, William J.; Frazier, Bruce E.; Wu, Joan Q. | D44: 2004 | E44: Hyperspectral remote sensing of postfire soil properties | F44: American Society of Photogrammetry and Remote Sensing Conference Proceedings | J44: conference-paper | L44: https://research.fs.usda.gov/treesearch/23527 | M44: USFSTreesearch
A45: Lewis_Robichaud_Hudak_etal_2012 | B45: Lewis | C45: Lewis, Sarah A.; Robichaud, Peter R.; Hudak, Andrew T.; Austin, Brian; Liebermann, Robert J. | D45: 2012 | E45: Utility of remotely sensed imagery for assessing the impact of salvage logging after forest fires | F45: Remote Sensing | G45: 2112-2132 | H45: 7 | I45: 4 | J45: article | K45: https://doi.org/10.3390/rs4072112 | L45: https://research.fs.usda.gov/treesearch/41111 | M45: USFSTreesearch | N45: 45736.767
A46: Llorens_Sobrino_Fernández_etal_2024 | B46: Llorens | C46: Llorens, Rafael; Sobrino, José Antonio; Fernández, Cristina; Fernández-Alonso, José M.; Vega, José Antonio | D46: 2024 | E46: Soil burn severity assessment using Sentinel-2 and radiometric measurements | F46: Fire | G46: 487 | H46: 12 | I46: 7 | J46: article | K46: https://doi.org/10.3390/fire7120487 | L46: https://www.scopus.com/inward/record.uri?eid=2-s2.0-85213458686&doi=10.3390%2ffire7120487&partnerID=40&md5=9e96b2376d83f126c38f6d1144225aff | M46: Scopus | N46: 45730.643
A47: Mallinis_Maris_Kalinderis_etal_2009 | B47: Mallinis | C47: Mallinis, G.; Maris, F.; Kalinderis, I.; Koutsias, N. | D47: 2009 | E47: Assessment of post-fire soil erosion risk in fire-affected watersheds using remote sensing and GIS | F47: GIScience & Remote Sensing | G47: 388-410 | H47: 4 | I47: 46 | J47: article | K47: https://doi.org/10.2747/1548-1603.46.4.388 | L47: https://www.scopus.com/inward/record.uri?eid=2-s2.0-76149124511&doi=10.2747%2f1548-1603.46.4.388&partnerID=40&md5=d4f4c28e0aa746ee30262b840eb0a841 | M47: Scopus | N47: 45730.821
A48: Marcos_Fernández-García_Fernández-Manso_etal_2018 | B48: Marcos | C48: Elena Marcos;VÃ­ctor FernÃ¡ndez-GarcÃ­a;Alfonso FernÃ¡ndezâ€“Manso;Dar A. Roberts;Carmen Quintano;L. Valbuena;Reyes TÃ¡rrega;E. Luisâ€_x0090_Calabuig;Leonor Calvo | D48: 2018 | E48: Evaluation of Composite Burn Index and Land Surface Temperature for Assessing Soil Burn Severity in Mediterranean Fire-Prone Pine Ecosystems | F48: Forests | G48: 494 | H48: 8 | I48: 9 | J48: article | K48: https://doi.org/10.3390/f9080494 | L48: https://www.mdpi.com/1999-4907/9/8/494 | M48: ResearchRabbit | N48: 45835.635
A49: Marquì­nez_Wozniak_Fernández_etal_2008 | B49: Marquì­nez | C49: Marquínez, J.; Wozniak, E.; Fernández, S.; Martínez, R. | D49: 2008 | E49: Analysis of the evolution of soil erosion classes using multitemporal Landsat imagery | F49: International Journal of Wildland Fire | G49: 549 | H49: 5 | I49: 17 | J49: article | K49: https://doi.org/10.1071/wf06138 | L49: https://doi.org/10.1071/wf06138 | M49: OpenAlex | N49: 45733.919
A50: Marra_Cambi_Fernandez-Lacruz_etal_2018 | B50: Marra | C50: Marra, Elena; Cambi, Martina; Fernandez-Lacruz, Raul; Giannetti, Francesca; Marchi, Enrico; Nordfjell, Tomas | D50: 2018 | E50: Photogrammetric estimation of wheel rut dimensions and soil compaction after increasing numbers of forwarder passes | F50: Scandinavian Journal of Forest Research | G50: 613-620 | H50: 6 | I50: 33 | J50: review | K50: https://doi.org/10.1080/02827581.2018.1427789 | L50: https://www.scopus.com/inward/record.uri?eid=2-s2.0-85041541415&doi=10.1080%2f02827581.2018.1427789&partnerID=40&md5=0868e39f070377d79627a7d5d80d82cb | M50: Scopus | N50: 45733.725
A51: Marra_Laschi_Fabiano_etal_2022 | B51: Marra | C51: Marra, Elena; Laschi, Andrea; Fabiano, Fabio; Foderi, Cristiano; Neri, Francesco; Mastrolonardo, Giovanni; Nordfjell, Tomas; Marchi, Enrico | D51: 2022 | E51: Impacts of wood extraction on soil: Assessing rutting and soil compaction caused by skidding and forwarding by means of traditional and innovative methods | F51: European Journal of Forest Research | G51: 71-86 | H51: 1 | I51: 141 | J51: article | K51: https://doi.org/10.1007/s10342-021-01420-w | L51: https://www.scopus.com/inward/record.uri?eid=2-s2.0-85119186195&doi=10.1007%2fs10342-021-01420-w&partnerID=40&md5=232f9047e4b1b12e76469724df96b79d | M51: Scopus | N51: 45733.79
A52: Marra_Wictorsson_Bohlin_etal_2021 | B52: Marra | C52: Marra, Elena; Wictorsson, Rasmus; Bohlin, Jonas; Marchi, Enrico; Nordfjell, Tomas | D52: 2021 | E52: Remote measuring of the depth of wheel ruts in forest terrain using a drone | F52: International Journal of Forest Engineering | G52: 224-234 | H52: 3 | I52: 32 | J52: article | K52: https://doi.org/10.1080/14942119.2021.1916228 | L52: https://www.scopus.com/inward/record.uri?eid=2-s2.0-85137999337&doi=10.1080%2f14942119.2021.1916228&partnerID=40&md5=5f5a066a331202018f9ab4d449a2d370 | M52: Scopus | N52: 45733.772
A53: McNeil_Beurs_Eshleman_etal_2007 | B53: McNeil | C53: McNeil, Brenden E.; De Beurs, Kirsten M.; Eshleman, Keith N.; Foster, Jane R.; Townsend, Philip A. | D53: 2007 | E53: Maintenance of ecosystem nitrogen limitation by ephemeral forest disturbance: An assessment using MODIS, Hyperion, and Landsat ETM+ | F53: Geophysical Research Letters | G53: 2007GL031387 | H53: 19 | I53: 34 | J53: article | K53: https://doi.org/10.1029/2007gl031387 | L53: https://doi.org/10.1029/2007gl031387 | M53: OpenAlex | N53: 45733.928
A54: Melander_Ritala_2018 | B54: Melander | C54: Melander, Lari; Ritala, Risto | D54: 2018 | E54: Time-of-flight imaging for assessing soil deformations and improving forestry vehicle tracking accuracy | F54: International Journal of Forest Engineering | G54: 63-73 | H54: 2 | I54: 29 | J54: article | K54: https://doi.org/10.1080/14942119.2018.1421341 | L54: https://doi.org/10.1080/14942119.2018.1421341 | M54: OpenAlex | N54: 45736.674
A55: Melendy_Hagen_Sullivan_etal_2018 | B55: Melendy | C55: Melendy, L.; Hagen, S.C.; Sullivan, F.B.; Pearson, T.R.H.; Walker, S.M.; Ellis, P.; Kustiyo; Sambodo, Ari Katmoko; Roswintiarti, O.; Hanson, M.A.; Klassen, A.W.; Palace, M.W.; Braswell, B.H.; Delgado, G.M. | D55: 2018 | E55: Automated method for measuring the extent of selective logging damage with airborne LiDAR data | F55: ISPRS Journal of Photogrammetry and Remote Sensing | G55: 228-240 | I55: 139 | J55: article | K55: https://doi.org/10.1016/j.isprsjprs.2018.02.022 | L55: https://www.scopus.com/inward/record.uri?eid=2-s2.0-85044441285&doi=10.1016%2fj.isprsjprs.2018.02.022&partnerID=40&md5=068999a846f5b8cf16be79b20c029f84 | M55: Scopus | N55: 45730.831
A56: Mohieddinne_Brasseur_Gallet-Moron_etal_2023 | B56: Mohieddinne | C56: Mohieddinne, Hamza; Brasseur, Boris; Gallet‐Moron, Emilie; Lenoir, Jonathan; Spicher, Fabien; Kobaissi, Ahmad; Horen, Hélène | D56: 2022 | E56: Assessment of soil compaction and rutting in managed forests through an airborne LiDAR technique | F56: Land Degradation & Development | G56: 1558-1569 | H56: 5 | I56: 34 | J56: article | K56: https://doi.org/10.1002/ldr.4553 | L56: https://doi.org/10.1002/ldr.4553 | M56: OpenAlex | N56: 45733.92
A57: Mohieddinne_Brasseur_Spicher_etal_2019 | B57: Mohieddinne | C57: Mohieddinne, Hamza; Brasseur, Boris; Spicher, Fabien; Gallet-Moron, Emilie; Buridant, Jérôme; Kobaissi, Ahmad; Horen, Hélène | D57: 2019 | E57: Physical recovery of forest soil after compaction by heavy machines, revealed by penetration resistance over multiple decades | F57: Forest Ecology and Management | G57: 117472 | I57: 449 | J57: article | K57: https://doi.org/10.1016/j.foreco.2019.117472 | L57: https://www.scopus.com/inward/record.uri?eid=2-s2.0-85069650177&doi=10.1016%2fj.foreco.2019.117472&partnerID=40&md5=fc9e63bc82d557235b81804f4dbf61b8 | M57: Scopus | N57: 45737.647
A58: Morgan_Keane_Dillon_etal_2014 | B58: Morgan | C58: Morgan, Penelope; Keane, Robert E.; Dillon, Gregory K.; Jain, Theresa B.; Hudak, Andrew T.; Karau, Eva C.; Sikkink, Pamela G.; Holden, Zachary A.; Strand, Eva K. | D58: 2014 | E58: Challenges of assessing fire and burn severity using field measures, remote sensing and modelling | F58: International Journal of Wildland Fire | G58: 1045 | H58: 8 | I58: 23 | J58: article | K58: https://doi.org/10.1071/WF13058 | L58: https://research.fs.usda.gov/treesearch/47843 | M58: USFSTreesearch | N58: 45736.765
A59: Niemi_Vastaranta_Vauhkonen_etal_2017 | B59: Niemi | C59: Niemi, Mikko T.; Vastaranta, Mikko; Vauhkonen, Jari; Melkas, Timo; Holopainen, Markus | D59: 2017 | E59: Airborne LiDAR-derived elevation data in terrain trafficability mapping | F59: Scandinavian Journal of Forest Research | G59: 762-773 | H59: 8 | I59: 32 | J59: article | K59: https://doi.org/10.1080/02827581.2017.1296181 | L59: https://www.scopus.com/inward/record.uri?eid=2-s2.0-85014538878&doi=10.1080%2f02827581.2017.1296181&partnerID=40&md5=bef030870b3e1e70062514ecc08ecaad | M59: Scopus | N59: 45733.718
A60: Pierzchała_Talbot_Astrup_2014 | B60: Pierzchała | C60: Pierzchała, Marek; Talbot, Bruce; Astrup, Rasmus | D60: 2014 | E60: Estimating soil displacement from timber extraction trails in steep terrain: Application of an unmanned aircraft for 3D modelling | F60: Forests | G60: 1212-1223 | H60: 6 | I60: 5 | J60: article | K60: https://doi.org/10.3390/f5061212 | L60: https://www.scopus.com/inward/record.uri?eid=2-s2.0-84902463861&doi=10.3390%2ff5061212&partnerID=40&md5=8b4ea0493f590714bce883d80a23b7ea | M60: Scopus | N60: 45734.561
A61: Pierzchała_Talbot_Astrup_2016 | B61: Pierzchała | C61: Pierzchała, Marek; Talbot, Bruce; Astrup, Rasmus | D61: 2016 | E61: Measuring wheel ruts with close-range photogrammetry | F61: Forestry | G61: 383-391 | H61: 4 | I61: 89 | J61: article | K61: https://doi.org/10.1093/forestry/cpw009 | L61: https://www.scopus.com/inward/record.uri?eid=2-s2.0-84984831766&doi=10.1093%2fforestry%2fcpw009&partnerID=40&md5=edf3ecc33280fda69547e065233ab9e8 | M61: Scopus | N61: 45730.829
A62: Pohjankukka_Riihimäki_Nevalainen_etal_2016 | B62: Pohjankukka | C62: Jonne Pohjankukka;Henri RiihimÃ¤ki;Paavo Nevalainen;Tapio Pahikkala;Jari Alaâ€_x0090_IlomÃ¤ki;Eija HyvÃ¶nen;J. Varjo;Jukka Heikkonen | D62: 2016 | E62: Predictability of boreal forest soil bearing capacity by machine learning | F62: Journal of Terramechanics | G62: 45665 | I62: 68 | J62: article | K62: https://doi.org/10.1016/j.jterra.2016.09.001 | L62: https://www.sciencedirect.com/science/article/pii/S0022489816300453 | M62: ResearchRabbit | N62: 45835.624
A63: Rengers_Tucker_Moody_etal_2016 | B63: Rengers | C63: Rengers, F. K.; Tucker, G. E.; Moody, J. A.; Ebel, B. A. | D63: 2016 | E63: Illuminating wildfire erosion and deposition patterns with repeat terrestrial LiDAR | F63: Journal of Geophysical Research: Earth Surface | G63: 588-608 | H63: 3 | I63: 121 | J63: article | K63: https://doi.org/10.1002/2015jf003600 | L63: https://doi.org/10.1002/2015jf003600 | M63: OpenAlex | N63: 45734.556
A64: Quintano_Fernandez-Manso_Calvo_etal_2019 | B64: Roberts | C64: Dar A. Roberts;Carmen Quintano;Alfonso FernÃ¡ndezâ€“Manso;Leonor Calvo | D64: 2019 | E64: Vegetation and Soil Fire Damage Analysis Based on Species Distribution Modeling Trained with Multispectral Satellite Data | F64: Remote Sensing | G64: 1832 | H64: 11 | I64: 15 | J64: article | K64: https://doi.org/10.3390/rs11151832 | L64: https://www.mdpi.com/2072-4292/11/15/1832 | M64: ResearchRabbit | N64: 45835.631
A65: Robichaud_Lewis_Brown_etal_2020 | B65: Robichaud | C65: Robichaud, Peter R.; Lewis, Sarah A.; Brown, Robert E.; Bone, Edwin D.; Brooks, Erin S. | D65: 2020 | E65: Evaluating post‐wildfire logging‐slash cover treatment to reduce hillslope erosion after salvage logging using ground measurements and remote sensing | F65: Hydrological Processes | G65: 4431-4445 | H65: 23 | I65: 34 | J65: analytic | K65: https://doi.org/10.1002/hyp.13882 | L65: https://research.ebsco.com/linkprocessor/plink?id=d3c53c39-0c96-3d2a-8bd7-33d879808112 | M65: EBSCOhost | N65: 45729.85
A66: Robichaud_Lewis_Laes_etal_2007 | B66: Robichaud | C66: Peter R. Robichaud;Sarah A. Lewis;Denise Laes;Andrew T. Hudak;Raymond F. Kokaly;Joseph A. Zamudio | D66: 2007 | E66: Postfire soil burn severity mapping with hyperspectral image unmixing | F66: Remote Sensing of Environment | G66: 467-480 | H66: 4 | I66: 108 | J66: article | K66: https://doi.org/10.1016/j.rse.2006.11.027 | L66: https://doi.org/10.1016/j.rse.2006.11.027 | M66: ResearchRabbit | N66: 45835.62
A67: Rogan_Franklin_2001 | B67: Rogan | C67: Rogan, John; Franklin, Janet | D67: 2001 | E67: Mapping wildfire burn severity in Southern California forests and shrublands using Enhanced Thematic Mapper imagery | F67: Geocarto International | G67: 91-106 | H67: 4 | I67: 16 | J67: article | K67: https://doi.org/10.1080/10106040108542218 | L67: https://www.scopus.com/inward/record.uri?eid=2-s2.0-33746607869&doi=10.1080%2f10106040108542218&partnerID=40&md5=5fcc968dab4f043c6e878e4d6df34010 | M67: Scopus | N67: 45730.753
A68: Salmivaara_Miettinen_Finér_etal_2018 | B68: Salmivaara | C68: Salmivaara, Aura; Miettinen, Mikko; Finér, Leena; Launiainen, Samuli; Korpunen, Heikki; Tuominen, Sakari; Heikkonen, Jukka; Nevalainen, Paavo; Sirén, Matti; Ala-Ilomäki, Jari; Uusitalo, Jori | D68: 2018 | E68: Wheel rut measurements by forest machine-mounted LiDAR sensors – Accuracy and potential for operational applications? | F68: International Journal of Forest Engineering | G68: 41-52 | H68: 1 | I68: 29 | J68: article | K68: https://doi.org/10.1080/14942119.2018.1419677 | L68: https://doi.org/10.1080/14942119.2018.1419677 | M68: OpenAlex | N68: 45735.676
A69: Sewell_Quideau_Dyck_etal_2020 | B69: Sewell | C69: Sewell, Paul D.; Quideau, Sylvie A.; Dyck, Miles; Macdonald, Ellen | D69: 2020 | E69: Long-term effects of harvest on boreal forest soils in relation to a remote sensing-based soil moisture index | F69: Forest Ecology and Management | G69: 117986 | I69: 462 | J69: article | K69: https://doi.org/10.1016/j.foreco.2020.117986 | L69: https://www.scopus.com/inward/record.uri?eid=2-s2.0-85079405075&doi=10.1016%2fj.foreco.2020.117986&partnerID=40&md5=a9c22c5e4316cb706282e584fb8f1094 | M69: Scopus | N69: 45737.652
A70: Shakesby_Chafer_Doerr_etal_2003 | B70: Shakesby | C70: Shakesby, R. A.; Chafer, C. J.; Doerr, S. H.; Blake, W. H.; Wallbrink, P.; Humphreys, G. S.; Harrington, B. A. | D70: 2003 | E70: Fire severity, water repellency characteristics and hydrogeomorphological changes following the Christmas 2001 Sydney forest fires | F70: Australian Geographer | G70: 147-175 | H70: 2 | I70: 34 | J70: article | K70: https://doi.org/10.1080/00049180301736 | L70: https://www.scopus.com/inward/record.uri?eid=2-s2.0-0042889141&doi=10.1080%2f00049180301736&partnerID=40&md5=491c90dc8a5567c7615a761a2bad86c6 | M70: Scopus | N70: 45730.812
A71: Sikkink | B71: Sikkink | C71: Sikkink, Pamela | D71: 2015 | E71: Comparison of six fire severity classification methods using Montana and Washington wildland fires | F71: Proceedings of the Large Wildland Fires Conference | J71: conference-paper | L71: https://research.fs.usda.gov/treesearch/49447 | M71: USFSTreesearch
A72: Talbot_Astrup_2021 | B72: Talbot | C72: Talbot, Bruce; Astrup, Rasmus | D72: 2021 | E72: A review of sensors, sensor-platforms and methods used in 3D modelling of soil displacement after timber harvesting | F72: Croatian Journal of Forest Engineering | G72: 149-164 | H72: 1 | I72: 42 | J72: review | K72: https://doi.org/10.5552/crojfe.2021.837 | L72: https://www.scopus.com/inward/record.uri?eid=2-s2.0-85097566395&doi=10.5552%2fcrojfe.2021.837&partnerID=40&md5=a19ec449d86c67601e6e6383f452f237 | M72: Scopus | N72: 45713.796
A73: Talbot_Rahlf_Astrup_2018 | B73: Talbot | C73: Talbot, Bruce; Rahlf, Johannes; Astrup, Rasmus | D73: 2018 | E73: An operational UAV-based approach for stand-level assessment of soil disturbance after forest harvesting | F73: Scandinavian Journal of Forest Research | G73: 387-396 | H73: 4 | I73: 33 | J73: article | K73: https://doi.org/10.1080/02827581.2017.1418421 | L73: https://www.scopus.com/inward/record.uri?eid=2-s2.0-85040973273&doi=10.1080%2f02827581.2017.1418421&partnerID=40&md5=566edada02915d5fe6d6363eb53859c0 | M73: Scopus | N73: 45681.858
A74: Tomljanović_Kolar_Đuka_etal_2022 | B74: Tomljanović | C74: Tomljanović, Kristijan; Kolar, Antonija; Đuka, Andreja; Franjević, Milivoj; Jurjević, Luka; Matak, Iva; Ugarković, Damir; Balenović, Ivan | D74: 2022 | E74: Application of UAS for monitoring of forest ecosystems: A review of experience and knowledge | F74: Croatian Journal of Forest Engineering | G74: 487-504 | H74: 2 | I74: 43 | J74: article | K74: https://doi.org/10.5552/crojfe.2022.1727 | L74: https://www.scopus.com/inward/record.uri?eid=2-s2.0-85135446876&doi=10.5552%2fcrojfe.2022.1727&partnerID=40&md5=a9d0a471cc40358cc5e3aa32d89cd720 | M74: Scopus | N74: 45733.795
A75: Udali_Talbot_Ackerman_etal_2024 | B75: Udali | C75: Udali, Alberto; Talbot, Bruce; Ackerman, Simon; Crous, Jacob; Grigolato, Stefano | D75: 2024 | E75: Enhancing precision in quantification and spatial distribution of logging residues in plantation stands | F75: European Journal of Forest Research | J75: article | K75: https://doi.org/10.1007/s10342-024-01699-5 | L75: https://doi.org/10.1007/s10342-024-01699-5 | M75: OpenAlex | N75: 45734.591
A76: Venanzi_Latterini_Civitarese_etal_2023 | B76: Venanzi | C76: Venanzi, Rachele; Latterini, Francesco; Civitarese, Vincenzo; Picchio, Rodolfo | D76: 2023 | E76: Recent applications of smart technologies for monitoring the sustainability of forest operations | F76: Forests | G76: 1503 | H76: 7 | I76: 14 | J76: review | K76: https://doi.org/10.3390/f14071503 | L76: https://www.scopus.com/inward/record.uri?eid=2-s2.0-85166181566&doi=10.3390%2ff14071503&partnerID=40&md5=8dc574b1c5c817ef837ae882709648a5 | M76: Scopus | N76: 45733.816
A77: Veraverbeke_Dennison_Gitas_etal_2018 | B77: Veraverbeke | C77: Sander Veraverbeke;Philip E. Dennison;Ioannis Z. Gitas;Glynn Hulley;Ðž. Ð’. ÐšÐ°Ð»Ð°ÑˆÐ½Ð¸ÐºÐ¾Ð²Ð°;Olga V. Kalashnikova;Thomas Katagis;Le Kuai;Ran Meng;Dar A. Roberts;E. Natasha Stavros | D77: 2018 | E77: Hyperspectral remote sensing of fire: State-of-the-art and future perspectives | F77: Remote Sensing of Environment | G77: 105-121 | I77: 216 | J77: article | K77: https://doi.org/10.1016/j.rse.2018.06.020 | L77: https://www.sciencedirect.com/science/article/pii/S0034425718302980 | M77: ResearchRabbit | N77: 45835.628
A78: Verbyla_Lord_2008 | B78: Verbyla | C78: Verbyla, D.; Lord, R. | D78: 2008 | E78: Estimating post‐fire organic soil depth in the Alaskan boreal forest using the Normalized Burn Ratio | F78: International Journal of Remote Sensing | G78: 3845-3853 | H78: 13 | I78: 29 | J78: article | K78: https://doi.org/10.1080101431160701802497 | L78: https://research.fs.usda.gov/treesearch/35232 | M78: USFSTreesearch | N78: 45736.696
A79: Whitman_Parisien_Holsinger_etal_2020 | B79: Whitman | C79: Whitman, Ellen; Parisien, Marc-André; Holsinger, Lisa M.; Park, Jane; Parks, Sean A. | D79: 2020 | E79: A method for creating a burn severity atlas: An example from Alberta, Canada | F79: International Journal of Wildland Fire | G79: 995 | H79: 11 | I79: 29 | J79: article | K79: https://doi.org/10.1071/wf19177 | L79: https://doi.org/10.1071/wf19177 | M79: OpenAlex | N79: 45730.803
A80: Nevalainen_Salmivaara_Ala-Ilomäki_etal_2017 | B80: Nevalainen | C80: Nevalainen, Paavo; Salmivaara, Aura; Ala-Ilomäki, Jari; Launiainen, Samuli; Hiedanpää, Juuso; Finér, Leena; Pahikkala, Tapio; Heikkonen, Jukka | E80: Estimating the rut depth by UAV photogrammetry | F80: Remote Sensing | G80: 1279 | H80: 12 | I80: 9 | K80: 10.3390/rs9121279 | M80: Manual | N80: 45681.859

Sheet 5_study_data
D1: STUDY SPACE TIME | S1: POPULATION | W1: INTERVENTION | AD1: OUTCOME | AK1: RS METHODS | BF1: STUDY GOALS
A2: study_id | B2: study_type | C2: data_collector | D2: country | E2: location_name | F2: location_lat | G2: location_lon | H2: full_aou_ha | I2: sample_site_n | J2: sample_unit | K2: sample_unit_clean | L2: min_area_reported | M2: max_area_reported | N2: total_area_reported | O2: area_ha | P2: sample_year_start | Q2: sample_year_end | R2: RS_acquisition_year | S2: biome | T2: forest_type | U2: dominant_species | V2: soil_type | W2: intervention_1 | X2: intervention_2 | Y2: intervention_3 | Z2: intervention_category_1 | AA2: intervention_category_2 | AB2: intervention_category_3 | AC2: intervention_year | AD2: outcome_1 | AE2: outcome_2 | AF2: outcome_3 | AG2: indicators_1 | AH2: indicators_2 | AI2: indicators_3 | AJ2: treatment | AK2: sensor_type | AL2: sensor_action | AM2: sensor_name | AN2: platform | AO2: platform_name | AP2: resolution_m | AQ2: rs_method | AR2: bands_used | AS2: metric_index_used | AT2: metric_index_description | AU2: classification_method | AV2: class_method_clean | AW2: rs_data_product | AX2: clean_rs_data_product | AY2: rs_temporal_design | AZ2: target_intervention | BA2: target_outcome | BB2: in_situ_indicators | BC2: ground_truthed | BD2: validation_model_metrics | BE2: rs_purpose_description | BF2: study_category | BG2: study_objective | BH2: broad_conclusion
A3: Robichaud_Lewis_Brown_etal_2020 | B3: peer-reviewed article | C3: Xavier & Aicha | D3: United-States | E3: North-central Washington | F3: 48.416358 | G3: -118.87059 | H3: 88000 | I3: 21; 24 | J3: skid track | K3: skid track | L3: 4m^2; 71 m^2 | M3: 8m^2; 141 m^2 | N3: 168 m^2; 2400 m^2 | O3: 0.0168; 0.24 | P3: 2016 | Q3: 2019 | R3: 2015; 2016; 2017; 2018; 2019 | S3: Temperate Conifer Forests | T3: temperate dry forest | U3: Douglas fir; Ponderosa pine | V3: Nevine Series andisol | W3: wildfire | X3: salvage logging | Y3: NA | Z3: wildfire | AA3: harvesting | AB3: NA | AC3: 2015;2016 | AD3: soil burn; soil erosion | AE3: soil rutting; soil erosion | AF3: NA | AG3: burn severity; fractional cover estimates; runoff sediment volume; soil water repellency; soil bulk density | AH3: soil water repellency; soil bulk density | AI3: NA | AJ3: slash cover | AK3: Hyperspectral | AL3: passive | AM3: WV110 | AN3: satellite | AO3: WorldView-2 | AP3: 1.8 | AQ3: Spectral analysis | AR3: red, nir | AS3: NDVI | AT3: vegetation index | AU3: k-means | AV3: unsupervised | AW3: classified NDVI values representing soil erosion on pre-and post-intervention images | AX3: classified NDVI image | AY3: mono-temporal/multi-annual | AZ3: salvage logging | BA3: skid trails | BB3: water drop penetration time; bulk density; ground/vegetation cover estimates | BC3: yes | BD3: NR | BE3: use NDVI to monitor change in veg and soil cover as proxy for disturbance and recovery after wildfire and effects of salvage logging skid trails | BF3: experimental | BG3: evaluate in wildfire burned areas the impacts of logging and slash treatments on sediment loss, determine effective slash cover levels for erosion control, assess the use of NDVI for estimating ground cover and erosion risk remotely, and compare vegetation responses between salvaged and unsalvaged sites. | BH3: applying logging slash to achieve at least 60% ground cover effectively reduced post-logging erosion, and NDVI imagery successfully tracked vegetation recovery and erosion risk over time.
A4: Giannetti_Chirici_Travaglini_etal_2017 | B4: peer-reviewed article | C4: Xavier & Aicha | D4: Italy | E4: Vallombrosa Forest | F4: 43.785278 | G4: 11.525556 | H4: 1269 | I4: 2 | J4: skid track | K4: skid track | L4: 589 m^2 | M4: 1047 m^2 | N4: 1636m^2 | O4: 0.1636 | P4: 2016 | Q4: 2016 | R4: 2016 | S4: Mediterranean Forests, Woodlands & Scrub | T4: NR | U4: Abies alba Mill | V4: Umbrept and Umbric Dytrochrept soils | W4: windthrow | X4: salvage logging | Y4: NA | Z4: windthrow | AA4: harvesting | AB4: NA | AC4: 2015; 2016 | AD4: soil rutting; soil compaction | AE4: soil displacement | AF4: NA | AG4: digital terrain model; changes in soil volume; soil bulk density; soil penetration resistance | AH4: digital terrain model; changes in soil volume | AI4: NA | AJ4: NA | AK4: LiDAR | AL4: active | AM4: ZEB1 | AN4: ground | AO4: NA | AP4: 0.01 | AQ4: LiDAR | AR4: nir | AS4: NA | AT4: NA | AU4: adaptive triangulated irregular network algorithm | AV4: other algorithm | AW4: high-resolution map of soil displacement | AX4: soil displacement map | AY4: multi-temporal/mono-annual | AZ4: salvage logging | BA4: soil disturbance; soil compaction | BB4: bulk density; penetration resistance | BC4: yes | BD4: NR | BE4: produce multi-temporal high-resolution DTM before and after logging for assessment of soil disturbance | BF4: before-after | BG4: assess logging-induced rutting using PLS to create high resolution assessment of soil disturbance before and after logging | BH4: PLS technology can be used to assess soil disturbance caused by forest harvesting machinery.
A5: Talbot_Rahlf_Astrup_2018 | B5: peer-reviewed article | C5: Xavier & Aicha | D5: Norway | E5: South-east Norway | F5: 59.932228 | G5: 9.662416 | H5: 32.9 | I5: 6 | J5: cutblock | K5: cutblock | L5: 1.2 ha | M5: 10.2 ha | N5: 32.9 ha | O5: 32.9 | P5: NR | Q5: NR | S5: Boreal Forests/Taiga | T5: NR | U5: NR | V5: NR | W5: cut-to-length logging | X5: NA | Y5: NA | Z5: harvesting | AA5: NA | AB5: NA | AC5: NR | AD5: soil rutting | AE5: NA | AF5: NA | AG5: rut severity | AH5: NA | AI5: NA | AJ5: NA | AK5: Stereo | AL5: passive | AM5: GoPro Hero 4 Silver; DJI Phantom 4 camera | AN5: UAV | AO5: DJI Phantom 2; DJI Phantom 4 | AP5: 2 | AQ5: Photogrammetry | AR5: red, green, blue | AS5: NA | AT5: NA | AU5: NA | AV5: NA | AW5: orthomosaic of site with buffered wheel track tracelines categorized by traffic intensity | AX5: orthomosaic | AY5: mono-temporal | AZ5: logging | BA5: wheel ruts | BB5: photointerpreted ruts | BC5: yes | BD5: NR | BE5: provide orthomosaic of target sites for tracing and sampling wheel ruts to determine severity and extent | BF5: observational | BG5: observe extent and categorize severity of cut to length machine traffic on harvest sites | BH5: generating UAV orthomosaics combined with desktop analysis allows less resource-intensive observation of wheel rut extent and severity than field-based methods
A6: Lewis_Robichaud_Archer_etal_2023 | B6: peer-reviewed article | C6: Aicha | D6: United-States | E6: Lolo National Forest, Montana | F6: 47.583377 | G6: -115.5843 | H6: 87500 | I6: 7 | J6: cutblock | K6: cutblock | L6: 2 ha | M6: 15 ha | N6: 71.5 ha | O6: 71.5 | P6: 2022 | Q6: 2022 | R6: 2014; 2016; 2017; 2018; 2019; 2020; 2022 | S6: Temperate Conifer Forests | T6: dry ponderosa pine | U6: Ponderosa pine; Douglas fir; Subalpine fir; Lodgepole pine | V6: silt loams | W6: wildfire | X6: salvage logging | Y6: NA | Z6: wildfire | AA6: harvesting | AB6: NA | AC6: 2016, 2017; 2018, 2019 | AD6: soil burn | AE6: soil compaction; soil disturbance | AF6: NA | AG6: char depth; soil water repellency | AH6: soil displacement; presence of tracks; soil water repellency; soil compaction depth | AI6: NA | AJ6: NA | AK6: Multispectral; Multispectral; Multispectral | AL6: passive | AM6: GIS; WV110; WV110 | AN6: satellite; satellite; satellite | AO6: GeoEye-1; WorldView-2; WorldView-3 | AP6: 1.8; 1.8; 1.24 | AQ6: Spectral analysis | AR6: red, nir | AS6: NDVI | AT6: vegetation index | AU6: regressive partitioning tree analysis | AV6: tree-based | AW6: classified NDVI values representing soil disturbance on pre-and post-intervention images | AX6: classified NDVI image | AY6: mono-temporal/multi-annual | AZ6: salvage logging | BA6: soil disturbance; soil compaction; vegetation disturbance; skid trails | BB6: detrimental soil disturbance classes | BC6: yes | BD6: NR | BE6: correlate NDVI estimations of detrimental soil disturbance to ground-measured values | BF6: before-after | BG6: develop methodology for remote evaluation of detrimental soil disturbance after post-fire salvage logging | BH6: post-salvage NDVI values strongly correlated with field measured detrimental soil disturbance
A7: Llorens_Sobrino_Fernández_etal_2024 | B7: peer-reviewed article | C7: Xavier & Aicha | D7: Spain | E7: Large forest fires in Spain | F7: 41.836748 | G7: -6.422043 | H7: 100000 | I7: 503 | J7: circular plots | K7: plot | L7: 1256.64m^2 | M7: 1256.64m^2 | N7: 632089.92 m^2 | O7: 63.2 | P7: 2017 | Q7: 2022 | R7: 2018; 2019 | S7: Mediterranean Forests, Woodlands & Scrub; Temperate Broadleaf & Mixed Forests | T7: NR | U7: Pinus sylvestris; Pinus pinea; Pinus pinaster | V7: Leptosols; Cambisols | W7: wildfire | X7: NA | Y7: NA | Z7: wildfire | AA7: NA | AB7: NA | AC7: 2018; 2019 | AD7: soil burn | AE7: NA | AF7: NA | AG7: soil burn severity index; emissivity; NBR | AH7: NA | AI7: NA | AJ7: NA | AK7: Multispectral; Thermal | AL7: passive; passive | AM7: MSI; CIMEL CE-312 | AN7: satellite; ground | AO7: Sentinel-2; NA | AP7: 20; NR | AQ7: Spectral analysis | AR7: blue, green, red, vegetation red edge, nir, swir1, swir2 | AS7: BAIS2; MIRBI; NBR; NBR2; CR; IOR | AT7: burn index; soil index | AU7: thresholding with separability index | AV7: threshold/rule based | AW7: soil burn severity map | AX7: burn severity map | AY7: mono-temporal | AZ7: fire | BA7: soil burn | BB7: soil burn severity classes | BC7: yes | BD7: NR | BE7: create soil burn severity maps using radiometric measurements and remote sensing data | BF7: operational | BG7: create soil burn severity maps to support soil rehabiltation after forest fire | BH7: integrating radiometric measurements with satellite imagery provides more robust results for post fire ecosystem management
A8: Affek_Zachwatowicz_Sosnowska_etal_2017 | B8: peer-reviewed article | C8: Xavier & Aicha | D8: Poland | E8: Polish Carpathian Mountains | F8: 49.691529 | G8: 22.548125 | H8: 263900 | I8: 60 | J8: forest stand | K8: forest stand | L8: 40 ha | M8: 40 ha | N8: 2400 ha | O8: 2400 | P8: 2013 | Q8: 2014 | S8: Temperate Conifer Forests | T8: NR | U8: Fagus sylvatica; Abies alba; Quercus robur; Carpinus betulus | V8: developed from loamy and clay weathered covers | W8: logging | X8: NA | Y8: NA | Z8: harvesting | AA8: NA | AB8: NA | AC8: NR | AD8: skid trails; soil rutting | AE8: NA | AF8: NA | AG8: spatial extent of roads and trails | AH8: NA | AI8: NA | AJ8: NA | AK8: LiDAR | AL8: active | AM8: Riegl LMS-Q680i | AN8: airborne | AO8: NR | AP8: 1 | AQ8: LiDAR | AR8: NR | AS8: NA | AT8: NA | AU8: NA | AV8: NA | AW8: digitisation of logging road network | AX8: road network map | AY8: mono-temporal | AZ8: logging | BA8: roads; skid trails | BB8: ground-based GPS measurements | BC8: yes | BD8: NR | BE8: detection of forest roads and skid trails under canopy | BF8: observational | BG8: explore implications of skidding on natural and cultural features in the Carpathian forest through LiDAR mapping | BH8: DEM obtained through LiDAR can be used to detect forest roads and skid trails under canopy
A9: Allen_Sorbel_2008 | B9: peer-reviewed article | C9: Xavier & Aicha | D9: United-States | E9: Alaska | F9: 65.620843 | G9: -153.00697 | H9: 75242 | I9: 289 | J9: circular plots | K9: plot | L9: 314.16 m² | M9: 706.86 m² | N9: NR | O9: NR | P9: 2001 | Q9: 2003 | R9: 1985; 1986; 1995; 1999; 2001; 2002; 2003 | S9: Boreal Forests/Taiga | T9: boreal forests | U9: picea mariana; picea glauca; betula papyrifera; populus balsamifera; populus tremuloides | V9: NR | W9: wildfire | X9: NA | Y9: NA | Z9: wildfire | AA9: NA | AB9: NA | AC9: 1999;2000;2001;2002 | AD9: soil burn | AE9: NA | AF9: NA | AG9: composite burn severity index; NBR | AH9: NA | AI9: NA | AJ9: NA | AK9: Multispectral | AL9: passive | AM9: TM; ETM | AN9: satellite | AO9: Landsat 5; Landsat 7 | AP9: 30 | AQ9: Image differencing | AR9: nir; swir2 | AS9: NBR; dNBR | AT9: burn index | AU9: NA | AV9: NA | AW9: burn severity layers | AX9: burn severity map | AY9: mono-temporal/multi-annual | AZ9: fire | BA9: soil burn | BB9: composite burn index | BC9: yes | BD9: NR | BE9: correlate dNBR estimations of soil burn severity to ground measured values | BF9: before-after | BG9: compare dNBR with ground based measurements to evaluate method's ability to accurately map burn severity in boreal and tundra ecosystems | BH9: dNBR values were strongly correlated with field measurements of burn severity, however it may be less accurate in areas of high fire severity.
A10: Beltrán-Marcos_Suárez-Seoane_Fernández-Guisuraga_etal_2021 | B10: peer-reviewed article | C10: Xavier & Aicha | D10: Spain | E10: Villapadierna | F10: 42.707067 | G10: -5.144415 | H10: 82.47 | I10: 80 | J10: square plots | K10: plot | L10: 0.25 m² | M10: 0.25 m² | N10: 20 m² | O10: 0.002 ha | P10: 2019 | Q10: 2019 | R10: 2019 | S10: Mediterranean Forests, Woodlands & Scrub | T10: mediterranean pine forest | U10: Pinus sylvestris; Pinus pinaster; Quercus pyrenaica | V10: Dystric; Humic Cambisols | W10: wildfire | X10: NA | Y10: NA | Z10: wildfire | AA10: NA | AB10: NA | AC10: 2019 | AD10: soil burn | AE10: NA | AF10: NA | AG10: soil burn severity; spectral indices; RGB indices; fractional cover estimates | AH10: NA | AI10: NA | AJ10: NA | AK10: Multispectral; RGB | AL10: passive; passive | AM10: Parrot SEQUOIA; Sony A6000 | AN10: UAV; UAV | AO10: FV8 octocopter | AP10: NR; NR | AQ10: Spectral analysis | AR10: green, red, red edge, nir | AS10: EGI; GCC; CI; BI; MaxDiff; NDVI; NDVIRE; NDWI | AT10: burn index; burn index; burn index; burn index; vegetation index; vegetation index; soil index | AU10: NR | AV10: NA | AW10: high resolution area map of CBSI category predictions | AX10: Composite Burn Soil Index map | AY10: mono-temporal/mono-annual | AZ10: fire | BA10: soil burn | BB10: composite burn index | BC10: yes | BD10: confusion matrices | BE10: evaluate high resolution multispectral/RGB products obtained by UAVs to characterize soil burn severity | BF10: observational | BG10: evaluate ability of multispectral and RGB imagery collected with UAV to characterize soil burn severity in areas affected by mixed-severity wildfires | BH10: multispectral indices (NDWI) performed better than RGB indices to determine soil burn severity at high spatial resolutions, UAV-based multispectral and RGB imagery has potential to assess soil burn severity in mixed-severity wildifre areas
A11: Beltrán-Marcos_Suárez-Seoane_Fernández-Guisuraga_etal_2023 | B11: peer-reviewed article | C11: Xavier & Aicha | D11: Spain | E11: Villapadierna | F11: 42.707067 | G11: -5.144415 | H11: 82.47 | I11: 34 | J11: square plots | K11: plot | L11: 0.25 m² | M11: 0.25 m² | N11: 8.5 m² | O11: 0.00085 | P11: 2019 | Q11: 2019 | R11: 2019 | S11: Mediterranean Forests, Woodlands & Scrub | T11: mediterranean pine forest | U11: Pinus sylvestris; Pinus pinaster; Quercus pyrenaica | V11: Dystric; Gleyic; Humic Cambisols | W11: wildfire | X11: NA | Y11: NA | Z11: wildfire | AA11: NA | AB11: NA | AC11: 2019 | AD11: soil burn | AE11: NA | AF11: NA | AG11: soil burn severity; soil moisture content; soil biophysical properties | AH11: NA | AI11: NA | AJ11: NA | AK11: Multispectral; Multispectral | AL11: passive | AM11: MSI; Parrot SEQUOIA | AN11: satellite; UAV | AO11: Sentinel-2; FV8 octocopter | AP11: 10; 0.5 | AQ11: Spectral analysis | AR11: blue; green; red; red-edge-1; red-edge-2; red-edge-3; nir; nir narrow; swir-1; swir-2 | AS11: NDVI; NDWI | AT11: vegetation index; soil index | AU11: decision tree calibrated with 10-fold cross-validation resampling technique | AV11: tree-based | AW11: mean spectral reflectance of soil samples across sensor type and soil burn severity category | AX11: multispectral image | AY11: mono-temporal/mono-annual | AZ11: fire | BA11: soil burn | BB11: composite burn index | BC11: yes | BD11: NR | BE11: assess potential of combining multispectral imagery at different spectral and spatial resolutions to estimate soil indicators of burn severity. | BF11: observational | BG11: assess the potential of combining multispectral imagery at different spectral and spatial resolutions to estimate soil indicators of burn severity. | BH11: reflectance values derived from the fused UAV-Sentinel-2 image performed extremely well to monitor the effects of wildfire on soil characteristics, especially for soil organic carbon content
A12: Bhatnagar_Puliti_Talbot_etal_2022 | B12: peer-reviewed article | C12: Xavier & Aicha | D12: Norway | E12: South-eastern Norway | F12: 59.93987 | G12: 10.121184 | H12: 100.6 | I12: 20 | J12: forest stand | K12: forest stand | L12: 0.5 ha | M12: 21.5 ha | N12: 100 ha | O12: 100 | P12: 2016 | Q12: 2019 | S12: Boreal Forests/Taiga | T12: NR | U12: NR | V12: NR | W12: logging | X12: NA | Y12: NA | Z12: harvesting | AA12: NA | AB12: NA | AC12: NR | AD12: soil rutting | AE12: NA | AF12: NA | AG12: rut severity index | AH12: NA | AI12: NA | AJ12: NA | AK12: RGB; RGB; RGB; RGB; RGB; RGB; RGB; RGB; RGB; RGB; RGB; RGB; RGB | AL12: passive | AM12: GoPro Hero 4; DJI Phantom 4 Pro | AN12: UAV; UAV; UAV; UAV; UAV; UAV; UAV; UAV; UAV; UAV; UAV; UAV; UAV | AO12: DJI Phantom 2; DJI Phantom 4 Pro | AP12: 0.032; 0.02; 0.033; 0.031; 0.015; 0.01; 0.029; 0.027; 0.071; 0.035; 0.019; 0.014; 0.024 | AQ12: Object-based analysis | AR12: red; green; blue | AS12: NA | AT12: NA | AU12: Convulational Neural Network | AV12: machine learning | AW12: manually annotated wheel rut categorized by severity | AX12: binary map of wheel ruts | AY12: mono-temporal/multi-annual | AZ12: logging | BA12: wheel ruts | BB12: photointerpreted ruts | BC12: no | BD12: fourfold cross-validation | BE12: combine drone imagery and algorithms to automate mapping of wheel rut severity after logging. | BF12: observational | BG12: examine whether the automated detection of wheel ruts caused by cut-to-length harvester and forwarder systems can be realized with a combination of drone RGB images of previously tree-covered sites acquired shortly after final harvests and CNNs. | BH12: drone-based photogrammetry and deep larning can be used to detect the presence of wheel ruts, severe ruts more accurately detected compared to light ruts.
A13: Bourgeau-Chavez_Kasischke_Riordan_etal_2007 | B13: peer-reviewed article | C13: Xavier & Aicha | D13: United-States | E13: Interior Alaska | F13: 64.292844 | G13: -147.51471 | H13: 16500 | I13: 9 | J13: forest stand | K13: forest stand | L13: 4 ha | M13: 4 ha | N13: 36 ha | O13: 36 | P13: 2003 | Q13: 2004 | R13: 1995; 2000; 2001; 2002; 2003; 2004 | S13: Boreal Forests/Taiga | T13: boreal forests | U13: Picea mariana | V13: clay loam; silty clay loam | W13: wildfire | X13: NA | Y13: NA | Z13: wildfire | AA13: NA | AB13: NA | AC13: 1991; 1994; 1999; 2003 | AD13: soil burn; soil moisture loss | AE13: NA | AF13: NA | AG13: burn severity index; surface roughness; vegetative biomass estimates; soil moisture content | AH13: NA | AI13: NA | AJ13: NA | AK13: SAR | AL13: active | AM13: ATSR-2 | AN13: satellite | AO13: ERS-2 | AP13: NR | AQ13: Image differencing | AR13: C-band | AS13: NA | AT13: NA | AU13: NR | AV13: NA | AW13: landsat-derived burn severity maps; classified soil moisture maps | AX13: burn severity map; soil moisture map | AY13: multi-temporal/multi-annual | AZ13: fire | BA13: soil burn; soil moisture | BB13: soil burn severity classes; soil moisture content | BC13: yes | BD13: NR | BE13: SAR-based soil moisture estimation over seasonal changes after wildfire burn | BF13: before-after | BG13: develop and evaluate a seasonal soil moisture index technique using satellite SAR data | BH13: successfully developed and validated, retains spatial resolution and provides temporal tracking of soil moisture
A14: Cambi_Giannetti_Bottalico_etal_2018 | B14: peer-reviewed article | C14: Xavier & Aicha | D14: Italy | E14: Biogenetic reserve of Vallombrosa | F14: 43.745982 | G14: 11.558272 | H14: 5.78 | I14: 1 | J14: forest stand | K14: forest stand | L14: 5.78 ha | M14: 5.78 ha | N14: 5.78 ha | O14: 5.78 | P14: NR | Q14: NR | S14: Mediterranean Forests, Woodlands & Scrub | T14: even aged plantation | U14: Abies alba Mill. | V14: Umbrepts; Umbric dytrochrepts | W14: salvage logging | X14: NA | Y14: NA | Z14: harvesting | AA14: NA | AB14: NA | AC14: NR | AD14: soil rutting; soil compaction | AE14: NA | AF14: NA | AG14: rut depth; bulge height; soil moisture; soil porosity; soil density | AH14: NA | AI14: NA | AJ14: NA | AK14: Stereo | AL14: passive | AM14: Nikon D90 | AN14: ground | AO14: NA | AP14: NR | AQ14: Photogrammetry | AR14: red; green; blue | AS14: NA | AT14: NA | AU14: NR | AV14: NA | AW14: high resolution surface models derived by structure-from-motion photogrammetry | AX14: digital terrain model | AY14: mono-temporal/mono-annual | AZ14: salvage logging | BA14: soil disturbance; wheel ruts | BB14: bulk density; shear resistance; penetration resistance | BC14: yes | BD14: NR | BE14: produce high-resolution surface models to determine soil disturbance and wheel rut differences between salvage logging machines | BF14: observational | BG14: describe effects of logging on physical properties of soil and depth of ruts through field measurements and photogrammetry analysis. | BH14: larger soil disturbance caused by forwarders than skidders. image-based models derived through SfM photogrammetric workflow is a useful tool to evaluate soil displacement caused by salvage logging machines
A15: Chasmer_Hopkinson_Petrone_etal_2017 | B15: peer-reviewed article | C15: Xavier & Aicha | D15: Canada | E15: Fort McMurray, Alberta | F15: 56.5 | G15: -111.26 | H15: 589552 | I15: 107 | J15: transects | K15: transect | L15: NR | M15: NR | N15: NR | O15: NR | P15: 2016 | Q15: 2016 | R15: 2008; 2016 | S15: Boreal Forests/Taiga | T15: wetland-upland forest | U15: NR | V15: NR | W15: wildfire | X15: NA | Y15: NA | Z15: wildfire | AA15: NA | AB15: NA | AC15: 2016 | AD15: soil burn | AE15: NA | AF15: NA | AG15: char depth | AH15: NA | AI15: NA | AJ15: NA | AK15: LiDAR; LiDAR; Multispectral; Multispectral | AL15: active; active; passive; passive | AM15: Teledyne Optech ALTM 3100EA; Teledyne Optech Titan ALTM; TM; ETM | AN15: airborne; airborne; satellite; satellite | AO15: NR; NR; Landsat 5; Landsat 7 | AP15: 1; 1; 1; 1 | AQ15: Spectral analysis | AR15: green; nir; swir | AS15: NBR; dNBR; ANBR | AT15: burn index | AU15: NR | AV15: NA | AW15: images of ground surface classified into burn severity classes | AX15: burn severity map | AY15: mono-temporal/multi-annual | AZ15: fire | BA15: soil burn | BB15: soil burn severity classes | BC15: yes | BD15: NR | BE15: determine accuracy of mapping depth of soil burn in boreal environments through comparison of LiDAR and and Landsat NBR | BF15: before-after | BG15: determine accuracy of detecting soil burn severity and depth in boreal peatlands and upland forests using LiDAR | BH15: LiDAR based burn severity index using ANBR shows promise but must be developed to reduce errors in depth of burn measurements
A16: Conrad-Rooney_Barker_Pasquarella_etal_2021 | B16: peer-reviewed article | C16: Xavier & Aicha | D16: United-States | E16: Amherst, Massachusets | F16: 42.370683 | G16: -72.504799 | H16: 8.1 | I16: 10 | J16: square plots | K16: plot | L16: 8100 m^2 | M16: 8100 m^2 | N16: 81000 m^2 | O16: 8.1 | P16: 2015 | Q16: 2018 | R16: 2015; 2016; 2017; 2018 | S16: Temperate Broadleaf & Mixed Forests | T16: oak-dominated mixed forest | U16: Quercus rubra | V16: NR | W16: insect outbreak | X16: NA | Y16: NA | Z16: insect outbreak | AA16: NA | AB16: NA | AC16: 2015; 2016; 2017; 2018 | AD16: soil nutrient loss | AE16: NA | AF16: NA | AG16: defoliation | AH16: NA | AI16: NA | AJ16: NA | AK16: Multispectral; Multispectral | AL16: passive; passive | AM16: ETM; OLI | AN16: satellite; satellite | AO16: Landsat 7; Landsat 8 | AP16: 30; 30 | AQ16: Image differencing | AR16: blue; green; red; nir; swir1; swir2 | AS16: TCG | AT16: vegetation index | AU16: NR | AV16: NA | AW16: defoliation severity derived from landsat imagery | AX16: defoliation map | AY16: mono-temporal/multi-annual | AZ16: insect outbreak | BA16: vegetation defoliation | BB16: vegetation greenness | BC16: yes | BD16: NR | BE16: capture range of defolitation intensities and durations | BF16: before-after | BG16: determine relationship between soil N concentrations and defoliation intensity | BH16: Trees in soil with lower N concentrations experience more herbivory, are correlated wtih more severe insect defoliation.
A17: Dąbek_Żmuda_Szczepański_etal_2018 | B17: conference proceedings | C17: Xavier & Aicha | D17: Poland | E17: Ciemniak, Western Sudetes | F17: 50.859167 | G17: 15.579167 | H17: 0.02 | I17: 1 | J17: skid track | K17: skid track | L17: 41 m^2 | M17: 41 m^2 | N17: 41 m^2 | O17: 0.0041 | P17: 2011 | Q17: 2013 | R17: 2011; 2012; 2013 | S17: Temperate Broadleaf & Mixed Forests | T17: NR | U17: NR | V17: NR | W17: logging | X17: NA | Y17: NA | Z17: harvesting | AA17: NA | AB17: NA | AC17: 2010 | AD17: soil erosion; skid trails | AE17: NA | AF17: NA | AG17: slope; digital terrain model | AH17: NA | AI17: NA | AJ17: NA | AK17: LiDAR | AL17: active | AM17: NR | AN17: ground | AO17: NR | AP17: 0.01 | AQ17: LiDAR | AR17: red; green; blue | AS17: NA | AT17: NA | AU17: NA | AV17: NA | AW17: detailed digital terrain 1 cm model of skid trails | AX17: digital terrain model | AY17: mono-temporal/multi-annual | AZ17: logging | BA17: skid trails; erosion | BB17: soil displacement | BC17: yes | BD17: NR | BE17: create DTMs to recognize created erosion forms and determine water erosion intesnisty of soil on a forest skid trail | BF17: observational | BG17: determine intensity and range of soil erosion along with volume of soil material loss as a result of logging activities and erosion processes. | BH17: TLS is efficient for use of monitoring soil erosion phenomena, qualitative and spatial range assessment.
A18: Deligiannakis_Pallikarakis_Papanikolaou_etal_2021 | B18: peer-reviewed article | C18: Xavier & Aicha | D18: Greece | E18: Central Greece | F18: 38.12397 | G18: 23.404082 | H18: NR | I18: 5 | J18: forest stand | K18: forest stand | L18: NR | M18: NR | N18: NR | O18: NR | P18: 2019 | Q18: 2021 | R18: 2019; 2020; 2021 | S18: Mediterranean Forests, Woodlands & Scrub | T18: coniferous forests and shrubs | U18: NR | V18: NR | W18: wildfire | X18: NA | Y18: NA | Z18: wildfire | AA18: NA | AB18: NA | AC18: 2019; 2012; 2009; 2020 | AD18: soil burn; soil erosion | AE18: NA | AF18: NA | AG18: slope; scarp identification | AH18: NA | AI18: NA | AJ18: NA | AK18: Stereo; LiDAR | AL18: passive; active | AM18: DJI Phantom 4; Optech Ilris | AN18: UAV; ground | AO18: DJI Phantom 4; NA | AP18: NR; NR | AQ18: Photogrammetry; LiDAR | AR18: red; green; blue | AS18: NA | AT18: NA | AU18: NA | AV18: NA | AW18: high resolution DSM and point clouds of landslides or early landslide phenomena | AX18: digital terrain model | AY18: mono-temporal/multi-annual | AZ18: fire | BA18: slumping; erosion | BB18: cracks and scarps; soil displacement | BC18: no | BD18: NA | BE18: detection of landslides, early landslide phenomena, monitor exisitng landslides in post-fire settings | BF18: observational | BG18: compare UAV derived DEM and point clouds with LiDAR derived point clouds ability to detect new cracks and scarps and monitor pre-exisitng landslides in areas burned by fire | BH18: UAV-derived and t-LiDAR datasets are effective at early landslide detection and monitoring in area burned no longer than 7 months before the flight, or 2-3 months after the rainy season
A19: Dubé_Berch_2013 | B19: peer-reviewed article | C19: Xavier & Aicha | D19: Canada | E19: British Columbia | F19: 54.357638 | G19: -123.19932 | H19: NR | I19: 23 | J19: forest stand | K19: forest stand | L19: NR | M19: NR | N19: NR | O19: NR | P19: NR | Q19: NR | S19: Temperate Conifer Forests | T19: NR | U19: NR | V19: mostly consolidated and of glacial origin | W19: insect outbreak | X19: salvage logging | Y19: NA | Z19: insect outbreak | AA19: harvesting | AB19: NA | AC19: NR | AD19: NA | AE19: soil rutting; soil displacement | AF19: NA | AG19: NA | AH19: presence of visual erosion; presence of roadside disturbances; green tree retention; presence of dead wood | AI19: NA | AJ19: NA | AK19: Multispectral; Multispectral; RGB | AL19: passive; passive; passive | AM19: TM; HRG; NR | AN19: satellite; satellite; airborne | AO19: Landsat 5; SPOT-5; NR | AP19: 30; 15; 1 | AQ19: Photo-interpretation | AR19: red; green; blue | AS19: NA | AT19: NA | AU19: NA | AV19: NA | AW19: satellite images with areas of soil disturbance identified | AX19: soil disturbance map | AY19: mono-temporal | AZ19: salvage logging | BA19: soil disturbance | BB19: access structures; wheel ruts; skid trails | BC19: yes | BD19: NR | BE19: identify and measure areas of soil disturbance using satellite imagery and low-level aerial photography to assess overalle state of soil management in relation to salvage harvesting | BF19: observational | BG19: assess harvesting-related soil disturbance in areas affected by mountain pine beetle using satellite imagery and low-aerial photographs | BH19: remote sensed images with a resolution greater than 2.5m can capture landslides, erosion, inordinate disturbance, roadside work areas, while aerial photographs in 10-cm pixel size are best to reveal less evident disturbance
A20: Ferenčík_Dudáková_Kardoš_etal_2022 | B20: peer-reviewed article | C20: Xavier & Aicha | D20: Slovakia | E20: Zvolen | F20: 48.643194 | G20: 19.036806 | H20: 9726 | I20: 3 | J20: rectangular plots | K20: plot | L20: 4.84 m^2 | M20: 5.56 m^2 | N20: 15.85 m^2 | O20: 0.001585 | P20: 2020 | Q20: 2021 | S20: Temperate Broadleaf & Mixed Forests | T20: NR | U20: NR | V20: Cambisol | W20: logging | X20: NA | Y20: NA | Z20: harvesting | AA20: NA | AB20: NA | AC20: NR | AD20: soil rutting; soil displacement | AE20: NA | AF20: NA | AG20: rut depth; rut volume | AH20: NA | AI20: NA | AJ20: skidder traffic | AK20: Stereo; Stereo | AL20: passive; passive | AM20: Canon EOS RP; Panasonic FZ 1000 | AN20: ground; ground | AO20: NR | AP20: NR; NR | AQ20: Photogrammetry | AR20: red; green; blue | AS20: NA | AT20: NA | AU20: NA | AV20: NA | AW20: DSM; 3D point cloud | AX20: digital terrain model | AY20: mono-temporal | AZ20: logging | BA20: wheel ruts | BB20: rut depth | BC20: yes | BD20: NR | BE20: use close-range photogrammetry to analyze soil surface changes caused by traffic of three types of wheeled skidders | BF20: experimental | BG20: analyze soil surface changes caused by traffic of three types of wheeled skidders | BH20: structure-from-motion photogrammetry can be applied to detect soil surface changes after traffic of forestry machinery
A21: Fernández_Fernández-Alonso_Vega_etal_2021 | B21: peer-reviewed article | C21: Xavier & Maisy | D21: Spain | E21: Nerva; Gravilanes; La Granja | F21: 39.588307 | G21: -4.715337 | H21: 3535 | I21: 25 | J21: plots | K21: plot | L21: 3600m^2 | M21: NR | N21: NR | O21: NR | P21: 2018 | Q21: 2019 | R21: 2018; 2019 | S21: Mediterranean Forests, Woodlands & Scrub | T21: NR | U21: Pinus pinaster; Pinus sylvestris; Pinus pinea | V21: Eutric Cambisols; Cambisols; Leptosols | W21: wildfire | X21: NA | Y21: NA | Z21: wildfire | AA21: NA | AB21: NA | AC21: 2018; 2019 | AD21: soil burn | AE21: NA | AF21: NA | AG21: soil burn severity index | AH21: NA | AI21: NA | AJ21: NA | AK21: Multispectral | AL21: passive | AM21: MSI | AN21: satellite | AO21: Sentinel-2 | AP21: 20 | AQ21: Spectral analysis | AR21: red; nir; swir | AS21: NBR; NDVI; BAIS2; MIRBI | AT21: burn index; vegetation index; burn index; burn index | AU21: NR | AV21: NA | AW21: spectral index layers; differenced spectral index layers | AX21: multispectral image | AY21: mono-temporal/multi-annual | AZ21: fire | BA21: soil degradation; soil erosion susceptibility | BB21: saturated hydraulic conductivity; mean wieight diameter of soil aggregates; soil organic carbon content | BC21: yes | BD21: coefficient of determination; root mean square error | BE21: To use Sentinel-2 spectral indices to assess post-fire alterations in soil properties related to erosion susceptibility | BF21: observational | BG21: To evaluate the ability of Sentinel-2 spectral indices to detect post-fire changes in soil properties linked to erosion susceptibility | BH21: Spectral indices, especially RBR and dMIRBI, show strong potential for assessing soil degradation after fire, but further validation across ecosystems is needed
A22: Fernández-Guisuraga_Marcos_Suárez-Seoane_etal_2022 | B22: peer-reviewed article | C22: Xavier & Maisy | D22: Spain | E22: Sierra de Cabrera Mountains | F22: 42.202716 | G22: -6.444527 | H22: 9940 | I22: 35 | J22: plots | K22: plot | L22: 900m^2 | M22: 900m^2 | N22: 31500m^2 | O22: 3.15 | P22: 2017 | Q22: 2018 | R22: 2017; 2018 | S22: Mediterranean Forests, Woodlands & Scrub | T22: NR | U22: quercus pyrenaica; pinus sylvestis | V22: Leptosols; Cambisols | W22: wildfire | X22: NA | Y22: NA | Z22: wildfire | AA22: NA | AB22: NA | AC22: 2017 | AD22: soil nutrient loss | AE22: NA | AF22: NA | AG22: soil organic carbon content; soil nitrogen content; soil phosphorus content | AH22: NA | AI22: NA | AJ22: NA | AK22: SAR; SAR | AL22: active; active | AM22: C-SAR; PALSAR-2 | AN22: satellite; satellite | AO22: Sentinel-1; ALOS-2 | AP22: 20; 20 | AQ22: SAR backscatter analysis | AR22: C-band;L-band | AS22: radar forest degradation index | AT22: forest defoliation index | AU22: maximum likelihood | AV22: probabilistic | AW22: prediction map of soil properties; plant community classification map | AX22: soil property map | AY22: mono-temporal/multi-annual | AZ22: fire | BA22: soil nutrient loss | BB22: measured soil crabon; measured soil nitrogen; measured soil phosphorus | BC22: yes | BD22: coefficient of determination; root mean squared error | BE22: To use SAR backscatter data to estimate and monitor post-fire changes in soil organic carbon, nitrogen, and phosphorus across a heterogeneous landscape | BF22: before-after | BG22: To evaluate the potential of SAR data to estimate and monitor post-fire changes in soil nutrients across a heterogeneous landscape | BH22: L-band SAR data reliably predicts post-fire soil nutrient dynamics and supports transferable remote sensing-based soil monitoring
A23: French_Kasischke_Bourgeau-Chavez_etal_1996 | B23: peer-reviewed article | C23: Xavier & Maisy | D23: United-States | E23: Interior Alaska | F23: 64.068456 | G23: -144.86821 | H23: NR | I23: 6 | J23: fire scars | K23: fire scar | L23: 1km^2 | M23: 1km^2 | N23: 6km^2 | O23: 600 | P23: 1992 | Q23: 1994 | R23: 1992; 1993; 1994 | S23: Boreal Forests/Taiga | T23: black spruce forests | U23: picea mariana | V23: silt loam; silty clay loam; loam; sandy loam; silty clay with gravel; sandy silt loam with gravel | W23: wildfire | X23: NA | Y23: NA | Z23: wildfire | AA23: NA | AB23: NA | AC23: 1979; 1983; 1987; 1990 | AD23: soil moisture loss | AE23: NA | AF23: NA | AG23: soil water content | AH23: NA | AI23: NA | AJ23: NA | AK23: SAR | AL23: active | AM23: AMI | AN23: satellite | AO23: ERS-1 | AP23: NR | AQ23: SAR backscatter analysis | AR23: C-band | AS23: NR | AT23: NR | AU23: NR | AV23: NA | AW23: SAR backscatter images | AX23: SAR backscatter map | AY23: multi-temporal/mono-annual | AZ23: fire | BA23: soil moisture | BB23: gravimetric soil water content; volumetric soil water content; organic horizon depth; permafrost depth; vegetation composition | BC23: yes | BD23: least squares regression | BE23: To use ERS-1 SAR backscatter imagery to quantify soil water levels in fire-disturbed black spruce forest ecosystems | BF23: observational | BG23: To assess the relationship between ERS-1 SAR backscatter and soil moisture in fire-disturbed boreal forest sites | BH23: ERS-1 SAR imagery can effectively detect soil moisture changes in young boreal forest burns, but its sensitivity decreases as vegetation regrows
A24: Godziek_2024 | B24: peer-reviewed article | C24: Xavier & Maisy | D24: Poland | E24: Polish Western Carpathians | F24: 49.526457 | G24: 19.81544 | H24: 3 | I24: 3 | J24: plots | K24: plot | L24: 1ha | M24: 1ha | N24: 3ha | O24: 3 | P24: 2023 | Q24: 2023 | R24: 2020 | S24: Temperate Conifer Forests | T24: norway spruce forests | U24: Picea abies | V24: NR | W24: windthrow | X24: NA | Y24: NA | Z24: windthrow | AA24: NA | AB24: NA | AC24: 2004; 2009; 2015 | AD24: soil displacement | AE24: NA | AF24: NA | AG24: root plate volume | AH24: NA | AI24: NA | AJ24: NA | AK24: LiDAR | AL24: active | AM24: NR | AN24: airborne | AO24: NR | AP24: 0.25 | AQ24: LiDAR | AR24: NR | AS24: NR | AT24: NR | AU24: threshold-based | AV24: threshold/rule based | AW24: digital terrain model; digital surface model; contour lines; root plate detection map | AX24: digital terrain model; contour lines; root plate detection map | AY24: mono-temporal | AZ24: windthrow | BA24: soil displacement | BB24: root plate dimensions | BC24: yes | BD24: Mann–Whitney U test; Kruskal–Wallis test | BE24: To use LiDAR-derived elevation models to detect root plates and estimate soil displacement caused by tree uprooting | BF24: proof-of-concept | BG24: To develop and validate a LiDAR-based method for detecting root plates and estimating soil displacement caused by tree uprooting | BH24: LiDAR data can effectively detect root plates and estimate biotransport, offering a scalable tool for assessing windthrow-driven soil disturbance in forest ecosystems
A25: Guilinger_Foufoula-Georgiou_Gray_etal_2023 | B25: peer-reviewed article | C25: Xavier & Maisy | D25: United-States | E25: Southern California | F25: 33.718151 | G25: -117.56407 | H25: 9308 | I25: 566 | J25: headwater sub-catchments | K25: watershed | L25: NR | M25: NR | N25: NR | O25: NR | P25: 2018 | Q25: 2019 | R25: 2018; 2020 | S25: Mediterranean Forests, Woodlands & Scrub | T25: california chaparral | U25: NR | V25: NR | W25: wildfire | X25: NA | Y25: NA | Z25: wildfire | AA25: NA | AB25: NA | AC25: 2018 | AD25: soil erosion | AE25: NA | AF25: NA | AG25: elevation change; sediment yield estimates; channel downcutting | AH25: NA | AI25: NA | AJ25: NA | AK25: LiDAR | AL25: active | AM25: NR | AN25: airborne | AO25: NR | AP25: 0.12 | AQ25: LiDAR | AR25: NR | AS25: NDVI; NBR | AT25: vegetation index; burn index | AU25: random forest | AV25: tree-based | AW25: erosion maps; deposition maps; NDVI layer; burn severity layer; orthoimages | AX25: orthomosaic; burn severity map; NDVI map; erosion map; deposition map | AY25: multi-temporal/mono-annual | AZ25: fire | BA25: soil erosion; sediment redistribution | BB25: visual assessment of channels/landslides/slope failure/sheet erosion/ravel deposits/sediment infilling; soil water repellency | BC25: yes | BD25: coefficient of determination; root mean square error; cross-validation | BE25: To use airborne LiDAR differencing to quantify postfire sediment redistribution and erosion in steep headwater catchments. | BF25: observational | BG25: To quantify and predict postfire sediment yield using airborne LiDAR and machine learning | BH25: Airborne LiDAR combined with data-driven modeling improves prediction of postfire erosion in steep catchments and should be applied in other fire-prone regions
A26: Haas_Hagge_Schack-Kirchner_etal_2016 | B26: peer-reviewed article | C26: Xavier & Maisy | D26: Germany | E26: Ravensburg, Germany | F26: 47.897953 | G26: 9.639169 | H26: 0.002 | I26: 6 | J26: plots | K26: plot | L26: 3.6m^2 | M26: 3.6m^2 | N26: 21.6m^2 | O26: 0.002 | P26: NR | Q26: NR | S26: Temperate Broadleaf & Mixed Forests | T26: NR | U26: NR | V26: Stagnic Luvisol | W26: logging | X26: NA | Y26: NA | Z26: harvesting | AA26: NA | AB26: NA | AC26: NR | AD26: soil rutting; soil displacement | AE26: NA | AF26: NA | AG26: rut depth; depression volume; bulk density | AH26: NA | AI26: NA | AJ26: forwarder traffic | AK26: Stereo | AL26: passive | AM26: Nikon 1 AW1 | AN26: ground | AO26: NR | AP26: 0.01 | AQ26: Photogrammetry | AR26: NR | AS26: NR | AT26: NR | AU26: NR | AV26: NA | AW26: digital elevation models | AX26: digital elevation model | AY26: multi-temporal/mono-annual | AZ26: logging | BA26: soil rutting | BB26: bulk density; rut depth; soil moisture | BC26: yes | BD26: NR | BE26: To use photogrammetry to generate high-resolution digital elevation models (DEMs) for assessing rut morphology caused by logging machinery | BF26: experimental | BG26: To compare the effects of different tire configurations on soil rutting using photogrammetry-derived DEMs | BH26: Photogrammetry-derived microtopography can effectively quantify soil damage; wide base tires significantly reduce rutting compared to standard tires and bogie tracks
A27: Heppelmann_Talbot_Antòn-Fernández_etal_2022 | B27: peer-reviewed article | C27: Xavier & Maisy | D27: Norway | E27: Southern Norway | F27: 60.105504 | G27: 9.896874 | H27: 105.3 | I27: 20 | J27: forest stand | K27: forest stand | L27: 0.5 ha | M27: 21.5 ha | N27: 105.3 ha | O27: 105.3 | P27: NR | Q27: NR | S27: Boreal Forests/Taiga | T27: clearcut spruce stands | U27: Picea abies | V27: NR | W27: clearcut | X27: NA | Y27: NA | Z27: harvesting | AA27: NA | AB27: NA | AC27: NR | AD27: soil rutting | AE27: NA | AF27: NA | AG27: rut severity | AH27: NA | AI27: NA | AJ27: NA | AK27: LiDAR; Stereo | AL27: active; passive | AM27: NR; DJI Phantom 4 Pro | AN27: airborne; UAV | AO27: NR; DJI Phantom 4 Pro | AP27: 1; 0.02 | AQ27: Photogrammetry | AR27: NR | AS27: DTW | AT27: topographic moisture index | AU27: NR | AV27: NA | AW27: ortho-mosaics; digital surface models; depth-to-water maps | AX27: orthomosaic; digital terrain model; depth-to-water map | AY27: mono-temporal | AZ27: logging | BA27: soil rutting | BB27: visual classification of rut severity | BC27: yes | BD27: AUC | BE27: To use UAV-based photogrammetry to classify wheel rut severity and evaluate its relationship with depth-to-water predictions | BF27: observational | BG27: To evaluate the predictive power of depth-to-water maps for identifying rut severity in mechanized forest operations | BH27: DTW maps are effective predictors of rut severity, especially in wet areas, but site-specific factors must be considered for accurate planning.
A28: Hoy_French_Turetsky_etal_2008 | B28: peer-reviewed article | C28: Xavier & Maisy | D28: United-States | E28: Interior Alaska | F28: 64.109494 | G28: -144.90261 | H28: 332171 | I28: 55 | J28: plots | K28: plot | L28: 400m^2 | M28: 400m^2 | N28: 22000 | O28: 2.2 | P28: 2005 | Q28: 2006 | R28: 2001; 2002; 2003; 2004 | S28: Boreal Forests/Taiga | T28: alaskan black spruce forest | U28: Picea mariana | V28: NR | W28: wildfire | X28: NA | Y28: NA | Z28: wildfire | AA28: NA | AB28: NA | AC28: 2004 | AD28: soil burn | AE28: NA | AF28: NA | AG28: composite burn index; NBR; depth of surface organic layer | AH28: NA | AI28: NA | AJ28: NA | AK28: Multispectral; Multispectral | AL28: passive; passive | AM28: TM; ETM | AN28: satellite; satellite | AO28: Landsat 5; Landsat 7 | AP28: 30; 30 | AQ28: Spectral analysis; Image differencing | AR28: nir; swir | AS28: NBR; NDVI; SAVI | AT28: burn index; vegetation index; soil adjusted vegetation index | AU28: NR | AV28: NA | AW28: fire severity maps; spectral index layers | AX28: burn severity map; multispectral image | AY28: mono-temporal/multi-annual | AZ28: fire | BA28: soil burn | BB28: composite burn index; organic layer depth | BC28: yes | BD28: coefficient of determination | BE28: To use Landsat-derived spectral indices to assess fire severity in Alaskan black spruce forests | BF28: proof-of-concept | BG28: To test the sensitivity of Landsat-derived spectral indices to ground-based fire severity metrics in Alaskan black spruce forest | BH28: Traditional remote sensing indices like dNBR show limited accuracy in estimating ground-layer fire severity in boreal ecosystems, highlighting the need for improved methods
A29: Hudak_Morgan_Bobbitt_etal_2007 | B29: peer-reviewed article | C29: Xavier & Maisy | D29: United-States | E29: Interior Alaska; Western Montana; Southern California | F29: 63.367934; 47.593407; 34.212507 | G29: -142.124286; -113.856831; -117.767671 | H29: 655000 | I29: 450 | J29: plots | K29: plot | L29: 81m^2 | M29: 81m^2 | N29: 36450m^2 | O29: 3.645 | P29: 2003 | Q29: 2004 | R29: 2001; 2002; 2003 | S29: Boreal Forests/Taiga; Temperate Conifer Forests; Mediterranean Forests, Woodlands & Scrub | T29: mixed conifer; chaparral; black spruce | U29: NR | V29: NR | W29: wildfire | X29: NA | Y29: NA | Z29: wildfire | AA29: NA | AB29: NA | AC29: 2003; 2004 | AD29: soil burn; soil water repellency | AE29: NA | AF29: NA | AG29: fractional cover estimates; mini-disk infiltrometer rate; water drop penetration time; duff moisture content | AH29: NA | AI29: NA | AJ29: NA | AK29: Multispectral | AL29: passive | AM29: TM | AN29: satellite | AO29: Landsat 5 | AP29: 30 | AQ29: Image differencing; Spectral analysis | AR29: red; nir; swir | AS29: NBR; NDVI | AT29: burn index; vegetation index | AU29: threshold-based | AV29: threshold/rule based | AW29: burn severity maps; fractional cover maps | AX29: burn severity map; fractional cover map | AY29: mono-temporal/Multi-annual | AZ29: fire | BA29: soil burn; soil water repellency | BB29: mini-disk infiltrometer rate; water drop penetration time; soil char characteristics; duff moisture content; estimated cover fractions | BC29: yes | BD29: pearson correlation coefficient | BE29: To use Landsat-derived burn severity indices and spectral mixture analysis to assess the relationship between satellite imagery and immediate post-fire effects on vegetation and soil | BF29: observational | BG29: To evaluate how well satellite-derived burn severity indices and fractional cover estimates correspond to immediate post-fire vegetation and soil effects | BH29: Remote sensing indices like NBR and dNBR are useful for rapid assessment of vegetation condition post-fire, but poorly reflect soil burn severity and water repellency
A30: Hudak_Robichaud_Jain_etal_2004 | B30: conference proceedings | C30: Xavier & Maisy | D30: United-States | E30: Western Montana | F30: 46.758324 | G30: -113.95246 | H30: 16644 | I30: 90 | J30: plots | K30: plot | L30: NR | M30: NR | N30: NR | O30: NR | P30: 2003 | Q30: 2003 | R30: 2002; 2003 | S30: Temperate Conifer Forests | T30: mixed conifer | U30: NR | V30: NR | W30: wildfire | X30: NA | Y30: NA | Z30: wildfire | AA30: NA | AB30: NA | AC30: 2003 | AD30: soil burn | AE30: NA | AF30: NA | AG30: burned area reflectance classification; NBR; fractional cover estimates; litter depth; duff depth | AH30: NA | AI30: NA | AJ30: NA | AK30: Multispectral; Multispectral | AL30: passive; passive | AM30: HRVIR; TM | AN30: satellite; satellite | AO30: SPOT-4; Landsat 5 | AP30: 20; 30 | AQ30: Image differencing | AR30: NR | AS30: NBR | AT30: burn index | AU30: threshold-based | AV30: threshold/rule based | AW30: burned area reflectance maps | AX30: multispectral image | AY30: mono-temporal/multi-annual | AZ30: fire | BA30: soil burn | BB30: ash cover; litter depth; duff depth; mineral soil cover; rock cover | BC30: yes | BD30: pearson correlation coefficient | BE30: To use NBR and dNBR indices derived from satellite imagery to map and assess post-fire burn severity for validation against field-based soil and vegetation indicators | BF30: observational | BG30: To evaluate how well satellite-derived burn severity indices (NBR/dNBR) correlate with field-based indicators of soil and vegetation burn severity | BH30: Satellite imagery effectively captures canopy burn severity but is less sensitive to fine-scale soil surface changes, highlighting the need for higher-resolution or hyperspectral data for soil degradation assessment
A31: Hudak_Robichaud_Evans_etal_2004 | B31: conference proceedings | C31: Xavier & Maisy | D31: United-States | E31: Western Montana; Southern California | F31: 47.983457; 34.212507 | G31: -114.324331; -117.767671 | H31: 58057 | I31: 306 | J31: plots | K31: plot | L31: 81m^2 | M31: 81m^2 | N31: 24786m^2 | O31: 2.48 | P31: 2003 | Q31: 2003 | R31: 2002; 2003 | S31: Temperate Conifer Forests; Mediterranean Forests, Woodlands & Scrub | T31: NR | U31: NR | V31: NR | W31: wildfire | X31: NA | Y31: NA | Z31: wildfire | AA31: NA | AB31: NA | AC31: 2003 | AD31: soil burn | AE31: NA | AF31: NA | AG31: NBR; fractional cover estimates; litter depth; canopy cover | AH31: NA | AI31: NA | AJ31: NA | AK31: Multispectral; Multispectral; Multispectral; Multispectral; Multispectral | AL31: passive; passive; passive; passive; passive | AM31: TM; HRVIR; ASTER; MASTER; MODIS | AN31: satellite; satellite; satellite; airborne; satellite | AO31: Landsat 5; SPOT-4; Terra; NR; Terra/Aqua | AP31: 30; 20; 30; 31.5; 250 | AQ31: Image differencing | AR31: nir; swir; red | AS31: NBR; NDVI | AT31: burn index; vegetation index | AU31: threshold-based | AV31: threshold/rule based | AW31: burned area reflectance maps; NBR raster; NCVI raster | AX31: multispectral image; NBR map; NDVI map | AY31: mono-temporal/multi-annual | AZ31: fire | BA31: soil burn | BB31: mineral soil cover; ash cover; char cover; duff/litter edpth; rock cover | BC31: yes | BD31: pearson correlation coefficient | BE31: To use dNBR and NBR indices derived from satellite imagery to assess post-fire burn severity across multiple wildfires | BF31: observational | BG31: To evaluate how well satellite-derived burn severity indices correlate with field-measured post-fire effects | BH31: BARC products are more indicative of post-fire vegetation condition than soil condition, especially in low to moderate severity burns
A32: Kadakci̇ Koca_2023 | B32: peer-reviewed article | C32: Xavier & Maisy | D32: Turkey | E32: Kozağaç | F32: 37.274925 | G32: 28.358135 | H32: 21646 | I32: 50 | J32: plots | K32: plot | L32: 900m^2 | M32: 900m^2 | N32: 36000m^2 | O32: 3.6 | P32: 2021 | Q32: 2021 | R32: 2021 | S32: Mediterranean Forests, Woodlands & Scrub | T32: pine forest | U32: Pinus nigra; Pinus brutia | V32: Calcerous regosols | W32: wildfire | X32: NA | Y32: NA | Z32: wildfire | AA32: NA | AB32: NA | AC32: 2021 | AD32: soil burn | AE32: NA | AF32: NA | AG32: composite burn severity index | AH32: NA | AI32: NA | AJ32: NA | AK32: Multispectral | AL32: passive | AM32: OLI | AN32: satellite | AO32: Landsat 8 | AP32: 30 | AQ32: Spectral analysis; Image differencing | AR32: nir; swir2; red; green; blue | AS32: NBR; NDVI; GOSAVI; NBI | AT32: burn index; vegetation index; adjusted vegetation index; blue index | AU32: statistical clustering | AV32: unsupervised | AW32: burn severity maps; spectral index layers | AX32: burn severity map; multispectral image | AY32: mono-temporal/mono-annual | AZ32: fire | BA32: soil burn severity | BB32: composite burn index | BC32: yes | BD32: classification accuracy; pearson correlation coefficient; silhouette coefficient | BE32: To use bi-temporal Landsat-8 imagery to produce a site-specific burn severity map using spectral indices and statistical clustering | BF32: proof-of-concept | BG32: To develop and validate a flexible, site-specific method for burn severity mapping using bi-temporal Landsat-8 spectral indices | BH32: The clustering-based method effectively classified burn severity and outperformed existing threshold models, especially in heterogeneous Mediterranean pine forests
A33: Kadakci Koca_Küçükuysal_Gül_etal_2024 | B33: peer-reviewed article | C33: Xavier & Maisy | D33: Turkey | E33: Muğla | F33: 37.465861 | G33: 28.404667 | H33: 21646 | I33: 45 | J33: plots | K33: plot | L33: 1m^2 | M33: 1m^2 | N33: 45m^2 | O33: 0.0045 | P33: 2022 | Q33: 2022 | R33: 2021 | S33: Mediterranean Forests, Woodlands & Scrub | T33: NR | U33: Pinus nigra; Pinus brutia | V33: Regosols | W33: wildfire | X33: NA | Y33: NA | Z33: wildfire | AA33: NA | AB33: NA | AC33: 2021 | AD33: soil burn; soil water repellency | AE33: NA | AF33: NA | AG33: soil burn severity; soil physical properties; soil water repellency; NBR | AH33: NA | AI33: NA | AJ33: control sites | AK33: Multispectral | AL33: passive | AM33: OLI | AN33: satellite | AO33: Landsat 8 | AP33: 30 | AQ33: Image differencing | AR33: NR | AS33: dNBR; dNDVI | AT33: burn index; vegetation index | AU33: threshold-based | AV33: threshold/rule based | AW33: dNBR map; dNDVI map; land surface temperature map; soil burn severity map; soil property layers | AX33: NBR map; NDVI map; land surface temperature map; burn severity map; soil property map | AY33: mono-temporal/mono-annual | AZ33: fire | BA33: soil burn severity | BB33: ground cover condition; ash color/depth; soil structure/texture; depth of root charring; water repellency; soil color | BC33: yes | BD33: compatibility rates | BE33: To use differenced spectral indices (dNBR, dNDVI) and land surface temperature (LST) maps to assess and spatially map soil burn severity for evaluating post-fire erosion susceptibility | BF33: proof-of-concept | BG33: To develop an improved soil burn severity mapping method for assessing post-fire erosion susceptibility | BH33: Integrating remote sensing with field and experimental soil data yields more accurate soil burn severity maps, enhancing post-fire erosion risk assessment
A34: Kim_Kim_Ha_etal_2023 | B34: peer-reviewed article | C34: Xavier & Maisy | D34: South Korea | E34: Research forest of Kangwon National University | F34: 37.776222 | G34: 127.82808 | H34: 3 | I34: 1 | J34: site | K34: forest stand | L34: 3ha | M34: 3ha | N34: 3ha | O34: 3 | P34: 2022 | Q34: 2022 | R34: 2022 | S34: Temperate Broadleaf & Mixed Forests | T34: NR | U34: NR | V34: coarse loamy; mixed; typic humudepts | W34: clear-cutting | X34: NA | Y34: NA | Z34: harvesting | AA34: NA | AB34: NA | AC34: 2022 | AD34: soil erosion | AE34: NA | AF34: NA | AG34: elevation change; soil volume displacement | AH34: NA | AI34: NA | AJ34: NA | AK34: Stereo | AL34: passive | AM34: DJI Zenmuse H20T | AN34: UAV | AO34: DJI Matrice 300 RTK | AP34: 0.03 | AQ34: Photogrammetry | AR34: NR | AS34: DSM of Difference (DoD) | AT34: change in elevation | AU34: NR | AV34: NA | AW34: digital surface models; DoD maps; orthomosaic images | AX34: digital terrain mode; orthomosaic | AY34: multi-temporal/mono-annual | AZ34: logging | BA34: soil surface deformation | BB34: soil surface height | BC34: yes | BD34: root mean square error | BE34: To use UAV photogrammetry to detect and monitor soil surface deformation (SSD) following timber harvesting on steep forest slopes | BF34: observational | BG34: To evaluate the feasibility and accuracy of UAV photogrammetry for detecting soil surface deformation after timber harvesting | BH34: UAV photogrammetry can effectively detect erosion and deposition on steep slopes post-harvest, but vegetation growth limits its accuracy over time
A35: Kim_Seo_Woo_etal_2025 | B35: peer-reviewed article | C35: Xavier & Maisy | D35: South Korea | E35: Research forest of Kangwon National University | F35: 37.8385 | G35: 127.83344 | H35: 4 | I35: 12 | J35: plots | K35: plot | L35: NR | M35: NR | N35: NR | O35: NR | P35: 2023 | Q35: 2023 | R35: 2023 | S35: Temperate Broadleaf & Mixed Forests | T35: NR | U35: Larix kaempferi | V35: sand; silt; clay | W35: logging | X35: NA | Y35: NA | Z35: harvesting | AA35: NA | AB35: NA | AC35: 2023 | AD35: soil rutting; soil compaction | AE35: NA | AF35: NA | AG35: rut depth; soil disturbance classification index; bulk density; soil porosity | AH35: NA | AI35: NA | AJ35: machine traffic | AK35: LiDAR; Stereo | AL35: active; passive | AM35: Emesent Hovermap ST; DJI Zenmuse H20T | AN35: ground; UAV | AO35: NR;DJI Matrice 300 RTK | AP35: NR; NR | AQ35: LiDAR; Photogrammetry | AR35: NR | AS35: NR | AT35: NR | AU35: NR | AV35: NA | AW35: digital elevation model; 3D point cloud; soil surface height profiles | AX35: digital elevation model; digital terrain model | AY35: mono-temporal | AZ35: logging | BA35: soil rutting; soil compaction | BB35: rut depth; rut severity assessment; bulk density; soil porosity | BC35: yes | BD35: coefficient of determination; root mean square error; linear regression | BE35: To evaluate the use of LiDAR and UAV photogrammetry techniques for assessing soil disturbance caused by forestry machinery on steep slopes | BF35: experimental | BG35: To evaluate the effectiveness of LiDAR and UAV photogrammetry for detecting soil disturbance caused by forestry machinery on steep slopes. | BH35: Mobile LiDAR accurately detects rut depth, while UAV photogrammetry shows potential for mapping disturbed areas but underestimates rut severity
A36: Kokaly_Rockwell_Haire_etal_2007 | B36: peer-reviewed article | C36: Xavier & Maisy | D36: United-States | E36: Bandelier National Monument | F36: 35.792676 | G36: -106.3717 | H36: 19300 | I36: 77 | J36: plots | K36: plot | L36: 1000m^2 | M36: 1000m^3 | N36: 77000m^2 | O36: 7.7 | P36: 2001 | Q36: 2001 | R36: 2000 | S36: Temperate Conifer Forests | T36: mid-elevation conifer forests | U36: Pinus ponderosa | V36: NR | W36: wildfire | X36: NA | Y36: NA | Z36: wildfire | AA36: NA | AB36: NA | AC36: 2000 | AD36: soil burn | AE36: NA | AF36: NA | AG36: NBR; surface cover estimates; soil type cover estimates | AH36: NA | AI36: NA | AJ36: post-fire rehabilitation | AK36: Hyperspectral | AL36: passive | AM36: AVIRIS | AN36: airborne | AO36: NR | AP36: 2.4 | AQ36: Spectral analysis; Image differencing | AR36: nir; swir | AS36: dNBR | AT36: burn ratio index | AU36: maximum likelihood; threshold-based | AV36: probabilistic; threshold/rule based | AW36: surface cover maps; burn severity maps | AX36: fractional cover map; burn severity map | AY36: mono-temporal/multi-annual | AZ36: fire | BA36: soil burn | BB36: ground char assessment | BC36: yes | BD36: kappa statistic; overall accuracy; spearman's rank correlation | BE36: To use hyperspectral and multispectral remote sensing to map post-fire surface cover and assess burn severity | BF36: before-after | BG36: To evaluate the use of hyperspectral and multispectral remote sensing for mapping post-fire surface cover and assessing burn severity | BH36: Hyperspectral remote sensing provides detailed and accurate post-fire surface cover maps that complement and improve interpretation of multispectral burn severity products
A37: Latterini_Venanzi_Tocci_etal_2020 | B37: conference proceedings | C37: Xavier & Maisy | D37: Italy | E37: Castel Giorgio, Umbria | F37: 42.681675 | G37: 11.978771 | H37: 16 | I37: 40 | J37: plots | K37: plot | L37: 314m^2 | M37: 1256m^2 | N37: 31400m^2 | O37: 3.14 | P37: 2017 | Q37: 2018 | R37: 2018 | S37: Mediterranean Forests, Woodlands & Scrub | T37: coppice forest | U37: Quercus cerris L.; astanea sativa Mill. | V37: NR | W37: logging | X37: NA | Y37: NA | Z37: harvesting | AA37: NA | AB37: NA | AC37: 2017;2018 | AD37: skid trails | AE37: NA | AF37: NA | AG37: visual track detection; skid trail width measurements | AH37: NA | AI37: NA | AJ37: NA | AK37: RGB; Multispectral | AL37: passive; passive | AM37: NR; MSI | AN37: UAV; satellite | AO37: NR; Sentinel-2 | AP37: 0.05; 10 | AQ37: Photo-interpretation | AR37: NR | AS37: NR | AT37: NR | AU37: NR | AV37: NA | AW37: skid trail maps | AX37: skid trail map | AY37: mono-temporal | AZ37: logging | BA37: skidding | BB37: skid trail width; forest road density | BC37: yes | BD37: dependent samples t-test | BE37: To use Sentinel-2 imagery, Google Earth satellite images, and UAV-acquired RGB imagery to evaluate their reliability in detecting and mapping skid trails caused by forest operations | BF37: proof-of-concept | BG37: To assess the accuracy of three remote sensing techniques in identifying skid trails caused by forest machinery | BH37: High-resolution imagery from UAVs and Google Earth shows potential for skid trail detection, but limitations in resolution, coverage, and timing constrain their operational effectiveness
